Workbook

Sheet 30_04_20
A1: 201
D2: Liquid Assests | G2: Read This | J2: Tied Assests
D3: Prod | E3: Where | F3: Who | G3: 43951 | H3: 43920 | J3: Prod | K3: Where | L3: Who | M3: Amount | Q3: At Risk | R3: Not a Risk - Cash
B4: =488+743 -> 1231 | D4: ISA | E4: Ford | F4: JG | G4: 30657 | H4: 28871 | J4: Jenny | M4: 0 | Q4: =G24-R4 -> 266541 | R4: =SUM(G11:G15) -> 236100 | T4: 130 | V4: 102.8 | W4: Share Price
B5: =504+803 -> 1307 | D5: ISA | E5: Ford | F5: MG | G5: 30657 | H5: 28871 | J5: Faye | M5: 22000 | P5: this is 17k + 5K | T5: 71 | V5: 1.125 | W5: Exchange | AE5: NSI | AF5: 100000
D6: FundSmith | G6: 7491 | H6: 6902 | J6: Nik | M6: 5000 | N6: 155K | P6: Med | Q6: =G4+G5+G16+G17+G18 -> 246723 | T6: =T4-T5 -> 59 | AE6: Share | AF6: 85000
C7: * | D7: Hargrevaes Lansdown | G7: 1091 | H7: 887 | P7: High | Q7: =SUM(G6:G10) -> 19818
C8: * | D8: Intractive Investor | G8: 10718 | H8: 9320
C9: * | D9: Bakkovor Now III | G9: 367 | H9: 552
C10: * | D10: Coinbase | G10: 151 | H10: 100 | J10: lister st | M10: 0
D11: Current account - Inv, Currt and Holid | E11: Nat West Invest/Holiday - Not EX, Not Prop, Not Current below 4K | G11: 75000 | H11: =66000+8000 -> 74000 | J11: Phil | M11: 1500 | R11: =14514*2 -> 29028 | AE11: Invest | AF11: 40000
D12: Premium Bonds | E12: Post Office | F12: JG | G12: 50000 | H12: 50000 | J12: House | K12: 2bed | M12: 37000 | AF12: =SUM(AF5:AF11) -> 225000
D13: Premium Bonds | E13: Post Office | F13: BH | G13: 11100 | H13: 10950
D14: Premium Bonds | E14: Post Office | F14: FG | G14: 50000 | H14: 50000 | Q14: 81287
A15: Q3 | B15: Q2 | C15: 2018 | D15: Premium Bonds | E15: Post Office | F15: MG | G15: 50000 | H15: 50000 | J15: House | K15: 3bed | M15: 35000 | Q15: =G4*2 -> 61314
A16: 766 | B16: 766 | C16: 523 | D16: EDSP | E16: Computershare | F16: MG | G16: 72611 | H16: 69937 | J16: Total | M16: =SUM(M4:M15) -> 100500 | N16: 73707 | Q16: =Q14-Q15 -> 19973 | X16: =SUM(A16:A18) -> 1867 | Y16: =X16*V4 -> 191927.6
A17: 504 | B17: 504 | D17: Trading Acocunt | E17: III ( both JG and MG) | F17: MGJG | G17: =23291*2 -> 46582 | H17: =22512+23423 -> 45935
A18: 597 | B18: 555 | C18: 684 | D18: OWN SAP | F18: MG | G18: 66216 | H18: 62398
A19: 2011 | C19: 99 | D19: SAP Shares | E19: 1 free | F19: MG | H19: 33 | J19: SAP Shares | K19: 1 free | N19: 42156 | P19: 37666 | W19: =388*70/1.43 -> 18993.007
A20: 2012 | C20: 96 | D20: SAP Shares | E20: 5 p 3y 3g | F20: MG | H20: 160 | J20: SAP Shares | K20: 5 p 3y 3g | N20: 41791 | P20: 35143
A21: 2013 | C21: 87 | D21: SAP Shares | E21: B3K3G1 | F21: MG | H21: 29 | J21: SAP Shares | K21: B3K3G1 | N21: 42583
M22: =SUM(M19:M21) -> 0
D24: Total | G24: =SUM(G4:G18) -> 502641 | H24: =SUM(H4:H18) -> 488723 | I24: 504894 | K24: =G26-H24 -> 13918 | M24: =M16+M22 -> 100500 | Z24: 1155
Q25: 900 | Z25: 80.13
D26: Potential Balance | G26: =G24 -> 502641 | H26: 493260 | K26: 7773 | AA26: =Z25*Z24 -> 92550.15
D27: Not so liquid | N27: Actual | O27: 31st Dec | P27: 31st Dec | Q27: 31st Dec | R27: 31st Dec | S27: 31st Dec | T27: 31st Dec | Z27: 1.5 | AA27: =AA26/Z27 -> 61700.1
D28: Aston | E28: Sold | G28: 0 | O28: 2015 | P28: 2016 | Q28: 2017 | R28: 2018 | S28: 2019 | T28: 2020 | U28: =T28+1 -> 2021
D29: Golf R | G29: 15000 | N29: Value | O29: 164433.05 | P29: 248589.4 | Q29: 314989.19 | R29: 335945 | S29: 336562 | T29: 374989.19
D30: Motor Bike | G30: 2000 | O30: 0 | P30: 0 | S30: 30000 | T30: 7000
G31: =SUM(G28:G30) -> 17000 | N31: Santandar | O31: 29028
N32: Total | O32: 193461.05 | P32: 248589.4 | Q32: 314989.19 | R32: 335945 | S32: 374989.19 | T32: 381989.19
D33: Less CC Debit | G33: 1600 | P33: 55128.35 | Q33: 66399.786 | R33: =R32-Q32 -> 20955.812
D35: Sub Total | G35: =G26+G31-G33 -> 518041 | N35: Q1 | P35: 282432.89 | Q35: 33843.485 | R35: 8687 | S35: 120736 | Z35: phil | AA35: 1500
N36: Q2 | P36: 294892.7 | Q36: 12459.809 | R36: 5697 | S36: 43735
D37: Tied Assetts | G37: =M24 -> 100500 | N37: Q3 | P37: 310690.69 | Q37: 15797.999 | R37: 37050 | S37: -7000
N38: Q4 | P38: 314989.19 | Q38: 4298.4936 | R38: -31361 | S38: 11634
D39: House | G39: 360000 | Q39: 66399.786 | R39: =SUM(R35:R38) -> 20073 | S39: =SUM(S35:S38) -> 169105
D40: less mortgage | G40: =G39 -> 360000
N41: Budget | O41: 31st Dec | P41: 31st Dec | Q41: 31st Dec | R41: 31st Dec | S41: 31st Dec | T41: 31st Dec | Z41: RN Pension
D42: Nett Worth | G42: =G40+G37+G35 -> 978541 | O42: 2015 | P42: 2016 | Q42: 2017 | R42: 2018 | S42: 2019 | T42: 2020 | Z42: Nissan | AA42: GSR Capital
N43: Base | O43: 105896.15 | P43: 163396.15 | Q43: 193396.15 | R43: 223396.15 | S43: 253396.15 | T43: 283396.15
N44: Save | O44: 30000 | P44: 30000 | Q44: 30000 | R44: 30000 | S44: 30000 | T44: 30000
N45: Extra | O45: 27500
N46: Total | O46: 163396.15 | P46: 193396.15 | Q46: 223396.15 | R46: 253396.15 | S46: 283396.15 | T46: 313396.15
T47: =T46-P32 -> 64806.752

Sheet 29_05_20
A1: 201
D2: Liquid Assests | G2: Read This | J2: Tied Assests
D3: Prod | E3: Where | F3: Who | G3: 43980 | H3: 43951 | J3: Prod | K3: Where | L3: Who | M3: Amount | Q3: At Risk | R3: Not a Risk - Cash
B4: =488+743 -> 1231 | D4: ISA | E4: Ford | F4: JG | G4: 52605 | H4: 30657 | J4: Jenny | M4: 0 | Q4: =G24-R4 -> 329648 | R4: =SUM(G11:G15) -> 199900 | T4: 130 | V4: 102.8 | W4: Share Price
B5: =504+803 -> 1307 | D5: ISA | E5: Ford | F5: MG | G5: 52605 | H5: 30657 | J5: Faye | M5: 22000 | P5: this is 17k + 5K | T5: 71 | V5: 1.125 | W5: Exchange | AE5: NSI | AF5: 100000
D6: FundSmith | G6: 8024 | H6: 7491 | J6: Nik | M6: 5000 | N6: 155K | P6: Med | Q6: =G4+G5+G16+G17+G18 -> 308286 | T6: =T4-T5 -> 59 | AE6: Share | AF6: 85000
C7: * | D7: Hargrevaes Lansdown | G7: 1156 | H7: 1091 | P7: High | Q7: =SUM(G6:G10) -> 21362
C8: * | D8: Intractive Investor | G8: 11606 | H8: 10718
C9: * | D9: Bakkovor Now III | G9: 410 | H9: 367
C10: * | D10: Coinbase | G10: 166 | H10: 151 | J10: lister st | M10: 0
D11: Current account - Inv, Currt and Holid | E11: Nat West Invest/Holiday - Not EX, Not Prop, Not Current below 4K | G11: 38800 | H11: 75000 | J11: Phil | M11: 1500 | R11: =14514*2 -> 29028 | AE11: Invest | AF11: 40000
D12: Premium Bonds | E12: Post Office | F12: JG | G12: 50000 | H12: 50000 | J12: House | K12: 2bed | M12: 37000 | AF12: =SUM(AF5:AF11) -> 225000
D13: Premium Bonds | E13: Post Office | F13: BH | G13: 11100 | H13: 11100
D14: Premium Bonds | E14: Post Office | F14: FG | G14: 50000 | H14: 50000 | Q14: 81287
A15: Q3 | B15: Q2 | C15: 2018 | D15: Premium Bonds | E15: Post Office | F15: MG | G15: 50000 | H15: 50000 | J15: House | K15: 3bed | M15: 35000 | Q15: =G4*2 -> 105210
A16: 766 | B16: 766 | C16: 523 | D16: EDSP | E16: Computershare | F16: MG | G16: 78218 | H16: 72611 | J16: Total | M16: =SUM(M4:M15) -> 100500 | N16: 73707 | Q16: =Q14-Q15 -> -23923 | X16: =SUM(A16:A18) -> 1867 | Y16: =X16*V4 -> 191927.6
A17: 504 | B17: 504 | D17: Trading Acocunt | E17: III ( both JG and MG) | F17: MGJG | G17: =25420+26482 -> 51902 | H17: =23291*2 -> 46582
A18: 597 | B18: 555 | C18: 715 | D18: OWN SAP | F18: MG | G18: 72956 | H18: 66216
A19: 2011 | C19: 99 | D19: SAP Shares | E19: 1 free | F19: MG | H19: 33 | J19: SAP Shares | K19: 1 free | N19: 42156 | P19: 37666 | W19: =388*70/1.43 -> 18993.007
A20: 2012 | C20: 96 | D20: SAP Shares | E20: 5 p 3y 3g | F20: MG | H20: 160 | J20: SAP Shares | K20: 5 p 3y 3g | N20: 41791 | P20: 35143
A21: 2013 | C21: 87 | D21: SAP Shares | E21: B3K3G1 | F21: MG | H21: 29 | J21: SAP Shares | K21: B3K3G1 | N21: 42583
M22: =SUM(M19:M21) -> 0
D24: Total | G24: =SUM(G4:G18) -> 529548 | H24: =SUM(H4:H18) -> 502641 | I24: 504894 | K24: =G26-H24 -> 26907 | M24: =M16+M22 -> 100500 | Z24: 1155
Q25: 900 | Z25: 80.13
D26: Potential Balance | G26: =G24 -> 529548 | H26: 493260 | K26: 7773 | AA26: =Z25*Z24 -> 92550.15
D27: Not so liquid | N27: Actual | O27: 31st Dec | P27: 31st Dec | Q27: 31st Dec | R27: 31st Dec | S27: 31st Dec | T27: 31st Dec | Z27: 1.5 | AA27: =AA26/Z27 -> 61700.1
D28: Aston | E28: Sold | G28: 0 | O28: 2015 | P28: 2016 | Q28: 2017 | R28: 2018 | S28: 2019 | T28: 2020 | U28: =T28+1 -> 2021
D29: Golf R | G29: 15000 | N29: Value | O29: 164433.05 | P29: 248589.4 | Q29: 314989.19 | R29: 335945 | S29: 336562 | T29: 374989.19
D30: Motor Bike | G30: 2000 | O30: 0 | P30: 0 | S30: 30000 | T30: 7000
G31: =SUM(G28:G30) -> 17000 | N31: Santandar | O31: 29028
N32: Total | O32: 193461.05 | P32: 248589.4 | Q32: 314989.19 | R32: 335945 | S32: 374989.19 | T32: 381989.19
D33: Less CC Debit | G33: 1600 | P33: 55128.35 | Q33: 66399.786 | R33: =R32-Q32 -> 20955.812
D35: Sub Total | G35: =G26+G31-G33 -> 544948 | N35: Q1 | P35: 282432.89 | Q35: 33843.485 | R35: 8687 | S35: 120736 | Z35: phil | AA35: 1500
N36: Q2 | P36: 294892.7 | Q36: 12459.809 | R36: 5697 | S36: 43735
D37: Tied Assetts | G37: =M24 -> 100500 | N37: Q3 | P37: 310690.69 | Q37: 15797.999 | R37: 37050 | S37: -7000
N38: Q4 | P38: 314989.19 | Q38: 4298.4936 | R38: -31361 | S38: 11634
D39: House | G39: 360000 | Q39: 66399.786 | R39: =SUM(R35:R38) -> 20073 | S39: =SUM(S35:S38) -> 169105
D40: less mortgage | G40: =G39 -> 360000
N41: Budget | O41: 31st Dec | P41: 31st Dec | Q41: 31st Dec | R41: 31st Dec | S41: 31st Dec | T41: 31st Dec | Z41: RN Pension
D42: Nett Worth | G42: =G40+G37+G35 -> 1005448 | O42: 2015 | P42: 2016 | Q42: 2017 | R42: 2018 | S42: 2019 | T42: 2020 | Z42: Nissan | AA42: GSR Capital
N43: Base | O43: 105896.15 | P43: 163396.15 | Q43: 193396.15 | R43: 223396.15 | S43: 253396.15 | T43: 283396.15
N44: Save | O44: 30000 | P44: 30000 | Q44: 30000 | R44: 30000 | S44: 30000 | T44: 30000
N45: Extra | O45: 27500
N46: Total | O46: 163396.15 | P46: 193396.15 | Q46: 223396.15 | R46: 253396.15 | S46: 283396.15 | T46: 313396.15
T47: =T46-P32 -> 64806.752

Sheet 30_06_20
A1: 201
D2: Liquid Assests | G2: Read This | J2: Tied Assests
D3: Prod | E3: Where | F3: Who | H3: 43980 | J3: Prod | K3: Where | L3: Who | M3: Amount | Q3: At Risk | R3: Not a Risk - Cash
B4: =488+743 -> 1231 | D4: ISA | E4: Ford | F4: JG | G4: 53060 | H4: 30657 | J4: Jenny | M4: 0 | Q4: =G24-R4 -> 355563 | R4: =SUM(G11:G15) -> 185100 | T4: 130 | V4: 102.8 | W4: Share Price
B5: =504+803 -> 1307 | D5: ISA | E5: Ford | F5: MG | G5: 53060 | H5: 30657 | J5: Faye | M5: 22000 | P5: this is 17k + 5K | T5: 71 | V5: 1.125 | W5: Exchange | AE5: NSI | AF5: 100000
D6: FundSmith | G6: 8061 | H6: 7491 | J6: Nik | M6: 5000 | N6: 155K | P6: Med | Q6: =G4+G5+G16+G17+G18 -> 333936 | T6: =T4-T5 -> 59 | AE6: Share | AF6: 85000
C7: * | D7: Hargrevaes Lansdown | G7: 1161 | H7: 1091 | P7: High | Q7: =SUM(G6:G10) -> 21627
C8: * | D8: Intractive Investor | G8: 11861 | H8: 10718
C9: * | D9: Bakkovor Now III | G9: 371 | H9: 367 | J9: Les and Jon | M9: 20000
C10: * | D10: Coinbase | G10: 173 | H10: 151 | J10: lister st | M10: 0
D11: Current account - Inv, Currt and Holid | E11: Nat West Invest/Holiday - Not EX, Not Prop, Not Current below 4K | G11: 23600 | H11: 75000 | J11: Phil | M11: 1500 | R11: =14514*2 -> 29028 | AE11: Invest | AF11: 40000
D12: Premium Bonds | E12: Post Office | F12: JG | G12: 50000 | H12: 50000 | J12: House | K12: 2bed | M12: 37000 | AF12: =SUM(AF5:AF11) -> 225000
D13: Premium Bonds | E13: Post Office | F13: BH | G13: 11500 | H13: 11100
D14: Premium Bonds | E14: Post Office | F14: FG | G14: 50000 | H14: 50000 | Q14: 81287
A15: Q3 | B15: Q2 | C15: 2018 | D15: Premium Bonds | E15: Post Office | F15: MG | G15: 50000 | H15: 50000 | J15: House | K15: 3bed | M15: 35000 | Q15: =G4*2 -> 106120
A16: 766 | B16: 766 | C16: 523 | D16: EDSP | E16: Computershare | F16: MG | G16: 87460 | H16: 72611 | J16: Total | M16: =SUM(M4:M15) -> 120500 | N16: 73707 | Q16: =Q14-Q15 -> -24833 | X16: =SUM(A16:A18) -> 1867 | Y16: =X16*V4 -> 191927.6
A17: 504 | B17: 504 | D17: Trading Acocunt | E17: III ( both JG and MG) | F17: MGJG | G17: =27906+29326 -> 57232 | H17: =23291*2 -> 46582
A18: 597 | B18: 555 | C18: 715 | D18: OWN SAP | F18: MG | G18: 83124 | H18: 66216
A19: 2011 | C19: 99 | D19: SAP Shares | E19: 1 free | F19: MG | H19: 33 | J19: SAP Shares | K19: 1 free | N19: 42156 | P19: 37666 | W19: =388*70/1.43 -> 18993.007
A20: 2012 | C20: 96 | D20: SAP Shares | E20: 5 p 3y 3g | F20: MG | H20: 160 | J20: SAP Shares | K20: 5 p 3y 3g | N20: 41791 | P20: 35143
A21: 2013 | C21: 87 | D21: SAP Shares | E21: B3K3G1 | F21: MG | H21: 29 | J21: SAP Shares | K21: B3K3G1 | N21: 42583
M22: =SUM(M19:M21) -> 0
D24: Total | G24: =SUM(G4:G18) -> 540663 | H24: 529548 | I24: 504894 | K24: =G26-H24 -> 11115 | M24: =M16+M22 -> 120500 | Z24: 1155
Q25: 900 | Z25: 80.13
D26: Potential Balance | G26: =G24 -> 540663 | H26: 493260 | K26: 7773 | AA26: =Z25*Z24 -> 92550.15
D27: Not so liquid | N27: Actual | O27: 31st Dec | P27: 31st Dec | Q27: 31st Dec | R27: 31st Dec | S27: 31st Dec | T27: 31st Dec | Z27: 1.5 | AA27: =AA26/Z27 -> 61700.1
D28: Aston | E28: Sold | G28: 0 | O28: 2015 | P28: 2016 | Q28: 2017 | R28: 2018 | S28: 2019 | T28: 2020 | U28: =T28+1 -> 2021
D29: Golf R | G29: 15000 | N29: Value | O29: 164433.05 | P29: 248589.4 | Q29: 314989.19 | R29: 335945 | S29: 336562 | T29: 374989.19
D30: Motor Bike | G30: 2000 | O30: 0 | P30: 0 | S30: 30000 | T30: 7000
G31: =SUM(G28:G30) -> 17000 | N31: Santandar | O31: 29028
N32: Total | O32: 193461.05 | P32: 248589.4 | Q32: 314989.19 | R32: 335945 | S32: 374989.19 | T32: 381989.19
D33: Less CC Debit | G33: 1600 | P33: 55128.35 | Q33: 66399.786 | R33: =R32-Q32 -> 20955.812
D35: Sub Total | G35: =G26+G31-G33 -> 556063 | N35: Q1 | P35: 282432.89 | Q35: 33843.485 | R35: 8687 | S35: 120736 | Z35: phil | AA35: 1500
N36: Q2 | P36: 294892.7 | Q36: 12459.809 | R36: 5697 | S36: 43735
D37: Tied Assetts | G37: =M24 -> 120500 | N37: Q3 | P37: 310690.69 | Q37: 15797.999 | R37: 37050 | S37: -7000
N38: Q4 | P38: 314989.19 | Q38: 4298.4936 | R38: -31361 | S38: 11634
D39: House | G39: 360000 | Q39: 66399.786 | R39: =SUM(R35:R38) -> 20073 | S39: =SUM(S35:S38) -> 169105
D40: less mortgage | G40: =G39 -> 360000
N41: Budget | O41: 31st Dec | P41: 31st Dec | Q41: 31st Dec | R41: 31st Dec | S41: 31st Dec | T41: 31st Dec | Z41: RN Pension
D42: Nett Worth | G42: =G40+G37+G35 -> 1036563 | O42: 2015 | P42: 2016 | Q42: 2017 | R42: 2018 | S42: 2019 | T42: 2020 | Z42: Nissan | AA42: GSR Capital
N43: Base | O43: 105896.15 | P43: 163396.15 | Q43: 193396.15 | R43: 223396.15 | S43: 253396.15 | T43: 283396.15
N44: Save | O44: 30000 | P44: 30000 | Q44: 30000 | R44: 30000 | S44: 30000 | T44: 30000
N45: Extra | O45: 27500
N46: Total | O46: 163396.15 | P46: 193396.15 | Q46: 223396.15 | R46: 253396.15 | S46: 283396.15 | T46: 313396.15
T47: =T46-P32 -> 64806.752

Sheet 31_07_20
A1: 201
D2: Liquid Assests | G2: Read This | J2: Tied Assests
D3: Prod | E3: Where | F3: Who | G3: 31st July | H3: 30th June | J3: Prod | K3: Where | L3: Who | M3: Amount | Q3: At Risk | R3: Not a Risk - Cash
B4: =488+743 -> 1231 | D4: ISA | E4: Ford | F4: JG | G4: 53648 | H4: 53060 | J4: Jenny | M4: 0 | Q4: =G24-R4 -> 372928 | R4: =SUM(G11:G15) -> 186500 | T4: 130 | V4: 102.8 | W4: Share Price
B5: =504+803 -> 1307 | D5: ISA | E5: Ford | F5: MG | G5: 53648 | H5: 53060 | J5: Faye | M5: 22000 | P5: this is 17k + 5K | T5: 71 | V5: 1.125 | W5: Exchange | AE5: NSI | AF5: 100000
D6: FundSmith | G6: 8126 | H6: 8061 | J6: Nik | M6: 5000 | N6: 155K | P6: Med | Q6: =G4+G5+G16+G17+G18 -> 351686 | T6: =T4-T5 -> 59 | AE6: Share | AF6: 85000
C7: * | D7: Hargrevaes Lansdown | G7: 1138 | H7: 1161 | P7: High | Q7: =SUM(G6:G10) -> 21242
C8: * | D8: Intractive Investor | G8: 11397 | H8: 11861
C9: * | D9: Bakkovor Now III | G9: 336 | H9: 371 | J9: Les and Jon | M9: 20000
C10: * | D10: Coinbase | G10: 245 | H10: 173 | J10: lister st | M10: 0
D11: Current account - Inv, Currt and Holid | E11: Nat West Invest/Holiday - Not EX, Not Prop, Not Current below 4K | G11: 25000 | H11: 23600 | J11: Phil | M11: 1500 | R11: =14514*2 -> 29028 | AE11: Invest | AF11: 40000
D12: Premium Bonds | E12: Post Office | F12: JG | G12: 50000 | H12: 50000 | J12: House | K12: 2bed | M12: 37000 | AF12: =SUM(AF5:AF11) -> 225000
D13: Premium Bonds | E13: Post Office | F13: BH | G13: 11500 | H13: 11500
D14: Premium Bonds | E14: Post Office | F14: FG | G14: 50000 | H14: 50000 | Q14: 81287
A15: Q3 | B15: Q2 | C15: 2018 | D15: Premium Bonds | E15: Post Office | F15: MG | G15: 50000 | H15: 50000 | J15: House | K15: 3bed | M15: 35000 | Q15: =G4*2 -> 107296
A16: 766 | B16: 766 | C16: 523 | D16: EDSP | E16: Computershare | F16: MG | G16: 93204 | H16: 87460 | J16: Total | M16: =SUM(M4:M15) -> 120500 | N16: 73707 | Q16: =Q14-Q15 -> -26009 | X16: =SUM(A16:A18) -> 1867 | Y16: =X16*V4 -> 191927.6
A17: 504 | B17: 504 | D17: Trading Acocunt | E17: III ( both JG and MG) | F17: MGJG | G17: =31181+30000 -> 61181 | H17: =27906+29326 -> 57232
A18: 597 | B18: 555 | C18: 715 | D18: OWN SAP | F18: MG | G18: 90005 | H18: 83124
A19: 2011 | C19: 99 | D19: SAP Shares | E19: 1 free | F19: MG | J19: SAP Shares | K19: 1 free | N19: 42156 | P19: 37666 | W19: =388*70/1.43 -> 18993.007
A20: 2012 | C20: 96 | D20: SAP Shares | E20: 5 p 3y 3g | F20: MG | J20: SAP Shares | K20: 5 p 3y 3g | N20: 41791 | P20: 35143
A21: 2013 | C21: 87 | D21: SAP Shares | E21: B3K3G1 | F21: MG | J21: SAP Shares | K21: B3K3G1 | N21: 42583
M22: =SUM(M19:M21) -> 0
D24: Total | G24: =SUM(G4:G18) -> 559428 | H24: 529548 | I24: 504894 | K24: =G26-H24 -> 29880 | M24: =M16+M22 -> 120500 | Z24: 1155
Q25: 900 | Z25: 80.13
D26: Potential Balance | G26: =G24 -> 559428 | H26: 493260 | K26: 7773 | AA26: =Z25*Z24 -> 92550.15
D27: Not so liquid | N27: Actual | O27: 31st Dec | P27: 31st Dec | Q27: 31st Dec | R27: 31st Dec | S27: 31st Dec | T27: 31st Dec | Z27: 1.5 | AA27: =AA26/Z27 -> 61700.1
D28: Aston | E28: Sold | G28: 0 | O28: 2015 | P28: 2016 | Q28: 2017 | R28: 2018 | S28: 2019 | T28: 2020 | U28: =T28+1 -> 2021
D29: Golf R | G29: 15000 | N29: Value | O29: 164433.05 | P29: 248589.4 | Q29: 314989.19 | R29: 335945 | S29: 336562 | T29: 374989.19
D30: Motor Bike | G30: 2000 | O30: 0 | P30: 0 | S30: 30000 | T30: 7000
G31: =SUM(G28:G30) -> 17000 | N31: Santandar | O31: 29028
N32: Total | O32: 193461.05 | P32: 248589.4 | Q32: 314989.19 | R32: 335945 | S32: 374989.19 | T32: 381989.19
D33: Less CC Debit | G33: 1600 | P33: 55128.35 | Q33: 66399.786 | R33: =R32-Q32 -> 20955.812
D35: Sub Total | G35: =G26+G31-G33 -> 574828 | N35: Q1 | P35: 282432.89 | Q35: 33843.485 | R35: 8687 | S35: 120736 | Z35: phil | AA35: 1500
N36: Q2 | P36: 294892.7 | Q36: 12459.809 | R36: 5697 | S36: 43735
D37: Tied Assetts | G37: =M24 -> 120500 | N37: Q3 | P37: 310690.69 | Q37: 15797.999 | R37: 37050 | S37: -7000
N38: Q4 | P38: 314989.19 | Q38: 4298.4936 | R38: -31361 | S38: 11634
D39: House | G39: 360000 | Q39: 66399.786 | R39: =SUM(R35:R38) -> 20073 | S39: =SUM(S35:S38) -> 169105
D40: less mortgage | G40: =G39 -> 360000
N41: Budget | O41: 31st Dec | P41: 31st Dec | Q41: 31st Dec | R41: 31st Dec | S41: 31st Dec | T41: 31st Dec | Z41: RN Pension
D42: Nett Worth | G42: =G40+G37+G35 -> 1055328 | O42: 2015 | P42: 2016 | Q42: 2017 | R42: 2018 | S42: 2019 | T42: 2020 | Z42: Nissan | AA42: GSR Capital
N43: Base | O43: 105896.15 | P43: 163396.15 | Q43: 193396.15 | R43: 223396.15 | S43: 253396.15 | T43: 283396.15
N44: Save | O44: 30000 | P44: 30000 | Q44: 30000 | R44: 30000 | S44: 30000 | T44: 30000
N45: Extra | O45: 27500
N46: Total | O46: 163396.15 | P46: 193396.15 | Q46: 223396.15 | R46: 253396.15 | S46: 283396.15 | T46: 313396.15
T47: =T46-P32 -> 64806.752

Sheet 31_08_20
A1: 201
D2: Liquid Assests | G2: Read This | J2: Tied Assests
D3: Prod | E3: Where | F3: Who | G3: 31st Aug | H3: 31st July | J3: Prod | K3: Where | L3: Who | M3: Amount | Q3: At Risk | R3: Not a Risk - Cash
B4: =488+743 -> 1231 | D4: ISA | E4: Ford | F4: JG | G4: =33591+22023 -> 55614 | H4: 53648 | J4: Jenny | M4: 0 | Q4: =G24-R4 -> 392474 | R4: =SUM(G11:G15) -> 192000 | T4: 130 | V4: 102.8 | W4: Share Price
B5: =504+803 -> 1307 | D5: ISA | E5: Ford | F5: MG | G5: 55491 | H5: 53648 | J5: Faye | M5: 22000 | P5: this is 17k + 5K | T5: 71 | V5: 1.125 | W5: Exchange | AE5: NSI | AF5: 100000
D6: FundSmith | G6: 8469 | H6: 8126 | J6: Nik | M6: 5000 | N6: 155K | P6: Med | Q6: =G5+#REF!+G16+G17+G18 -> #REF! | T6: =T4-T5 -> 59 | AE6: Share | AF6: 85000
C7: * | D7: Hargrevaes Lansdown | G7: 1193 | H7: 1138 | P7: High | Q7: =SUM(G6:G10) -> 21793
C8: * | D8: Intractive Investor | G8: 11541 | H8: 11397
C9: * | D9: Bakkovor Now III | G9: 312 | H9: 336 | J9: Les and Jon | M9: 20000
C10: * | D10: Coinbase | G10: 278 | H10: 245 | J10: lister st | M10: 0
D11: Current account - Inv, Currt and Holid | E11: Nat West Invest/Holiday - Not EX, Not Prop, Not Current below 4K | G11: 42000 | H11: 25000 | J11: Phil | M11: 1500 | R11: =14514*2 -> 29028 | AE11: Invest | AF11: 40000
D12: Premium Bonds | E12: Post Office | F12: JG | G12: 50000 | H12: 50000 | J12: House | K12: 2bed | M12: 37000 | AF12: =SUM(AF5:AF11) -> 225000
D13: Premium Bonds | E13: Post Office | F13: BH | G13: 0 | H13: 11500
D14: Premium Bonds | E14: Post Office | F14: FG | G14: 50000 | H14: 50000 | Q14: 81287
A15: Q3 | B15: Q2 | C15: 2018 | D15: Premium Bonds | E15: Post Office | F15: MG | G15: 50000 | H15: 50000 | J15: House | K15: 3bed | M15: 35000 | Q15: =G5*2 -> 110982
A16: 766 | B16: 766 | C16: 774 | D16: EDSP | E16: Computershare | F16: MG | G16: 96526 | H16: 93204 | J16: Total | M16: =SUM(M4:M15) -> 120500 | N16: 73707 | Q16: =Q14-Q15 -> -29695 | X16: =SUM(A16:A18) -> 1867 | Y16: =X16*V4 -> 191927.6
A17: 504 | B17: 504 | D17: Trading Acocunt | E17: III ( both JG and MG) | F17: MGJG | G17: =30791+235+32292 -> 63318 | H17: =31181+30000 -> 61181
A18: 597 | B18: 555 | C18: 759 | D18: OWN SAP | F18: MG | G18: 99732 | H18: 90005
A19: 2011 | C19: 99 | D19: SAP Shares | E19: 1 free | F19: MG | J19: SAP Shares | K19: 1 free | N19: 42156 | P19: 37666 | W19: =388*70/1.43 -> 18993.007
A20: 2012 | C20: 96 | D20: SAP Shares | E20: 5 p 3y 3g | F20: MG | J20: SAP Shares | K20: 5 p 3y 3g | N20: 41791 | P20: 35143
A21: 2013 | C21: 87 | D21: SAP Shares | E21: B3K3G1 | F21: MG | J21: SAP Shares | K21: B3K3G1 | N21: 42583
M22: =SUM(M19:M21) -> 0
D24: Total | G24: =SUM(G4:G18) -> 584474 | H24: =SUM(H4:H18) -> 559428 | I24: 504894 | K24: =G26-H24 -> 25046 | M24: =M16+M22 -> 120500 | Z24: 1155
Q25: 900 | Z25: 80.13
D26: Potential Balance | G26: =G24 -> 584474 | H26: 493260 | I26: =G24-H24 -> 25046 | K26: 7773 | AA26: =Z25*Z24 -> 92550.15
D27: Not so liquid | N27: Actual | O27: 31st Dec | P27: 31st Dec | Q27: 31st Dec | R27: 31st Dec | S27: 31st Dec | T27: 31st Dec | Z27: 1.5 | AA27: =AA26/Z27 -> 61700.1
D28: Aston | E28: Sold | G28: 0 | O28: 2015 | P28: 2016 | Q28: 2017 | R28: 2018 | S28: 2019 | T28: 2020 | U28: =T28+1 -> 2021
D29: Golf R | G29: 15000 | N29: Value | O29: 164433.05 | P29: 248589.4 | Q29: 314989.19 | R29: 335945 | S29: 336562 | T29: 374989.19
D30: Motor Bike | G30: 2000 | O30: 0 | P30: 0 | S30: 30000 | T30: 7000
G31: =SUM(G28:G30) -> 17000 | N31: Santandar | O31: 29028
N32: Total | O32: 193461.05 | P32: 248589.4 | Q32: 314989.19 | R32: 335945 | S32: 374989.19 | T32: 381989.19
D33: Less CC Debit | G33: 1600 | P33: 55128.35 | Q33: 66399.786 | R33: =R32-Q32 -> 20955.812
D35: Sub Total | G35: =G26+G31-G33 -> 599874 | N35: Q1 | P35: 282432.89 | Q35: 33843.485 | R35: 8687 | S35: 120736 | Z35: phil | AA35: 1500
N36: Q2 | P36: 294892.7 | Q36: 12459.809 | R36: 5697 | S36: 43735
D37: Tied Assetts | G37: =M24 -> 120500 | N37: Q3 | P37: 310690.69 | Q37: 15797.999 | R37: 37050 | S37: -7000
N38: Q4 | P38: 314989.19 | Q38: 4298.4936 | R38: -31361 | S38: 11634
D39: House | G39: 360000 | Q39: 66399.786 | R39: =SUM(R35:R38) -> 20073 | S39: =SUM(S35:S38) -> 169105
D40: less mortgage | G40: =G39 -> 360000
N41: Budget | O41: 31st Dec | P41: 31st Dec | Q41: 31st Dec | R41: 31st Dec | S41: 31st Dec | T41: 31st Dec | Z41: RN Pension
D42: Nett Worth | G42: =G40+G37+G35 -> 1080374 | O42: 2015 | P42: 2016 | Q42: 2017 | R42: 2018 | S42: 2019 | T42: 2020 | Z42: Nissan | AA42: GSR Capital
N43: Base | O43: 105896.15 | P43: 163396.15 | Q43: 193396.15 | R43: 223396.15 | S43: 253396.15 | T43: 283396.15
N44: Save | O44: 30000 | P44: 30000 | Q44: 30000 | R44: 30000 | S44: 30000 | T44: 30000
N45: Extra | O45: 27500
N46: Total | O46: 163396.15 | P46: 193396.15 | Q46: 223396.15 | R46: 253396.15 | S46: 283396.15 | T46: 313396.15
T47: =T46-P32 -> 64806.752

Sheet 01_10_20
A1: 201
D2: Liquid Assests | G2: Read This | J2: Tied Assests
D3: Prod | E3: Where | F3: Who | G3: 1st October | H3: 31st Aug | J3: Prod | K3: Where | L3: Who | M3: Amount | Q3: At Risk | R3: Not a Risk - Cash
B4: =488+743 -> 1231 | D4: ISA | E4: Ford | F4: JG | G4: 55221 | H4: =33591+22023 -> 55614 | J4: Jenny | M4: 0 | Q4: =G24-R4 -> 382859.99 | R4: =SUM(G11:G15) -> 192000 | T4: 130 | V4: 102.8 | W4: Share Price
B5: =504+803 -> 1307 | D5: ISA | E5: Ford | F5: MG | G5: 55221 | H5: 55491 | J5: Faye | M5: 22000 | P5: this is 17k + 5K | T5: 71 | V5: 1.125 | W5: Exchange | AE5: NSI | AF5: 100000
D6: FundSmith | G6: 8580 | H6: 8469 | J6: Nik | M6: 5000 | N6: 155K | P6: Med | Q6: =#REF!+#REF!+G16+G17+G18 -> #REF! | T6: =T4-T5 -> 59 | AE6: Share | AF6: 85000
C7: * | D7: Hargrevaes Lansdown | G7: 1348 | H7: 1193 | P7: High | Q7: =SUM(G6:G10) -> 22076
C8: * | D8: Intractive Investor | G8: 11545 | H8: 11541
C9: * | D9: Bakkovor Now III | G9: 343 | H9: 312 | J9: Les and Jon | M9: 20000
C10: * | D10: Coinbase | G10: 260 | H10: 278 | J10: lister st | M10: 0
D11: Current account - Inv, Currt and Holid | E11: Nat West Invest/Holiday - Not EX, Not Prop, Not Current below 4K | G11: 42000 | H11: 42000 | J11: Phil | M11: 1500 | R11: =14514*2 -> 29028 | AE11: Invest | AF11: 40000
D12: Premium Bonds | E12: Post Office | F12: JG | G12: 50000 | H12: 50000 | J12: House | K12: 2bed | M12: 38000 | AF12: =SUM(AF5:AF11) -> 225000
D13: Premium Bonds | E13: Post Office | F13: BH | G13: 0 | H13: 0
D14: Premium Bonds | E14: Post Office | F14: FG | G14: 50000 | H14: 50000 | Q14: 81287
A15: Q3 | B15: Q2 | C15: 2018 | D15: Premium Bonds | E15: Post Office | F15: MG | G15: 50000 | H15: 50000 | J15: House | K15: 3bed | M15: 36000 | Q15: =#REF!*2 -> #REF!
A16: 766 | B16: 766 | C16: 774 | D16: EDSP | E16: Computershare | F16: MG | G16: 94346.65 | H16: 96526 | J16: Total | M16: =SUM(M4:M15) -> 122500 | N16: 73707 | Q16: =Q14-Q15 -> #REF! | X16: =SUM(A16:A18) -> 1867 | Y16: =X16*V4 -> 191927.6
A17: 504 | B17: 504 | D17: Trading Acocunt | E17: III ( both JG and MG) | F17: MGJG | G17: =231+30104+31578 -> 61913 | H17: =30791+235+32292 -> 63318
A18: 597 | B18: 555 | C18: 772 | D18: OWN SAP | F18: MG | G18: 94082.34 | H18: 99732
A19: 2011 | C19: 99 | D19: SAP Shares | E19: 1 free | F19: MG | J19: SAP Shares | K19: 1 free | N19: 42156 | P19: 37666 | W19: =388*70/1.43 -> 18993.007
A20: 2012 | C20: 96 | D20: SAP Shares | E20: 5 p 3y 3g | F20: MG | J20: SAP Shares | K20: 5 p 3y 3g | N20: 41791 | P20: 35143
A21: 2013 | C21: 87 | D21: SAP Shares | E21: B3K3G1 | F21: MG | J21: SAP Shares | K21: B3K3G1 | N21: 42583
M22: =SUM(M19:M21) -> 0
D24: Total | G24: =SUM(G4:G18) -> 574859.99 | H24: =SUM(H4:H18) -> 584474 | I24: 504894 | K24: =G26-H24 -> -9614.01 | M24: =M16+M22 -> 122500 | Z24: 1155
Q25: 900 | Z25: 80.13
D26: Potential Balance | G26: =G24 -> 574859.99 | H26: 584474 | I26: =G24-H24 -> -9614.01 | K26: 7773 | AA26: =Z25*Z24 -> 92550.15
D27: Not so liquid | N27: Actual | O27: 31st Dec | P27: 31st Dec | Q27: 31st Dec | R27: 31st Dec | S27: 31st Dec | T27: 31st Dec | Z27: 1.5 | AA27: =AA26/Z27 -> 61700.1
D28: Aston | E28: Sold | G28: 0 | O28: 2015 | P28: 2016 | Q28: 2017 | R28: 2018 | S28: 2019 | T28: 2020 | U28: =T28+1 -> 2021
D29: Golf R | G29: 15000 | N29: Value | O29: 164433.05 | P29: 248589.4 | Q29: 314989.19 | R29: 335945 | S29: 336562 | T29: 374989.19
D30: Motor Bike | G30: 2000 | O30: 0 | P30: 0 | S30: 30000 | T30: 7000
G31: =SUM(G28:G30) -> 17000 | N31: Santandar | O31: 29028
N32: Total | O32: 193461.05 | P32: 248589.4 | Q32: 314989.19 | R32: 335945 | S32: 374989.19 | T32: 381989.19
D33: Less CC Debit | G33: 1600 | P33: 55128.35 | Q33: 66399.786 | R33: =R32-Q32 -> 20955.812
D35: Sub Total | G35: =G26+G31-G33 -> 590259.99 | N35: Q1 | P35: 282432.89 | Q35: 33843.485 | R35: 8687 | S35: 120736 | Z35: phil | AA35: 1500
N36: Q2 | P36: 294892.7 | Q36: 12459.809 | R36: 5697 | S36: 43735
D37: Tied Assetts | G37: =M24 -> 122500 | N37: Q3 | P37: 310690.69 | Q37: 15797.999 | R37: 37050 | S37: -7000
N38: Q4 | P38: 314989.19 | Q38: 4298.4936 | R38: -31361 | S38: 11634
D39: House | G39: 360000 | Q39: 66399.786 | R39: =SUM(R35:R38) -> 20073 | S39: =SUM(S35:S38) -> 169105
D40: less mortgage | G40: =G39 -> 360000
N41: Budget | O41: 31st Dec | P41: 31st Dec | Q41: 31st Dec | R41: 31st Dec | S41: 31st Dec | T41: 31st Dec | Z41: RN Pension
D42: Nett Worth | G42: =G40+G37+G35 -> 1072760 | O42: 2015 | P42: 2016 | Q42: 2017 | R42: 2018 | S42: 2019 | T42: 2020 | Z42: Nissan | AA42: GSR Capital
N43: Base | O43: 105896.15 | P43: 163396.15 | Q43: 193396.15 | R43: 223396.15 | S43: 253396.15 | T43: 283396.15
N44: Save | O44: 30000 | P44: 30000 | Q44: 30000 | R44: 30000 | S44: 30000 | T44: 30000
N45: Extra | O45: 27500
N46: Total | O46: 163396.15 | P46: 193396.15 | Q46: 223396.15 | R46: 253396.15 | S46: 283396.15 | T46: 313396.15
T47: =T46-P32 -> 64806.752

Sheet 30-10-20
A1: 201
D2: Liquid Assests | G2: Read This | J2: Tied Assests
D3: Prod | E3: Where | F3: Who | G3: 44134 | H3: 1st October | J3: Prod | K3: Where | L3: Who | M3: Amount | Q3: At Risk | R3: Not a Risk - Cash
B4: =488+743 -> 1231 | D4: ISA | E4: Ford | F4: JG | G4: =32582+21348 -> 53930 | H4: 55221 | J4: Jenny | M4: 0 | Q4: =G24-R4 -> 300299 | R4: =SUM(G11:G15) -> 193427 | T4: 130 | V4: 102.8 | W4: Share Price
B5: =504+803 -> 1307 | D5: ISA | E5: Ford | F5: MG | G5: 53930 | H5: 55221 | J5: Faye | M5: 22000 | P5: this is 17k + 5K | T5: 71 | V5: 1.125 | W5: Exchange | AE5: NSI | AF5: 100000
D6: FundSmith | G6: 8307 | H6: 8580 | J6: Nik | M6: 5000 | N6: 155K | P6: Med | Q6: =#REF!+#REF!+G16+G17+G18 -> #REF! | T6: =T4-T5 -> 59 | AE6: Share | AF6: 85000
C7: * | D7: Hargrevaes Lansdown | G7: 1346 | H7: 1348 | P7: High | Q7: =SUM(G6:G10) -> 22260
C8: * | D8: Intractive Investor | G8: 12020 | H8: 11545
C9: * | D9: Bakkovor Now III | G9: 310 | H9: 343 | J9: Les and Jon | M9: 20000
C10: * | D10: Coinbase | G10: 277 | H10: 260 | J10: lister st | M10: 0
D11: Current account - Inv, Currt and Holid | E11: Nat West Invest/Holiday - Not EX, Not Prop, Not Current below 4K | G11: 43427 | H11: 42000 | J11: Phil | M11: 1500 | R11: =14514*2 -> 29028 | AE11: Invest | AF11: 40000
D12: Premium Bonds | E12: Post Office | F12: JG | G12: 50000 | H12: 50000 | J12: House | K12: 2bed | M12: 38000 | AF12: =SUM(AF5:AF11) -> 225000
D13: Premium Bonds | E13: Post Office | F13: BH | H13: 0
D14: Premium Bonds | E14: Post Office | F14: FG | G14: 50000 | H14: 50000 | Q14: 81287
A15: Q3 | B15: Q2 | C15: 2018 | D15: Premium Bonds | E15: Post Office | F15: MG | G15: 50000 | H15: 50000 | J15: House | K15: 3bed | M15: 36000 | Q15: =#REF!*2 -> #REF!
A16: 766 | B16: 766 | C16: 774 | D16: EDSP | E16: Computershare | F16: MG | G16: 63712 | H16: 94346.65 | J16: Total | M16: =SUM(M4:M15) -> 122500 | N16: 73707 | Q16: =Q14-Q15 -> #REF! | X16: =SUM(A16:A18) -> 1867 | Y16: =X16*V4 -> 191927.6
A17: 504 | B17: 504 | D17: Trading Acocunt | E17: III ( both JG and MG) | F17: MGJG | G17: =20336+206+21377 -> 41919 | H17: =231+30104+31578 -> 61913
A18: 597 | B18: 555 | C18: 772 | D18: OWN SAP | F18: MG | G18: 64548 | H18: 94082.34
A19: 2011 | C19: 99 | D19: SAP Shares | E19: 1 free | F19: MG | J19: SAP Shares | K19: 1 free | N19: 42156 | P19: 37666 | W19: =388*70/1.43 -> 18993.007
A20: 2012 | C20: 96 | D20: SAP Shares | E20: 5 p 3y 3g | F20: MG | J20: SAP Shares | K20: 5 p 3y 3g | N20: 41791 | P20: 35143
A21: 2013 | C21: 87 | D21: SAP Shares | E21: B3K3G1 | F21: MG | J21: SAP Shares | K21: B3K3G1 | N21: 42583
M22: =SUM(M19:M21) -> 0
D24: Total | G24: =SUM(G4:G18) -> 493726 | H24: =SUM(H4:H18) -> 574859.99 | I24: 504894 | K24: =G26-H24 -> -81133.99 | M24: =M16+M22 -> 122500 | Z24: 1155
Q25: 900 | Z25: 80.13
D26: Potential Balance | G26: =G24 -> 493726 | H26: 584474 | I26: =G24-H24 -> -81133.99 | K26: 7773 | AA26: =Z25*Z24 -> 92550.15
D27: Not so liquid | N27: Actual | O27: 31st Dec | P27: 31st Dec | Q27: 31st Dec | R27: 31st Dec | S27: 31st Dec | T27: 31st Dec | Z27: 1.5 | AA27: =AA26/Z27 -> 61700.1
D28: Aston | E28: Sold | G28: 0 | O28: 2015 | P28: 2016 | Q28: 2017 | R28: 2018 | S28: 2019 | T28: 2020 | U28: =T28+1 -> 2021
D29: Golf R | G29: 15000 | N29: Value | O29: 164433.05 | P29: 248589.4 | Q29: 314989.19 | R29: 335945 | S29: 336562 | T29: 374989.19
D30: Motor Bike | G30: 2000 | O30: 0 | P30: 0 | S30: 30000 | T30: 7000
G31: =SUM(G28:G30) -> 17000 | N31: Santandar | O31: 29028
N32: Total | O32: 193461.05 | P32: 248589.4 | Q32: 314989.19 | R32: 335945 | S32: 374989.19 | T32: 381989.19
D33: Less CC Debit | G33: 1600 | P33: 55128.35 | Q33: 66399.786 | R33: =R32-Q32 -> 20955.812
D35: Sub Total | G35: =G26+G31-G33 -> 509126 | N35: Q1 | P35: 282432.89 | Q35: 33843.485 | R35: 8687 | S35: 120736 | Z35: phil | AA35: 1500
N36: Q2 | P36: 294892.7 | Q36: 12459.809 | R36: 5697 | S36: 43735
D37: Tied Assetts | G37: =M24 -> 122500 | N37: Q3 | P37: 310690.69 | Q37: 15797.999 | R37: 37050 | S37: -7000
N38: Q4 | P38: 314989.19 | Q38: 4298.4936 | R38: -31361 | S38: 11634
D39: House | G39: 360000 | Q39: 66399.786 | R39: =SUM(R35:R38) -> 20073 | S39: =SUM(S35:S38) -> 169105
D40: less mortgage | G40: =G39 -> 360000
N41: Budget | O41: 31st Dec | P41: 31st Dec | Q41: 31st Dec | R41: 31st Dec | S41: 31st Dec | T41: 31st Dec | Z41: RN Pension
D42: Nett Worth | G42: =G40+G37+G35 -> 991626 | O42: 2015 | P42: 2016 | Q42: 2017 | R42: 2018 | S42: 2019 | T42: 2020 | Z42: Nissan | AA42: GSR Capital
N43: Base | O43: 105896.15 | P43: 163396.15 | Q43: 193396.15 | R43: 223396.15 | S43: 253396.15 | T43: 283396.15
N44: Save | O44: 30000 | P44: 30000 | Q44: 30000 | R44: 30000 | S44: 30000 | T44: 30000
N45: Extra | O45: 27500
N46: Total | O46: 163396.15 | P46: 193396.15 | Q46: 223396.15 | R46: 253396.15 | S46: 283396.15 | T46: 313396.15
T47: =T46-P32 -> 64806.752

Sheet 30-11-20
A1: 201
D2: Liquid Assests | G2: Read This | J2: Tied Assests
D3: Prod | E3: Where | F3: Who | G3: 44165 | H3: 44134 | J3: Prod | K3: Where | L3: Who | M3: Amount | Q3: At Risk | R3: Not a Risk - Cash
B4: =488+743 -> 1231 | D4: ISA | E4: Ford | F4: JG | G4: 57186 | H4: =32582+21348 -> 53930 | J4: Jenny | M4: 0 | Q4: =G24-R4 -> 333420 | R4: =SUM(G11:G15) -> 185700 | T4: 130 | V4: 102.8 | W4: Share Price
B5: =504+803 -> 1307 | D5: ISA | E5: Ford | F5: MG | G5: 57186 | H5: 53930 | J5: Faye | M5: 22000 | P5: this is 17k + 5K | T5: 71 | V5: 1.125 | W5: Exchange | AE5: NSI | AF5: 100000
D6: FundSmith | G6: 8712 | H6: 8307 | J6: Nik | M6: 5000 | N6: 155K | P6: Med | Q6: =#REF!+#REF!+G16+G17+G18 -> #REF! | T6: =T4-T5 -> 59 | AE6: Share | AF6: 85000
C7: * | D7: Hargrevaes Lansdown | G7: 1488 | H7: 1346 | P7: High | Q7: =SUM(G6:G10) -> 28688
C8: * | D8: Intractive Investor | G8: 15053 | H8: 12020
C9: * | D9: Bakkovor Now III | G9: 435 | H9: 310 | J9: Les and Jon | M9: 20000
C10: * | D10: Now CfD | G10: 3000 | H10: 277 | J10: lister st | M10: 0
D11: Current account - Inv, Currt and Holid | E11: Nat West Invest/Holiday - Not EX, Not Prop, Not Current below 4K | G11: 35700 | H11: 43427 | J11: Phil | M11: 1500 | R11: =14514*2 -> 29028 | AE11: Invest | AF11: 40000
D12: Premium Bonds | E12: Post Office | F12: JG | G12: 50000 | H12: 50000 | J12: House | K12: 2bed | M12: 38000 | AF12: =SUM(AF5:AF11) -> 225000
D13: Premium Bonds | E13: Post Office | F13: BH
D14: Premium Bonds | E14: Post Office | F14: FG | G14: 50000 | H14: 50000 | Q14: 81287
A15: Q3 | B15: Q2 | C15: 2018 | D15: Premium Bonds | E15: Post Office | F15: MG | G15: 50000 | H15: 50000 | J15: House | K15: 3bed | M15: 36000 | Q15: =#REF!*2 -> #REF!
A16: 766 | B16: 766 | C16: 774 | D16: EDSP | E16: Computershare | F16: MG | G16: 70709 | H16: 63712 | J16: Total | M16: =SUM(M4:M15) -> 122500 | N16: 73707 | Q16: =Q14-Q15 -> #REF! | X16: =SUM(A16:A18) -> 1867 | Y16: =X16*V4 -> 191927.6
A17: 504 | B17: 504 | D17: Trading Acocunt | E17: III ( both JG and MG) | F17: MGJG | G17: =(23229-G9)+23723 -> 46517 | H17: =20336+206+21377 -> 41919
A18: 597 | B18: 555 | C18: 800 | D18: OWN SAP | F18: MG | G18: 73134 | H18: 64548
A19: 2011 | C19: 99 | D19: SAP Shares | E19: 1 free | F19: MG | J19: SAP Shares | K19: 1 free | N19: 42156 | P19: 37666 | W19: =388*70/1.43 -> 18993.007
A20: 2012 | C20: 96 | D20: SAP Shares | E20: 5 p 3y 3g | F20: MG | J20: SAP Shares | K20: 5 p 3y 3g | N20: 41791 | P20: 35143
A21: 2013 | C21: 87 | D21: SAP Shares | E21: B3K3G1 | F21: MG | J21: SAP Shares | K21: B3K3G1 | N21: 42583
M22: =SUM(M19:M21) -> 0
D24: Total | G24: =SUM(G4:G18) -> 519120 | H24: =SUM(H4:H18) -> 493726 | I24: 504894 | K24: =G26-H24 -> 25394 | M24: =M16+M22 -> 122500 | Z24: 1155
Q25: 900 | Z25: 80.13
D26: Potential Balance | G26: =G24 -> 519120 | H26: 584474 | I26: =G24-H24 -> 25394 | K26: 7773 | AA26: =Z25*Z24 -> 92550.15
D27: Not so liquid | N27: Actual | O27: 31st Dec | P27: 31st Dec | Q27: 31st Dec | R27: 31st Dec | S27: 31st Dec | T27: 31st Dec | Z27: 1.5 | AA27: =AA26/Z27 -> 61700.1
D28: Aston | E28: Sold | G28: 0 | O28: 2015 | P28: 2016 | Q28: 2017 | R28: 2018 | S28: 2019 | T28: 2020 | U28: =T28+1 -> 2021
D29: Golf R | G29: 15000 | N29: Value | O29: 164433.05 | P29: 248589.4 | Q29: 314989.19 | R29: 335945 | S29: 336562 | T29: 374989.19
D30: Motor Bike | G30: 2000 | O30: 0 | P30: 0 | S30: 30000 | T30: 7000
G31: =SUM(G28:G30) -> 17000 | N31: Santandar | O31: 29028
N32: Total | O32: 193461.05 | P32: 248589.4 | Q32: 314989.19 | R32: 335945 | S32: 374989.19 | T32: 381989.19
D33: Less CC Debit | G33: 1600 | P33: 55128.35 | Q33: 66399.786 | R33: =R32-Q32 -> 20955.812
D35: Sub Total | G35: =G26+G31-G33 -> 534520 | N35: Q1 | P35: 282432.89 | Q35: 33843.485 | R35: 8687 | S35: 120736 | Z35: phil | AA35: 1500
N36: Q2 | P36: 294892.7 | Q36: 12459.809 | R36: 5697 | S36: 43735
D37: Tied Assetts | G37: =M24 -> 122500 | N37: Q3 | P37: 310690.69 | Q37: 15797.999 | R37: 37050 | S37: -7000
N38: Q4 | P38: 314989.19 | Q38: 4298.4936 | R38: -31361 | S38: 11634
D39: House | G39: 360000 | Q39: 66399.786 | R39: =SUM(R35:R38) -> 20073 | S39: =SUM(S35:S38) -> 169105
D40: less mortgage | G40: =G39 -> 360000
N41: Budget | O41: 31st Dec | P41: 31st Dec | Q41: 31st Dec | R41: 31st Dec | S41: 31st Dec | T41: 31st Dec | Z41: RN Pension
D42: Nett Worth | G42: =G40+G37+G35 -> 1017020 | O42: 2015 | P42: 2016 | Q42: 2017 | R42: 2018 | S42: 2019 | T42: 2020 | Z42: Nissan | AA42: GSR Capital
N43: Base | O43: 105896.15 | P43: 163396.15 | Q43: 193396.15 | R43: 223396.15 | S43: 253396.15 | T43: 283396.15
N44: Save | O44: 30000 | P44: 30000 | Q44: 30000 | R44: 30000 | S44: 30000 | T44: 30000
N45: Extra | O45: 27500
N46: Total | O46: 163396.15 | P46: 193396.15 | Q46: 223396.15 | R46: 253396.15 | S46: 283396.15 | T46: 313396.15
T47: =T46-P32 -> 64806.752

Sheet 31-12-20
A1: 201
D2: Liquid Assests | G2: Read This | J2: Tied Assests
D3: Prod | E3: Where | F3: Who | G3: 31/21/2020 | H3: 44165 | J3: Prod | K3: Where | L3: Who | M3: Amount | Q3: At Risk | R3: Not a Risk - Cash
B4: =488+743 -> 1231 | D4: ISA | E4: Ford | F4: JG | G4: 58971 | H4: 57186 | J4: Family Loans | Q4: =G24-R4 -> 352798 | R4: =SUM(G11:G15) -> 183948 | T4: 130 | V4: 102.8 | W4: Share Price
B5: =504+803 -> 1307 | D5: ISA | E5: Ford | F5: MG | G5: 58971 | H5: 57186 | J5: Faye | M5: 22000 | P5: this is 17k + 5K | T5: 71 | V5: 1.125 | W5: Exchange | AE5: NSI | AF5: 100000
D6: FundSmith | G6: 8862 | H6: 8712 | J6: Nik | M6: 5000 | N6: 155K | P6: Med | Q6: =#REF!+#REF!+G16+G17+G18 -> #REF! | T6: =T4-T5 -> 59 | AE6: Share | AF6: 85000
C7: * | D7: Hargrevaes Lansdown | G7: 1439 | H7: 1488 | J7: Les and Jon | M7: 20000 | P7: High | Q7: =SUM(G6:G10) -> 31952
C8: * | D8: Intractive Investor | G8: 19009 | H8: 15053 | J8: Phil | M8: 1500
C9: * | D9: Bakkovor Now III | G9: 426 | H9: 435 | M9: =SUM(M5:M8) -> 48500
C10: * | D10: Now CfD | G10: 2216 | H10: 3000
D11: Current account - Inv, Currt and Holid | E11: Nat West Invest/Holiday - Not EX, Not Prop, Not Current below 4K | G11: 33948 | H11: 35700 | R11: =14514*2 -> 29028 | AE11: Invest | AF11: 40000
D12: Premium Bonds | E12: Post Office | F12: JG | G12: 50000 | H12: 50000 | AF12: =SUM(AF5:AF11) -> 225000
D13: Premium Bonds | E13: Post Office | F13: BH | J13: Rented Properties
D14: Premium Bonds | E14: Post Office | F14: FG | G14: 50000 | H14: 50000 | J14: House | K14: 2bed | M14: 38000 | Q14: 81287
A15: Q3 | B15: Q2 | C15: 2018 | D15: Premium Bonds | E15: Post Office | F15: MG | G15: 50000 | H15: 50000 | J15: House | K15: 3bed | M15: 36000 | Q15: =#REF!*2 -> #REF!
A16: 766 | B16: 766 | C16: 774 | D16: EDSP | E16: Computershare | F16: MG | G16: 74852 | H16: 70709 | J16: Total | M16: =SUM(M14:M15) -> 74000 | N16: 73707 | Q16: =Q14-Q15 -> #REF! | X16: =SUM(A16:A18) -> 1867 | Y16: =X16*V4 -> 191927.6
A17: 504 | B17: 504 | D17: Trading Acocunt | E17: III ( both JG and MG) | F17: MGJG | G17: =(24473-G9)+25001 -> 49048 | H17: =(23229-H9)+23723 -> 46517
A18: 597 | B18: 555 | C18: 800 | D18: OWN SAP | F18: MG | G18: 79004 | H18: 73134
A19: 2011 | C19: 99 | D19: SAP Shares | E19: 1 free | F19: MG | J19: SAP Shares | K19: 1 free | N19: 42156 | P19: 37666 | W19: =388*70/1.43 -> 18993.007
A20: 2012 | C20: 96 | D20: SAP Shares | E20: 5 p 3y 3g | F20: MG | J20: SAP Shares | K20: 5 p 3y 3g | N20: 41791 | P20: 35143
A21: 2013 | C21: 87 | D21: SAP Shares | E21: B3K3G1 | F21: MG | J21: SAP Shares | K21: B3K3G1 | N21: 42583
M22: =SUM(M19:M21) -> 0
D24: Total | G24: =SUM(G4:G18) -> 536746 | H24: =SUM(H4:H18) -> 519120 | I24: 504894 | M24: =M9+M16 -> 122500 | Z24: 1155
Q25: 900 | Z25: 80.13
D26: Potential Balance | G26: =G24 -> 536746 | H26: 584474 | I26: =G24-H24 -> 17626 | K26: 77 | AA26: =Z25*Z24 -> 92550.15
D27: Not so liquid | N27: Actual | O27: 31st Dec | P27: 31st Dec | Q27: 31st Dec | R27: 31st Dec | S27: 31st Dec | T27: 31st Dec | Z27: 1.5 | AA27: =AA26/Z27 -> 61700.1
D28: Aston | E28: Sold | G28: 0 | O28: 2015 | P28: 2016 | Q28: 2017 | R28: 2018 | S28: 2019 | T28: 2020 | U28: =T28+1 -> 2021
D29: Golf R | G29: 15000 | N29: Value | O29: 164433.05 | P29: 248589.4 | Q29: 314989.19 | R29: 335945 | S29: 336562 | T29: 374989.19
D30: Motor Bike | G30: 2000 | O30: 0 | P30: 0 | S30: 30000 | T30: 7000
G31: =SUM(G28:G30) -> 17000 | N31: Santandar | O31: 29028
N32: Total | O32: 193461.05 | P32: 248589.4 | Q32: 314989.19 | R32: 335945 | S32: 374989.19 | T32: 381989.19
D33: Less CC Debit | G33: 1600 | P33: 55128.35 | Q33: 66399.786 | R33: =R32-Q32 -> 20955.812
D35: Sub Total | G35: =G26+G31-G33 -> 552146 | N35: Q1 | P35: 282432.89 | Q35: 33843.485 | R35: 8687 | S35: 120736 | Z35: phil | AA35: 1500
N36: Q2 | P36: 294892.7 | Q36: 12459.809 | R36: 5697 | S36: 43735
D37: Tied Assetts | G37: =M24 -> 122500 | N37: Q3 | P37: 310690.69 | Q37: 15797.999 | R37: 37050 | S37: -7000
N38: Q4 | P38: 314989.19 | Q38: 4298.4936 | R38: -31361 | S38: 11634
D39: House | G39: 360000 | Q39: 66399.786 | R39: =SUM(R35:R38) -> 20073 | S39: =SUM(S35:S38) -> 169105
D40: less mortgage | G40: =G39 -> 360000
N41: Budget | O41: 31st Dec | P41: 31st Dec | Q41: 31st Dec | R41: 31st Dec | S41: 31st Dec | T41: 31st Dec | Z41: RN Pension
D42: Nett Worth | G42: =G40+G37+G35 -> 1034646 | O42: 2015 | P42: 2016 | Q42: 2017 | R42: 2018 | S42: 2019 | T42: 2020 | Z42: Nissan | AA42: GSR Capital
N43: Base | O43: 105896.15 | P43: 163396.15 | Q43: 193396.15 | R43: 223396.15 | S43: 253396.15 | T43: 283396.15
N44: Save | O44: 30000 | P44: 30000 | Q44: 30000 | R44: 30000 | S44: 30000 | T44: 30000
N45: Extra | O45: 27500
N46: Total | O46: 163396.15 | P46: 193396.15 | Q46: 223396.15 | R46: 253396.15 | S46: 283396.15 | T46: 313396.15
T47: =T46-P32 -> 64806.752

Sheet 31-01-21
A1: 201
D2: Liquid Assests | G2: Read This | J2: Tied Assests
D3: Prod | E3: Where | F3: Who | G3: 44227 | H3: 31/21/2020 | J3: Prod | K3: Where | L3: Who | M3: Amount | Q3: At Risk | R3: Not a Risk - Cash
B4: =488+743 -> 1231 | D4: ISA | E4: Ford | F4: JG | G4: 58600 | H4: 58971 | J4: Family Loans | Q4: =G25-R4 -> 367559 | R4: =SUM(G12:G16) -> 158000 | T4: 130 | V4: 102.8 | W4: Share Price
B5: =504+803 -> 1307 | D5: ISA | E5: Ford | F5: MG | G5: 58600 | H5: 58971 | J5: Faye | M5: 22000 | P5: this is 17k + 5K | T5: 71 | V5: 1.125 | W5: Exchange | AE5: NSI | AF5: 100000
D6: FundSmith | G6: 8661 | H6: 8862 | J6: Nik | M6: 5000 | N6: 155K | P6: Med | Q6: =#REF!+#REF!+G17+G18+G19 -> #REF! | T6: =T4-T5 -> 59 | AE6: Share | AF6: 85000
C7: * | D7: Hargrevaes Lansdown | G7: 1414 | H7: 1439 | J7: Les and Jon | M7: 20000 | P7: High | Q7: =SUM(G6:G10) -> 30799
C8: * | D8: Intractive Investor | G8: 18865 | H8: 19009 | J8: Phil | M8: 1500
C9: * | D9: Bakkovor Now III | G9: 439 | H9: 426 | M9: =SUM(M5:M8) -> 48500
C10: * | D10: Now CfD | G10: 1420 | H10: 2216
D11: ClearWaterCapital | G11: 23024
D12: Current account - Inv, Currt and Holid | E12: Nat West Invest/Holiday - Not EX, Not Prop, Not Current below 4K | G12: 8000 | H12: 33948 | R12: =14514*2 -> 29028 | AE12: Invest | AF12: 40000
D13: Premium Bonds | E13: Post Office | F13: JG | G13: 50000 | H13: 50000 | AF13: =SUM(AF5:AF12) -> 225000
D14: Premium Bonds | E14: Post Office | F14: BH | J14: Rented Properties
C15: 105.06 | D15: Premium Bonds | E15: Post Office | F15: FG | G15: 50000 | H15: 50000 | J15: House | K15: 2bed | M15: 38000 | Q15: 81287
A16: Q3 | B16: Q2 | C16: 44227 | D16: Premium Bonds | E16: Post Office | F16: MG | G16: 50000 | H16: 50000 | J16: House | K16: 3bed | M16: 36000 | Q16: =#REF!*2 -> #REF!
A17: 766 | B17: 766 | C17: 774 | D17: EDSP | E17: Computershare | F17: MG | G17: 71991 | H17: 74852 | J17: Total | M17: =SUM(M15:M16) -> 74000 | N17: 73707 | Q17: =Q15-Q16 -> #REF! | X17: =SUM(A17:A19) -> 1867 | Y17: =X17*V4 -> 191927.6
A18: 504 | B18: 504 | D18: Trading Acocunt | E18: III ( both JG and MG) | F18: MGJG | G18: =22892+217+24043 -> 47152 | H18: =(24473-H9)+25001 -> 49048
A19: 597 | B19: 555 | C19: 832 | D19: OWN SAP | F19: MG | G19: 77393 | H19: 79004
A20: 2011 | C20: 99 | D20: SAP Shares | E20: 1 free | F20: MG | J20: SAP Shares | K20: 1 free | N20: 42156 | P20: 37666 | W20: =388*70/1.43 -> 18993.007
A21: 2012 | C21: 96 | D21: SAP Shares | E21: 5 p 3y 3g | F21: MG | J21: SAP Shares | K21: 5 p 3y 3g | N21: 41791 | P21: 35143
A22: 2013 | C22: 87 | D22: SAP Shares | E22: B3K3G1 | F22: MG | J22: SAP Shares | K22: B3K3G1 | N22: 42583
M23: =SUM(M20:M22) -> 0
D25: Total | G25: =SUM(G4:G19) -> 525559 | H25: =SUM(H4:H19) -> 536746 | I25: 504894 | M25: =M9+M17 -> 122500 | Z25: 1155
Q26: 900 | Z26: 80.13
D27: Potential Balance | G27: =G25 -> 525559 | H27: 584474 | I27: =G25-H25 -> -11187 | K27: 77 | AA27: =Z26*Z25 -> 92550.15
D28: Not so liquid | N28: Actual | O28: 31st Dec | P28: 31st Dec | Q28: 31st Dec | R28: 31st Dec | S28: 31st Dec | T28: 31st Dec | Z28: 1.5 | AA28: =AA27/Z28 -> 61700.1
D29: Aston | E29: Sold | G29: 0 | O29: 2015 | P29: 2016 | Q29: 2017 | R29: 2018 | S29: 2019 | T29: 2020 | U29: =T29+1 -> 2021
D30: Golf R | G30: 15000 | N30: Value | O30: 164433.05 | P30: 248589.4 | Q30: 314989.19 | R30: 335945 | S30: 336562 | T30: 374989.19
D31: Motor Bike | G31: 2000 | O31: 0 | P31: 0 | S31: 30000 | T31: 7000
G32: =SUM(G29:G31) -> 17000 | N32: Santandar | O32: 29028
N33: Total | O33: 193461.05 | P33: 248589.4 | Q33: 314989.19 | R33: 335945 | S33: 374989.19 | T33: 381989.19
D34: Less CC Debit | G34: 1600 | P34: 55128.35 | Q34: 66399.786 | R34: =R33-Q33 -> 20955.812
D36: Sub Total | G36: =G27+G32-G34 -> 540959 | N36: Q1 | P36: 282432.89 | Q36: 33843.485 | R36: 8687 | S36: 120736 | Z36: phil | AA36: 1500
N37: Q2 | P37: 294892.7 | Q37: 12459.809 | R37: 5697 | S37: 43735
D38: Tied Assetts | G38: =M25 -> 122500 | N38: Q3 | P38: 310690.69 | Q38: 15797.999 | R38: 37050 | S38: -7000
N39: Q4 | P39: 314989.19 | Q39: 4298.4936 | R39: -31361 | S39: 11634
D40: House | G40: 360000 | Q40: 66399.786 | R40: =SUM(R36:R39) -> 20073 | S40: =SUM(S36:S39) -> 169105
D41: less mortgage | G41: =G40 -> 360000
N42: Budget | O42: 31st Dec | P42: 31st Dec | Q42: 31st Dec | R42: 31st Dec | S42: 31st Dec | T42: 31st Dec | Z42: RN Pension
D43: Nett Worth | G43: =G41+G38+G36 -> 1023459 | O43: 2015 | P43: 2016 | Q43: 2017 | R43: 2018 | S43: 2019 | T43: 2020 | Z43: Nissan | AA43: GSR Capital
N44: Base | O44: 105896.15 | P44: 163396.15 | Q44: 193396.15 | R44: 223396.15 | S44: 253396.15 | T44: 283396.15
N45: Save | O45: 30000 | P45: 30000 | Q45: 30000 | R45: 30000 | S45: 30000 | T45: 30000
N46: Extra | O46: 27500
N47: Total | O47: 163396.15 | P47: 193396.15 | Q47: 223396.15 | R47: 253396.15 | S47: 283396.15 | T47: 313396.15
T48: =T47-P33 -> 64806.752

Sheet 28-02-21
A1: 201
D2: Liquid Assests | G2: Read This | J2: Tied Assests
D3: Prod | E3: Where | F3: Who | G3: 44227 | H3: 44227 | J3: Prod | K3: Where | L3: Who | M3: Amount | Q3: At Risk | R3: Not a Risk - Cash
B4: =488+743 -> 1231 | D4: ISA | E4: Ford | F4: JG | G4: 58560 | H4: 58600 | J4: Family Loans | Q4: =G25-R4 -> 366933 | R4: =SUM(G12:G16) -> 156780 | T4: 130 | V4: 102.8 | W4: Share Price
B5: =504+803 -> 1307 | D5: ISA | E5: Ford | F5: MG | G5: 58560 | H5: 58600 | J5: Faye | M5: 22000 | P5: this is 17k + 5K | T5: 71 | V5: 1.125 | W5: Exchange | AE5: NSI | AF5: 100000
D6: FundSmith | G6: 8756 | H6: 8661 | J6: Nik | M6: 5000 | N6: 155K | P6: Med | Q6: =#REF!+#REF!+G17+G18+G19 -> #REF! | T6: =T4-T5 -> 59 | AE6: Share | AF6: 85000
C7: * | D7: Hargrevaes Lansdown | G7: 1322 | H7: 1414 | J7: Les and Jon | M7: 20000 | P7: High | Q7: =SUM(G6:G10) -> 30458
C8: * | D8: Intractive Investor | G8: 18773 | H8: 18865 | J8: Phil | M8: 1500
C9: * | D9: Bakkovor Now Jarvis | G9: 468 | H9: 439 | M9: =SUM(M5:M8) -> 48500
C10: * | D10: Now CfD | G10: 1139 | H10: 1420
D11: ClearWaterCapital | G11: =58262-(G9+22137+5468) -> 30189 | H11: 23024
D12: Current account - Inv, Currt and Holid | E12: Nat West Invest/Holiday - Not EX, Not Prop, Not Current below 4K | G12: =7780-1000 -> 6780 | H12: 8000 | R12: =14514*2 -> 29028 | AE12: Invest | AF12: 40000
D13: Premium Bonds | E13: Post Office | F13: JG | G13: 50000 | H13: 50000 | AF13: =SUM(AF5:AF12) -> 225000
D14: Premium Bonds | E14: Post Office | F14: BH | J14: Rented Properties
C15: 105.06 | D15: Premium Bonds | E15: Post Office | F15: FG | G15: 50000 | H15: 50000 | J15: House | K15: 2bed | M15: 38000 | Q15: 81287
A16: Q3 | B16: Q2 | C16: 44227 | D16: Premium Bonds | E16: Post Office | F16: MG | G16: 50000 | H16: 50000 | J16: House | K16: 3bed | M16: 36000 | Q16: =#REF!*2 -> #REF!
A17: 766 | B17: 766 | C17: 774 | D17: EDSP | E17: Computershare | F17: MG | G17: 68635 | H17: 71991 | J17: Total | M17: =SUM(M15:M16) -> 74000 | N17: 73707 | Q17: =Q15-Q16 -> #REF! | X17: =SUM(A17:A19) -> 1867 | Y17: =X17*V4 -> 191927.6
A18: 504 | B18: 504 | D18: Trading Acocunt | E18: III ( both JG and MG) | F18: MGJG | G18: =21947+190+23246 -> 45383 | H18: =22892+217+24043 -> 47152
A19: 597 | B19: 555 | C19: 847 | D19: OWN SAP | F19: MG | G19: 75148 | H19: 77393
A20: 2011 | C20: 99 | D20: SAP Shares | E20: 1 free | F20: MG | J20: SAP Shares | K20: 1 free | N20: 42156 | P20: 37666 | W20: =388*70/1.43 -> 18993.007
A21: 2012 | C21: 96 | D21: SAP Shares | E21: 5 p 3y 3g | F21: MG | J21: SAP Shares | K21: 5 p 3y 3g | N21: 41791 | P21: 35143
A22: 2013 | C22: 87 | D22: SAP Shares | E22: B3K3G1 | F22: MG | J22: SAP Shares | K22: B3K3G1 | N22: 42583
M23: =SUM(M20:M22) -> 0
D25: Total | G25: =SUM(G4:G19) -> 523713 | H25: =SUM(H4:H19) -> 525559 | I25: =G25-H25 -> -1846 | M25: =M9+M17 -> 122500 | Z25: 1155
Q26: 900 | Z26: 80.13
D27: Potential Balance | K27: 77 | AA27: =Z26*Z25 -> 92550.15
D28: Not so liquid | N28: Actual | O28: 31st Dec | P28: 31st Dec | Q28: 31st Dec | R28: 31st Dec | S28: 31st Dec | T28: 31st Dec | Z28: 1.5 | AA28: =AA27/Z28 -> 61700.1
D29: Aston | E29: Sold | G29: 0 | O29: 2015 | P29: 2016 | Q29: 2017 | R29: 2018 | S29: 2019 | T29: 2020 | U29: =T29+1 -> 2021
D30: Golf R | G30: 15000 | N30: Value | O30: 164433.05 | P30: 248589.4 | Q30: 314989.19 | R30: 335945 | S30: 336562 | T30: 374989.19
D31: Motor Bike | G31: 2000 | O31: 0 | P31: 0 | S31: 30000 | T31: 7000
G32: =SUM(G29:G31) -> 17000 | N32: Santandar | O32: 29028
N33: Total | O33: 193461.05 | P33: 248589.4 | Q33: 314989.19 | R33: 335945 | S33: 374989.19 | T33: 381989.19
D34: Less CC Debit | G34: 1600 | P34: 55128.35 | Q34: 66399.786 | R34: =R33-Q33 -> 20955.812
D36: Sub Total | G36: =G27+G32-G34 -> 15400 | N36: Q1 | P36: 282432.89 | Q36: 33843.485 | R36: 8687 | S36: 120736 | Z36: phil | AA36: 1500
N37: Q2 | P37: 294892.7 | Q37: 12459.809 | R37: 5697 | S37: 43735
D38: Tied Assetts | G38: =M25 -> 122500 | N38: Q3 | P38: 310690.69 | Q38: 15797.999 | R38: 37050 | S38: -7000
N39: Q4 | P39: 314989.19 | Q39: 4298.4936 | R39: -31361 | S39: 11634
D40: House | G40: 360000 | Q40: 66399.786 | R40: =SUM(R36:R39) -> 20073 | S40: =SUM(S36:S39) -> 169105
D41: less mortgage | G41: =G40 -> 360000
N42: Budget | O42: 31st Dec | P42: 31st Dec | Q42: 31st Dec | R42: 31st Dec | S42: 31st Dec | T42: 31st Dec | Z42: RN Pension
D43: Nett Worth | G43: =G41+G38+G36 -> 497900 | O43: 2015 | P43: 2016 | Q43: 2017 | R43: 2018 | S43: 2019 | T43: 2020 | Z43: Nissan | AA43: GSR Capital
N44: Base | O44: 105896.15 | P44: 163396.15 | Q44: 193396.15 | R44: 223396.15 | S44: 253396.15 | T44: 283396.15
N45: Save | O45: 30000 | P45: 30000 | Q45: 30000 | R45: 30000 | S45: 30000 | T45: 30000
N46: Extra | O46: 27500
N47: Total | O47: 163396.15 | P47: 193396.15 | Q47: 223396.15 | R47: 253396.15 | S47: 283396.15 | T47: 313396.15
T48: =T47-P33 -> 64806.752

Sheet 31-03-21
A1: 201
D2: Liquid Assests | G2: Read This | J2: Tied Assests
D3: Prod | E3: Where | F3: Who | G3: 44286 | H3: 44227 | J3: Prod | K3: Where | L3: Who | M3: Amount | Q3: At Risk | R3: Not a Risk - Cash
B4: =488+743 -> 1231 | D4: ISA | E4: Ford | F4: JG | G4: 58606 | H4: 58600 | J4: Family Loans | Q4: =G25-R4 -> 368569 | R4: =SUM(G12:G16) -> 171300 | T4: 130 | V4: 102.8 | W4: Share Price
B5: =504+803 -> 1307 | D5: ISA | E5: Ford | F5: MG | G5: 58606 | H5: 58600 | J5: Faye | M5: 22000 | P5: this is 17k + 5K | T5: 71 | V5: 1.125 | W5: Exchange | AE5: NSI | AF5: 100000
D6: FundSmith | G6: 8941 | H6: 8661 | J6: Nik | M6: 5000 | N6: 155K | P6: Med | Q6: =#REF!+#REF!+G17+G18+G19 -> #REF! | T6: =T4-T5 -> 59 | AE6: Share | AF6: 85000
C7: * | D7: Hargrevaes Lansdown | G7: 1309 | H7: 1414 | J7: Les and Jon | M7: 20000 | P7: High | Q7: =SUM(G6:G10) -> 31389
C8: * | D8: Intractive Investor | G8: 19029 | H8: 18865 | J8: Phil | M8: 1500
C9: * | D9: Bakkovor Now Jarvis | G9: 620 | H9: 439 | M9: =SUM(M5:M8) -> 48500
C10: * | D10: Now CfD | G10: 1490 | H10: 1420
D11: ClearWaterCapital | G11: 28000 | H11: 23024
D12: Current account - Inv, Currt and Holid | E12: Nat West Invest/Holiday - Not EX, Not Prop, Not Current below 4K | G12: 21300 | H12: 8000 | R12: =14514*2 -> 29028 | AE12: Invest | AF12: 40000
D13: Premium Bonds | E13: Post Office | F13: JG | G13: 50000 | H13: 50000 | AF13: =SUM(AF5:AF12) -> 225000
D14: Premium Bonds | E14: Post Office | F14: BH | J14: Rented Properties
C15: 105.06 | D15: Premium Bonds | E15: Post Office | F15: FG | G15: 50000 | H15: 50000 | J15: House | K15: 2bed | M15: 38000 | Q15: 81287
A16: Q3 | B16: Q2 | C16: 44227 | D16: Premium Bonds | E16: Post Office | F16: MG | G16: 50000 | H16: 50000 | J16: House | K16: 3bed | M16: 36000 | Q16: =#REF!*2 -> #REF!
A17: 766 | B17: 766 | C17: 774 | D17: EDSP | E17: equateplus.com | F17: MG | G17: 68883 | H17: 71991 | J17: Total | M17: =SUM(M15:M16) -> 74000 | N17: 73707 | Q17: =Q15-Q16 -> #REF! | X17: =SUM(A17:A19) -> 1867 | Y17: =X17*V4 -> 191927.6
A18: 504 | B18: 504 | D18: Trading Account | E18: III ( both JG and MG) | F18: MGJG | G18: =23501+22680 -> 46181 | H18: =22892+217+24043 -> 47152
A19: 597 | B19: 555 | C19: 864.54 | D19: OWN SAP | E19: equateplus.com | F19: MG | G19: 76904 | H19: 77393
A20: 2011 | C20: 99 | D20: SAP Shares | E20: 1 free | F20: MG | J20: SAP Shares | K20: 1 free | N20: 42156 | P20: 37666 | W20: =388*70/1.43 -> 18993.007
A21: 2012 | C21: 96 | D21: SAP Shares | E21: 5 p 3y 3g | F21: MG | J21: SAP Shares | K21: 5 p 3y 3g | N21: 41791 | P21: 35143
A22: 2013 | C22: 87 | D22: SAP Shares | E22: B3K3G1 | F22: MG | J22: SAP Shares | K22: B3K3G1 | N22: 42583
M23: =SUM(M20:M22) -> 0
D25: Total | G25: =SUM(G4:G19) -> 539869 | H25: =SUM(H4:H19) -> 525559 | I25: =G25-H25 -> 14310 | M25: =M9+M17 -> 122500 | Z25: 1155
Q26: 900 | Z26: 80.13
D27: Potential Balance | K27: 77 | AA27: =Z26*Z25 -> 92550.15
D28: Not so liquid | N28: Actual | O28: 31st Dec | P28: 31st Dec | Q28: 31st Dec | R28: 31st Dec | S28: 31st Dec | T28: 31st Dec | Z28: 1.5 | AA28: =AA27/Z28 -> 61700.1
D29: Aston | E29: Sold | G29: 0 | O29: 2015 | P29: 2016 | Q29: 2017 | R29: 2018 | S29: 2019 | T29: 2020 | U29: =T29+1 -> 2021
D30: Golf R | G30: 15000 | N30: Value | O30: 164433.05 | P30: 248589.4 | Q30: 314989.19 | R30: 335945 | S30: 336562 | T30: 374989.19
D31: Motor Bike | G31: 2000 | O31: 0 | P31: 0 | S31: 30000 | T31: 7000
G32: =SUM(G29:G31) -> 17000 | N32: Santandar | O32: 29028
N33: Total | O33: 193461.05 | P33: 248589.4 | Q33: 314989.19 | R33: 335945 | S33: 374989.19 | T33: 381989.19
D34: Less CC Debit | G34: 1600 | P34: 55128.35 | Q34: 66399.786 | R34: =R33-Q33 -> 20955.812
D36: Sub Total | G36: =G27+G32-G34 -> 15400 | N36: Q1 | P36: 282432.89 | Q36: 33843.485 | R36: 8687 | S36: 120736 | Z36: phil | AA36: 1500
N37: Q2 | P37: 294892.7 | Q37: 12459.809 | R37: 5697 | S37: 43735
D38: Tied Assetts | G38: =M25 -> 122500 | N38: Q3 | P38: 310690.69 | Q38: 15797.999 | R38: 37050 | S38: -7000
N39: Q4 | P39: 314989.19 | Q39: 4298.4936 | R39: -31361 | S39: 11634
D40: House | G40: 360000 | Q40: 66399.786 | R40: =SUM(R36:R39) -> 20073 | S40: =SUM(S36:S39) -> 169105
D41: less mortgage | G41: =G40 -> 360000
N42: Budget | O42: 31st Dec | P42: 31st Dec | Q42: 31st Dec | R42: 31st Dec | S42: 31st Dec | T42: 31st Dec | Z42: RN Pension
D43: Nett Worth | G43: =G41+G38+G36 -> 497900 | O43: 2015 | P43: 2016 | Q43: 2017 | R43: 2018 | S43: 2019 | T43: 2020 | Z43: Nissan | AA43: GSR Capital
N44: Base | O44: 105896.15 | P44: 163396.15 | Q44: 193396.15 | R44: 223396.15 | S44: 253396.15 | T44: 283396.15
N45: Save | O45: 30000 | P45: 30000 | Q45: 30000 | R45: 30000 | S45: 30000 | T45: 30000
N46: Extra | O46: 27500
N47: Total | O47: 163396.15 | P47: 193396.15 | Q47: 223396.15 | R47: 253396.15 | S47: 283396.15 | T47: 313396.15
T48: =T47-P33 -> 64806.752

Sheet 30-04-21
A1: 201
D2: Liquid Assests | G2: Read This | J2: Tied Assests
D3: Prod | E3: Where | F3: Who | G3: 44347 | H3: 44316 | J3: Prod | K3: Where | L3: Who | M3: Amount | Q3: At Risk | R3: Not a Risk - Cash
B4: =488+743 -> 1231 | D4: ISA | E4: Ford | F4: JG | G4: 60898 | H4: 61166 | J4: Family Loans | Q4: =G25-R4 -> 398026 | R4: =SUM(G12:G16) -> 157000 | T4: 130 | V4: 102.8 | W4: Share Price
B5: =504+803 -> 1307 | D5: ISA | E5: Ford | F5: MG | G5: 60898 | H5: 61166 | J5: Faye | M5: 22000 | P5: this is 17k + 5K | T5: 71 | V5: 1.125 | W5: Exchange | AE5: NSI | AF5: 100000
D6: FundSmith | G6: 9400 | H6: 9495 | J6: Nik | M6: 5000 | N6: 155K | P6: Med | Q6: =#REF!+#REF!+G17+G18+G19 -> #REF! | T6: =T4-T5 -> 59 | AE6: Share | AF6: 85000
C7: * | D7: Hargrevaes Lansdown | G7: 1223 | H7: 1266 | J7: Les and Jon | M7: 20000 | P7: High | Q7: =SUM(G6:G10) -> 31234
C8: * | D8: Intractive Investor | G8: 18643 | H8: 19165 | J8: Phil | M8: 1500
C9: * | D9: Bakkovor Now Jarvis | G9: 718 | H9: 698 | M9: =SUM(M5:M8) -> 48500
C10: * | D10: Now CfD | G10: 1250 | H10: 1403 | J10: Cars
D11: ClearWaterCapital | G11: 28000 | H11: 28000 | J11: MG | M11: 9000
D12: Current account - Inv, Currt and Holid | E12: Nat West Invest/Holiday - Not EX, Not Prop, Not Current below 4K | G12: 7000 | H12: 9000 | J12: Yeti | M12: 11000 | R12: =14514*2 -> 29028 | AE12: Invest | AF12: 40000
D13: Premium Bonds | E13: Post Office | F13: JG | G13: 50000 | H13: 50000 | M13: =SUM(M11:M12) -> 20000 | AF13: =SUM(AF5:AF12) -> 225000
D14: Premium Bonds | E14: Post Office | F14: BH | J14: Rented Properties
C15: 105.06 | D15: Premium Bonds | E15: Post Office | F15: FG | G15: 50000 | H15: 50000 | J15: House | K15: 2bed | M15: =38000+1500 -> 39500 | Q15: 81287
A16: Q3 | B16: Q2 | C16: 44227 | D16: Premium Bonds | E16: Post Office | F16: MG | G16: 50000 | H16: 50000 | J16: House | K16: 3bed | M16: =38000+1500 -> 39500 | Q16: =#REF!*2 -> #REF!
A17: 766 | B17: 766 | C17: 774 | D17: EDSP | E17: equateplus.com | F17: MG | G17: 76583 | H17: 78758 | J17: Total | M17: =SUM(M15:M16) -> 79000 | N17: 73707 | Q17: =Q15-Q16 -> #REF! | X17: =SUM(A17:A19) -> 1867 | Y17: =X17*V4 -> 191927.6
A18: 504 | B18: 504 | D18: Trading Account | E18: III ( both JG and MG) | F18: MGJG | G18: =26323+25555 -> 51878 | H18: =26323+25555 -> 51878
A19: 597 | B19: 555 | C19: 880 | D19: OWN SAP | E19: equateplus.com | F19: MG | G19: 88535 | H19: 89536
A20: 2011 | C20: 99 | D20: SAP Shares | E20: 1 free | F20: MG | J20: SAP Shares | K20: 1 free | N20: 42156 | P20: 37666 | W20: =388*70/1.43 -> 18993.007
A21: 2012 | C21: 96 | D21: SAP Shares | E21: 5 p 3y 3g | F21: MG | J21: SAP Shares | K21: 5 p 3y 3g | N21: 41791 | P21: 35143
A22: 2013 | C22: 87 | D22: SAP Shares | E22: B3K3G1 | F22: MG | J22: SAP Shares | K22: B3K3G1 | N22: 42583
M23: =SUM(M20:M22) -> 0
D25: Total | G25: =SUM(G4:G19) -> 555026 | H25: =SUM(H4:H19) -> 561531 | I25: =G25-H25 -> -6505 | M25: =M9+M17+M13 -> 147500 | Z25: 1155
Q26: 900 | Z26: 80.13
D27: Potential Balance | K27: 77 | AA27: =Z26*Z25 -> 92550.15
D28: Not so liquid | N28: Actual | O28: 31st Dec | P28: 31st Dec | Q28: 31st Dec | R28: 31st Dec | S28: 31st Dec | T28: 31st Dec | Z28: 1.5 | AA28: =AA27/Z28 -> 61700.1
D29: Aston | E29: Sold | G29: 0 | O29: 2015 | P29: 2016 | Q29: 2017 | R29: 2018 | S29: 2019 | T29: 2020 | U29: =T29+1 -> 2021
D30: Golf R | G30: 15000 | N30: Value | O30: 164433.05 | P30: 248589.4 | Q30: 314989.19 | R30: 335945 | S30: 336562 | T30: 374989.19
D31: Motor Bike | G31: 2000 | O31: 0 | P31: 0 | S31: 30000 | T31: 7000
G32: =SUM(G29:G31) -> 17000 | N32: Santandar | O32: 29028
N33: Total | O33: 193461.05 | P33: 248589.4 | Q33: 314989.19 | R33: 335945 | S33: 374989.19 | T33: 381989.19
D34: Less CC Debit | G34: 1600 | P34: 55128.35 | Q34: 66399.786 | R34: =R33-Q33 -> 20955.812
D36: Sub Total | G36: =G27+G32-G34 -> 15400 | N36: Q1 | P36: 282432.89 | Q36: 33843.485 | R36: 8687 | S36: 120736 | Z36: phil | AA36: 1500
N37: Q2 | P37: 294892.7 | Q37: 12459.809 | R37: 5697 | S37: 43735
D38: Tied Assetts | G38: =M25 -> 147500 | N38: Q3 | P38: 310690.69 | Q38: 15797.999 | R38: 37050 | S38: -7000
N39: Q4 | P39: 314989.19 | Q39: 4298.4936 | R39: -31361 | S39: 11634
D40: House | G40: 360000 | Q40: 66399.786 | R40: =SUM(R36:R39) -> 20073 | S40: =SUM(S36:S39) -> 169105
D41: less mortgage | G41: =G40 -> 360000
N42: Budget | O42: 31st Dec | P42: 31st Dec | Q42: 31st Dec | R42: 31st Dec | S42: 31st Dec | T42: 31st Dec | Z42: RN Pension
D43: Nett Worth | G43: =G41+G38+G36 -> 522900 | O43: 2015 | P43: 2016 | Q43: 2017 | R43: 2018 | S43: 2019 | T43: 2020 | Z43: Nissan | AA43: GSR Capital
N44: Base | O44: 105896.15 | P44: 163396.15 | Q44: 193396.15 | R44: 223396.15 | S44: 253396.15 | T44: 283396.15
N45: Save | O45: 30000 | P45: 30000 | Q45: 30000 | R45: 30000 | S45: 30000 | T45: 30000
N46: Extra | O46: 27500
N47: Total | O47: 163396.15 | P47: 193396.15 | Q47: 223396.15 | R47: 253396.15 | S47: 283396.15 | T47: 313396.15
T48: =T47-P33 -> 64806.752

Sheet 30-06-21
A1: 201
D2: Liquid Assests | G2: Read This | J2: Tied Assests
D3: Prod | E3: Where | F3: Who | G3: 44377 | H3: 44347 | J3: Prod | K3: Where | L3: Who | M3: Amount | Q3: At Risk | R3: Not a Risk - Cash
B4: =488+743 -> 1231 | D4: ISA | E4: Ford | F4: JG | G4: =37676+24892 -> 62568 | H4: 60898 | J4: Family Loans | Q4: =G25-R4 -> 411777 | R4: =SUM(G12:G16) -> 156000 | T4: 130 | V4: 102.8 | W4: Share Price
B5: =504+803 -> 1307 | D5: ISA | E5: Ford | F5: MG | G5: =37676+24892 -> 62568 | H5: 60898 | J5: Faye | M5: 22000 | P5: this is 17k + 5K | T5: 71 | V5: 1.125 | W5: Exchange | AE5: NSI | AF5: 100000
D6: FundSmith | G6: 10021 | H6: 9400 | J6: Nik | M6: 5000 | N6: 155K | P6: Med | Q6: =#REF!+#REF!+G17+G18+G19 -> #REF! | T6: =T4-T5 -> 59 | AE6: Share | AF6: 85000
C7: * | D7: Hargrevaes Lansdown | G7: 1329 | H7: 1223 | J7: Les and Jon | M7: 20000 | P7: High | Q7: =SUM(G6:G10) -> 21990
C8: * | D8: Intractive Investor | G8: 8961 | H8: 18643 | J8: Phil | M8: 1500
C9: * | D9: Bakkovor Now Jarvis | G9: 679 | H9: 718 | M9: =SUM(M5:M8) -> 48500
C10: * | D10: Now CfD | G10: 1000 | H10: 1250 | J10: Cars
D11: ClearWaterCapital | G11: =28000+10252 -> 38252 | H11: 28000 | J11: MG | M11: 9000
D12: Current account - Inv, Currt and Holid | E12: Nat West Invest/Holiday - Not EX, Not Prop, Not Current below 4K | G12: 6000 | H12: 7000 | J12: Yeti | M12: 11000 | R12: =14514*2 -> 29028 | AE12: Invest | AF12: 40000
D13: Premium Bonds | E13: Post Office | F13: JG | G13: 50000 | H13: 50000 | M13: =SUM(M11:M12) -> 20000 | AF13: =SUM(AF5:AF12) -> 225000
D14: Premium Bonds | E14: Post Office | F14: BH | J14: Rented Properties
C15: 105.06 | D15: Premium Bonds | E15: Post Office | F15: FG | G15: 50000 | H15: 50000 | J15: House | K15: 2bed | M15: =38000+1500 -> 39500 | Q15: 81287
A16: Q3 | B16: Q2 | C16: 44227 | D16: Premium Bonds | E16: Post Office | F16: MG | G16: 50000 | H16: 50000 | J16: House | K16: 3bed | M16: =38000+1500 -> 39500 | Q16: =#REF!*2 -> #REF!
A17: 766 | B17: 766 | C17: 783 | D17: EDSP | E17: equateplus.com | F17: MG | G17: 79947 | H17: 76583 | J17: Total | M17: =SUM(M15:M16) -> 79000 | N17: 73707 | Q17: =Q15-Q16 -> #REF! | X17: =SUM(A17:A19) -> 1867 | Y17: =X17*V4 -> 191927.6
A18: 504 | B18: 504 | D18: Trading Account | E18: III ( both JG and MG) | F18: MGJG | G18: =25700+26750 -> 52450 | H18: =26323+25555 -> 51878
A19: 597 | B19: 555 | C19: 880 | D19: OWN SAP | E19: equateplus.com | F19: MG | G19: 94002 | H19: 88535
A20: 2011 | C20: 99 | D20: SAP Shares | E20: 1 free | F20: MG | J20: SAP Shares | K20: 1 free | N20: 42156 | P20: 37666 | W20: =388*70/1.43 -> 18993.007
A21: 2012 | C21: 96 | D21: SAP Shares | E21: 5 p 3y 3g | F21: MG | J21: SAP Shares | K21: 5 p 3y 3g | N21: 41791 | P21: 35143
A22: 2013 | C22: 87 | D22: SAP Shares | E22: B3K3G1 | F22: MG | J22: SAP Shares | K22: B3K3G1 | N22: 42583
M23: =SUM(M20:M22) -> 0
D25: Total | G25: =SUM(G4:G19) -> 567777 | H25: =SUM(H4:H19) -> 555026 | I25: =G25-H25 -> 12751 | M25: =M9+M17+M13 -> 147500 | Z25: 1155
Q26: 900 | Z26: 80.13
D27: Potential Balance | K27: 77 | AA27: =Z26*Z25 -> 92550.15
D28: Not so liquid | N28: Actual | O28: 31st Dec | P28: 31st Dec | Q28: 31st Dec | R28: 31st Dec | S28: 31st Dec | T28: 31st Dec | Z28: 1.5 | AA28: =AA27/Z28 -> 61700.1
D29: Aston | E29: Sold | G29: 0 | O29: 2015 | P29: 2016 | Q29: 2017 | R29: 2018 | S29: 2019 | T29: 2020 | U29: =T29+1 -> 2021
D30: Golf R | G30: 15000 | N30: Value | O30: 164433.05 | P30: 248589.4 | Q30: 314989.19 | R30: 335945 | S30: 336562 | T30: 374989.19
D31: Motor Bike | G31: 2000 | O31: 0 | P31: 0 | S31: 30000 | T31: 7000
G32: =SUM(G29:G31) -> 17000 | N32: Santandar | O32: 29028
N33: Total | O33: 193461.05 | P33: 248589.4 | Q33: 314989.19 | R33: 335945 | S33: 374989.19 | T33: 381989.19
D34: Less CC Debit | G34: 1600 | P34: 55128.35 | Q34: 66399.786 | R34: =R33-Q33 -> 20955.812
D36: Sub Total | G36: =G27+G32-G34 -> 15400 | N36: Q1 | P36: 282432.89 | Q36: 33843.485 | R36: 8687 | S36: 120736 | Z36: phil | AA36: 1500
N37: Q2 | P37: 294892.7 | Q37: 12459.809 | R37: 5697 | S37: 43735
D38: Tied Assetts | G38: =M25 -> 147500 | N38: Q3 | P38: 310690.69 | Q38: 15797.999 | R38: 37050 | S38: -7000
N39: Q4 | P39: 314989.19 | Q39: 4298.4936 | R39: -31361 | S39: 11634
D40: House | G40: 360000 | Q40: 66399.786 | R40: =SUM(R36:R39) -> 20073 | S40: =SUM(S36:S39) -> 169105
D41: less mortgage | G41: =G40 -> 360000
N42: Budget | O42: 31st Dec | P42: 31st Dec | Q42: 31st Dec | R42: 31st Dec | S42: 31st Dec | T42: 31st Dec | Z42: RN Pension
D43: Nett Worth | G43: =G41+G38+G36 -> 522900 | O43: 2015 | P43: 2016 | Q43: 2017 | R43: 2018 | S43: 2019 | T43: 2020 | Z43: Nissan | AA43: GSR Capital
N44: Base | O44: 105896.15 | P44: 163396.15 | Q44: 193396.15 | R44: 223396.15 | S44: 253396.15 | T44: 283396.15
N45: Save | O45: 30000 | P45: 30000 | Q45: 30000 | R45: 30000 | S45: 30000 | T45: 30000
N46: Extra | O46: 27500
N47: Total | O47: 163396.15 | P47: 193396.15 | Q47: 223396.15 | R47: 253396.15 | S47: 283396.15 | T47: 313396.15
T48: =T47-P33 -> 64806.752

Sheet 30-07-21
A1: 201
D2: Liquid Assests | G2: Read This | J2: Tied Assests
D3: Prod | E3: Where | F3: Who | G3: 44407 | H3: 44377 | J3: Prod | K3: Where | L3: Who | M3: Amount | Q3: At Risk | R3: Not a Risk - Cash
B4: =488+743 -> 1231 | D4: ISA | E4: Ford | F4: JG | G4: 63594 | H4: =37676+24892 -> 62568 | J4: Family Loans | Q4: =H25-R4 -> 411777 | R4: =SUM(H12:H16) -> 156000 | T4: 130 | V4: 102.8 | W4: Share Price
B5: =504+803 -> 1307 | D5: ISA | E5: Ford | F5: MG | G5: 63594 | H5: =37676+24892 -> 62568 | J5: Faye | M5: 22000 | P5: this is 17k + 5K | T5: 71 | V5: 1.125 | W5: Exchange | AE5: NSI | AF5: 100000
D6: FundSmith | G6: 10319 | H6: 10021 | J6: Nik | M6: 5000 | N6: 155K | P6: Med | Q6: =#REF!+#REF!+H17+H18+H19 -> #REF! | T6: =T4-T5 -> 59 | AE6: Share | AF6: 85000
C7: * | D7: Hargrevaes Lansdown | G7: 1280 | H7: 1329 | J7: Les and Jon | M7: 20000 | P7: High | Q7: =SUM(H6:H10) -> 21990
C8: * | D8: Intractive Investor | G8: 8865 | H8: 8961 | J8: Phil | M8: 1500
C9: * | D9: Bakkovor Now Jarvis | G9: 700 | H9: 679 | M9: =SUM(M5:M8) -> 48500
C10: * | D10: Now CfD | G10: 1244 | H10: 1000 | J10: Cars
D11: ClearWaterCapital | G11: =41000+10511-700 -> 50811 | H11: =28000+10252 -> 38252 | J11: MG | M11: 9000
D12: Current account - Inv, Currt and Holid | E12: Nat West Invest/Holiday - Not EX, Not Prop, Not Current below 4K | G12: 9000 | H12: 6000 | J12: Yeti | M12: 11000 | R12: =14514*2 -> 29028 | AE12: Invest | AF12: 40000
D13: Premium Bonds | E13: Post Office | F13: JG | G13: 50000 | H13: 50000 | M13: =SUM(M11:M12) -> 20000 | AF13: =SUM(AF5:AF12) -> 225000
D14: Premium Bonds | E14: Post Office | F14: BH | J14: Rented Properties
C15: 105.06 | D15: Premium Bonds | E15: Post Office | F15: FG | G15: 50000 | H15: 50000 | J15: House | K15: 2bed | M15: =38000+1500 -> 39500 | Q15: 81287
A16: Q3 | B16: Q2 | C16: 44227 | D16: Premium Bonds | E16: Post Office | F16: MG | G16: 50000 | H16: 50000 | J16: House | K16: 3bed | M16: =38000+1500 -> 39500 | Q16: =#REF!*2 -> #REF!
A17: 766 | B17: 766 | C17: 783 | D17: EDSP | E17: equateplus.com | F17: MG | G17: 80752 | H17: 79947 | J17: Total | M17: =SUM(M15:M16) -> 79000 | N17: 73707 | Q17: =Q15-Q16 -> #REF! | X17: =SUM(A17:A19) -> 1867 | Y17: =X17*V4 -> 191927.6
A18: 504 | B18: 504 | D18: Trading Account | E18: III ( both JG and MG) | F18: MGJG | G18: =(25495/1.15)+27056 -> 49225.565 | H18: =25700+26750 -> 52450
A19: 597 | B19: 555 | C19: 880 | D19: OWN SAP | E19: equateplus.com | F19: MG | G19: 96421 | H19: 94002
A20: 2011 | C20: 99 | D20: SAP Shares | E20: 1 free | F20: MG | J20: SAP Shares | K20: 1 free | N20: 42156 | P20: 37666 | W20: =388*70/1.43 -> 18993.007
A21: 2012 | C21: 96 | D21: SAP Shares | E21: 5 p 3y 3g | F21: MG | J21: SAP Shares | K21: 5 p 3y 3g | N21: 41791 | P21: 35143
A22: 2013 | C22: 87 | D22: SAP Shares | E22: B3K3G1 | F22: MG | J22: SAP Shares | K22: B3K3G1 | N22: 42583
M23: =SUM(M20:M22) -> 0
D25: Total | G25: =SUM(G4:G19) -> 585805.57 | H25: =SUM(H4:H19) -> 567777 | I25: =H25-#REF! -> #REF! | M25: =M9+M17+M13 -> 147500 | Z25: 1155
Q26: 900 | Z26: 80.13
D27: Potential Balance | K27: 77 | AA27: =Z26*Z25 -> 92550.15
D28: Not so liquid | N28: Actual | O28: 31st Dec | P28: 31st Dec | Q28: 31st Dec | R28: 31st Dec | S28: 31st Dec | T28: 31st Dec | Z28: 1.5 | AA28: =AA27/Z28 -> 61700.1
D29: Aston | E29: Sold | G29: 0 | O29: 2015 | P29: 2016 | Q29: 2017 | R29: 2018 | S29: 2019 | T29: 2020 | U29: =T29+1 -> 2021
D30: Golf R | G30: 15000 | N30: Value | O30: 164433.05 | P30: 248589.4 | Q30: 314989.19 | R30: 335945 | S30: 336562 | T30: 374989.19
D31: Motor Bike | G31: 2000 | O31: 0 | P31: 0 | S31: 30000 | T31: 7000
G32: =SUM(G29:G31) -> 17000 | N32: Santandar | O32: 29028
N33: Total | O33: 193461.05 | P33: 248589.4 | Q33: 314989.19 | R33: 335945 | S33: 374989.19 | T33: 381989.19
D34: Less CC Debit | G34: 1600 | P34: 55128.35 | Q34: 66399.786 | R34: =R33-Q33 -> 20955.812
D36: Sub Total | G36: =G27+G32-G34 -> 15400 | N36: Q1 | P36: 282432.89 | Q36: 33843.485 | R36: 8687 | S36: 120736 | Z36: phil | AA36: 1500
N37: Q2 | P37: 294892.7 | Q37: 12459.809 | R37: 5697 | S37: 43735
D38: Tied Assetts | G38: =M25 -> 147500 | N38: Q3 | P38: 310690.69 | Q38: 15797.999 | R38: 37050 | S38: -7000
N39: Q4 | P39: 314989.19 | Q39: 4298.4936 | R39: -31361 | S39: 11634
D40: House | G40: 360000 | Q40: 66399.786 | R40: =SUM(R36:R39) -> 20073 | S40: =SUM(S36:S39) -> 169105
D41: less mortgage | G41: =G40 -> 360000
N42: Budget | O42: 31st Dec | P42: 31st Dec | Q42: 31st Dec | R42: 31st Dec | S42: 31st Dec | T42: 31st Dec | Z42: RN Pension
D43: Nett Worth | G43: =G41+G38+G36 -> 522900 | O43: 2015 | P43: 2016 | Q43: 2017 | R43: 2018 | S43: 2019 | T43: 2020 | Z43: Nissan | AA43: GSR Capital
N44: Base | O44: 105896.15 | P44: 163396.15 | Q44: 193396.15 | R44: 223396.15 | S44: 253396.15 | T44: 283396.15
N45: Save | O45: 30000 | P45: 30000 | Q45: 30000 | R45: 30000 | S45: 30000 | T45: 30000
N46: Extra | O46: 27500
N47: Total | O47: 163396.15 | P47: 193396.15 | Q47: 223396.15 | R47: 253396.15 | S47: 283396.15 | T47: 313396.15
T48: =T47-P33 -> 64806.752

Sheet 31-08-21
A1: 201
D2: Liquid Assests | G2: Read This | J2: Tied Assests | N2: 524438 | O2: b
D3: Prod | E3: Where | F3: Who | G3: 44439 | H3: 44407 | J3: Prod | K3: Where | L3: Who | M3: Amount | Q3: At Risk | R3: Not a Risk - Cash
B4: =488+743 -> 1231 | D4: ISA | E4: Ford | F4: JG | G4: 65656 | H4: 63594 | J4: Family Loans | Q4: =H25-R4 -> 426805.57 | R4: =SUM(H12:H16) -> 159000 | T4: 130 | V4: 102.8 | W4: Share Price
B5: =504+803 -> 1307 | D5: ISA | E5: Ford | F5: MG | G5: 65656 | H5: 63594 | J5: Faye | M5: 22000 | P5: this is 17k + 5K | T5: 71 | V5: 1.125 | W5: Exchange | AE5: NSI | AF5: 100000
D6: FundSmith | G6: 10400 | H6: 10319 | J6: Nik | M6: 5000 | N6: 155K | P6: Med | Q6: =#REF!+#REF!+H17+H18+H19 -> #REF! | T6: =T4-T5 -> 59 | AE6: Share | AF6: 85000
C7: * | D7: Hargrevaes Lansdown | G7: 1280 | H7: 1280 | J7: Les and Jon | M7: 20000 | P7: High | Q7: =SUM(H6:H10) -> 22408
C8: * | D8: Intractive Investor | G8: =9349+731 -> 10080 | H8: 8865 | J8: Phil | M8: 1500
C9: * | D9: Bakkovor Now Jarvis but ISA | G9: 12218 | H9: 700 | M9: =SUM(M5:M8) -> 48500
C10: * | D10: Now CfD | G10: 1278 | H10: 1244 | J10: Cars
D11: ClearWaterCapital | G11: 55189 | H11: =41000+10511-700 -> 50811 | J11: MG | M11: 9000
D12: Current account - Inv, Currt and Holid | E12: Nat West Invest/Holiday - Not EX, Not Prop, Not Current below 4K | G12: 7300 | H12: 9000 | J12: Yeti | M12: 11000 | R12: =14514*2 -> 29028 | AE12: Invest | AF12: 40000
D13: Premium Bonds | E13: Post Office | F13: JG | G13: 50000 | H13: 50000 | M13: =SUM(M11:M12) -> 20000 | AF13: =SUM(AF5:AF12) -> 225000
D14: Premium Bonds | E14: Post Office | F14: BH | J14: Rented Properties
C15: 105.06 | D15: Premium Bonds | E15: Post Office | F15: FG | G15: 50000 | H15: 50000 | J15: House | K15: 2bed | M15: =38000+1500 -> 39500 | Q15: 81287
A16: Q3 | B16: Q2 | C16: 44227 | D16: Premium Bonds | E16: Post Office | F16: MG | G16: 50000 | H16: 50000 | J16: House | K16: 3bed | M16: =38000+1500 -> 39500 | Q16: =#REF!*2 -> #REF!
A17: 766 | B17: 766 | C17: 783 | D17: EDSP | E17: equateplus.com | F17: MG | G17: 84370 | H17: 80752 | J17: Total | M17: =SUM(M15:M16) -> 79000 | N17: 73707 | Q17: =Q15-Q16 -> #REF! | X17: =SUM(A17:A19) -> 1867 | Y17: =X17*V4 -> 191927.6
A18: 504 | B18: 504 | C18: ??? | D18: Trading Account | E18: III ( both JG and MG) | F18: MGJG | G18: 28210 | H18: =(25495/1.15)+27056 -> 49225.565
A19: 597 | B19: 555 | C19: 949 | D19: OWN SAP | E19: equateplus.com | F19: MG | G19: 102258 | H19: 96421
A20: 2011 | C20: 99 | D20: SAP Shares | E20: 1 free | F20: MG | J20: SAP Shares | K20: 1 free | N20: 42156 | P20: 37666 | W20: =388*70/1.43 -> 18993.007
A21: 2012 | C21: 96 | D21: SAP Shares | E21: 5 p 3y 3g | F21: MG | J21: SAP Shares | K21: 5 p 3y 3g | N21: 41791 | P21: 35143
A22: 2013 | C22: 87 | D22: SAP Shares | E22: B3K3G1 | F22: MG | J22: SAP Shares | K22: B3K3G1 | N22: 42583
M23: =SUM(M20:M22) -> 0
D25: Total | G25: =SUM(G4:G19) -> 593895 | H25: =SUM(H4:H19) -> 585805.57 | I25: =H25-#REF! -> #REF! | M25: =M9+M17+M13 -> 147500 | Z25: 1155
Q26: 900 | Z26: 80.13
D27: Potential Balance | K27: 77 | AA27: =Z26*Z25 -> 92550.15
D28: Not so liquid | N28: Actual | O28: 31st Dec | P28: 31st Dec | Q28: 31st Dec | R28: 31st Dec | S28: 31st Dec | T28: 31st Dec | Z28: 1.5 | AA28: =AA27/Z28 -> 61700.1
D29: Aston | E29: Sold | G29: 0 | O29: 2015 | P29: 2016 | Q29: 2017 | R29: 2018 | S29: 2019 | T29: 2020 | U29: =T29+1 -> 2021
D30: Golf R | G30: 15000 | N30: Value | O30: 164433.05 | P30: 248589.4 | Q30: 314989.19 | R30: 335945 | S30: 336562 | T30: 374989.19
D31: Motor Bike | G31: 2000 | O31: 0 | P31: 0 | S31: 30000 | T31: 7000
G32: =SUM(G29:G31) -> 17000 | N32: Santandar | O32: 29028
N33: Total | O33: 193461.05 | P33: 248589.4 | Q33: 314989.19 | R33: 335945 | S33: 374989.19 | T33: 381989.19
D34: Less CC Debit | G34: 1600 | P34: 55128.35 | Q34: 66399.786 | R34: =R33-Q33 -> 20955.812
D36: Sub Total | G36: =G27+G32-G34 -> 15400 | N36: Q1 | P36: 282432.89 | Q36: 33843.485 | R36: 8687 | S36: 120736 | Z36: phil | AA36: 1500
N37: Q2 | P37: 294892.7 | Q37: 12459.809 | R37: 5697 | S37: 43735
D38: Tied Assetts | G38: =M25 -> 147500 | N38: Q3 | P38: 310690.69 | Q38: 15797.999 | R38: 37050 | S38: -7000
N39: Q4 | P39: 314989.19 | Q39: 4298.4936 | R39: -31361 | S39: 11634
D40: House | G40: 360000 | Q40: 66399.786 | R40: =SUM(R36:R39) -> 20073 | S40: =SUM(S36:S39) -> 169105
D41: less mortgage | G41: =G40 -> 360000
N42: Budget | O42: 31st Dec | P42: 31st Dec | Q42: 31st Dec | R42: 31st Dec | S42: 31st Dec | T42: 31st Dec | Z42: RN Pension
D43: Nett Worth | G43: =G41+G38+G36 -> 522900 | O43: 2015 | P43: 2016 | Q43: 2017 | R43: 2018 | S43: 2019 | T43: 2020 | Z43: Nissan | AA43: GSR Capital
N44: Base | O44: 105896.15 | P44: 163396.15 | Q44: 193396.15 | R44: 223396.15 | S44: 253396.15 | T44: 283396.15
N45: Save | O45: 30000 | P45: 30000 | Q45: 30000 | R45: 30000 | S45: 30000 | T45: 30000
N46: Extra | O46: 27500
N47: Total | O47: 163396.15 | P47: 193396.15 | Q47: 223396.15 | R47: 253396.15 | S47: 283396.15 | T47: 313396.15
T48: =T47-P33 -> 64806.752

Sheet 30-09-21
A1: 201
D2: Liquid Assests | G2: Read This | J2: Tied Assests | N2: 524438 | O2: b
D3: Prod | E3: Where | F3: Who | G3: 44469 | H3: 44439 | J3: Prod | K3: Where | L3: Who | M3: Amount | Q3: At Risk | R3: Not a Risk - Cash
B4: =488+743 -> 1231 | D4: ISA | E4: Ford | F4: JG | G4: 63524 | H4: 65656 | J4: Family Loans | Q4: =H25-R4 -> 436595 | R4: =SUM(H12:H16) -> 157300 | T4: 130 | V4: 102.8 | W4: Share Price
B5: =504+803 -> 1307 | D5: ISA | E5: Ford | F5: MG | G5: 63524 | H5: 65656 | J5: Faye | M5: 22000 | P5: this is 17k + 5K | T5: 71 | V5: 1.125 | W5: Exchange | AE5: NSI | AF5: 100000
D6: FundSmith | G6: 10179 | H6: 10400 | J6: Nik | M6: 5000 | N6: 155K | P6: Med | Q6: =#REF!+#REF!+H17+H18+H19 -> #REF! | T6: =T4-T5 -> 59 | AE6: Share | AF6: 85000
C7: * | D7: Hargrevaes Lansdown | G7: 1429 | H7: 1280 | J7: Les and Jon | M7: 20000 | P7: High | Q7: =SUM(H6:H10) -> 35256
C8: * | D8: Intractive Investor | G8: 9422 | H8: =9349+731 -> 10080 | J8: Phil | M8: 1500
C9: * | D9: Now Jarvis but ISA | G9: 13928 | H9: 12218 | M9: =SUM(M5:M8) -> 48500
C10: * | D10: Now CfD | G10: 967 | H10: 1278 | J10: Cars
D11: ClearWaterCapital | G11: 57313 | H11: 55189 | J11: MG | M11: 9000
D12: Current account - Inv, Currt and Holid | E12: Nat West Invest/Holiday - Not EX, Not Prop, Not Current below 4K | G12: =7000+2500 -> 9500 | H12: 7300 | J12: Yeti | M12: 11000 | R12: =14514*2 -> 29028 | AE12: Invest | AF12: 40000
D13: Premium Bonds | E13: Post Office | F13: JG | G13: 50000 | H13: 50000 | M13: =SUM(M11:M12) -> 20000 | AF13: =SUM(AF5:AF12) -> 225000
D14: Premium Bonds | E14: Post Office | F14: BH | J14: Rented Properties
C15: 105.06 | D15: Premium Bonds | E15: Post Office | F15: FG | G15: 50000 | H15: 50000 | J15: House | K15: 2bed | M15: =38000+1500 -> 39500 | Q15: 81287
A16: Q3 | B16: Q2 | C16: 44227 | D16: Premium Bonds | E16: Post Office | F16: MG | G16: 50000 | H16: 50000 | J16: House | K16: 3bed | M16: =38000+1500 -> 39500 | Q16: =#REF!*2 -> #REF!
A17: 766 | B17: 766 | C17: 783 | D17: EDSP | E17: equateplus.com | F17: MG | G17: 55851 | H17: 84370 | J17: Total | M17: =SUM(M15:M16) -> 79000 | N17: 73707 | Q17: =Q15-Q16 -> #REF! | X17: =SUM(A17:A19) -> 1867 | Y17: =X17*V4 -> 191927.6
A18: 504 | B18: 504 | C18: ??? | D18: Trading Account | E18: III ( both JG and MG) | F18: MGJG | G18: =(222*116.88)/1.16+26371 -> 48739.414 | H18: 28210
A19: 597 | B19: 555 | C19: 949 | D19: OWN SAP | E19: equateplus.com | F19: MG | G19: 96669 | H19: 102258
A20: 2011 | C20: 99 | D20: SAP Shares | E20: 1 free | F20: MG | J20: SAP Shares | K20: 1 free | N20: 42156 | P20: 37666 | W20: =388*70/1.43 -> 18993.007
A21: 2012 | C21: 96 | D21: SAP Shares | E21: 5 p 3y 3g | F21: MG | J21: SAP Shares | K21: 5 p 3y 3g | N21: 41791 | P21: 35143
A22: 2013 | C22: 87 | D22: SAP Shares | E22: B3K3G1 | F22: MG | J22: SAP Shares | K22: B3K3G1 | N22: 42583
M23: =SUM(M20:M22) -> 0
D25: Total | G25: =SUM(G4:G19) -> 581045.41 | H25: =SUM(H4:H19) -> 593895 | I25: =H25-#REF! -> #REF! | M25: =M9+M17+M13 -> 147500 | Z25: 1155
Q26: 900 | Z26: 80.13
D27: Potential Balance | K27: 77 | AA27: =Z26*Z25 -> 92550.15
D28: Not so liquid | N28: Actual | O28: 31st Dec | P28: 31st Dec | Q28: 31st Dec | R28: 31st Dec | S28: 31st Dec | T28: 31st Dec | Z28: 1.5 | AA28: =AA27/Z28 -> 61700.1
D29: Aston | E29: Sold | G29: 0 | O29: 2015 | P29: 2016 | Q29: 2017 | R29: 2018 | S29: 2019 | T29: 2020 | U29: =T29+1 -> 2021
D30: Golf R | G30: 15000 | N30: Value | O30: 164433.05 | P30: 248589.4 | Q30: 314989.19 | R30: 335945 | S30: 336562 | T30: 374989.19
D31: Motor Bike | G31: 2000 | O31: 0 | P31: 0 | S31: 30000 | T31: 7000
G32: =SUM(G29:G31) -> 17000 | N32: Santandar | O32: 29028
N33: Total | O33: 193461.05 | P33: 248589.4 | Q33: 314989.19 | R33: 335945 | S33: 374989.19 | T33: 381989.19
D34: Less CC Debit | G34: 1600 | P34: 55128.35 | Q34: 66399.786 | R34: =R33-Q33 -> 20955.812
D36: Sub Total | G36: =G27+G32-G34 -> 15400 | N36: Q1 | P36: 282432.89 | Q36: 33843.485 | R36: 8687 | S36: 120736 | Z36: phil | AA36: 1500
N37: Q2 | P37: 294892.7 | Q37: 12459.809 | R37: 5697 | S37: 43735
D38: Tied Assetts | G38: =M25 -> 147500 | N38: Q3 | P38: 310690.69 | Q38: 15797.999 | R38: 37050 | S38: -7000
N39: Q4 | P39: 314989.19 | Q39: 4298.4936 | R39: -31361 | S39: 11634
D40: House | G40: 360000 | Q40: 66399.786 | R40: =SUM(R36:R39) -> 20073 | S40: =SUM(S36:S39) -> 169105
D41: less mortgage | G41: =G40 -> 360000
N42: Budget | O42: 31st Dec | P42: 31st Dec | Q42: 31st Dec | R42: 31st Dec | S42: 31st Dec | T42: 31st Dec | Z42: RN Pension
D43: Nett Worth | G43: =G41+G38+G36 -> 522900 | O43: 2015 | P43: 2016 | Q43: 2017 | R43: 2018 | S43: 2019 | T43: 2020 | Z43: Nissan | AA43: GSR Capital
N44: Base | O44: 105896.15 | P44: 163396.15 | Q44: 193396.15 | R44: 223396.15 | S44: 253396.15 | T44: 283396.15
N45: Save | O45: 30000 | P45: 30000 | Q45: 30000 | R45: 30000 | S45: 30000 | T45: 30000
N46: Extra | O46: 27500
N47: Total | O47: 163396.15 | P47: 193396.15 | Q47: 223396.15 | R47: 253396.15 | S47: 283396.15 | T47: 313396.15
T48: =T47-P33 -> 64806.752

Sheet 29-10-21
A1: 201
D2: Liquid Assests | G2: Read This | J2: Tied Assests | N2: 524438 | O2: b
D3: Prod | E3: Where | F3: Who | G3: 44498 | H3: 44439 | J3: Prod | K3: Where | L3: Who | M3: Amount | Q3: At Risk | R3: Not a Risk - Cash
B4: =488+743 -> 1231 | D4: ISA | E4: Ford | F4: JG | G4: 64563 | H4: 63524 | J4: Family Loans | Q4: =H25-R4 -> 421545.41 | R4: =SUM(H12:H16) -> 159500 | T4: 130 | V4: 102.8 | W4: Share Price
B5: =504+803 -> 1307 | D5: ISA | E5: Ford | F5: MG | G5: 64563 | H5: 63524 | J5: Faye | M5: 22000 | P5: this is 17k + 5K | T5: 71 | V5: 1.125 | W5: Exchange | AE5: NSI | AF5: 100000
D6: FundSmith | G6: 10230 | H6: 10179 | J6: Nik | M6: 5000 | N6: 155K | P6: Med | Q6: =#REF!+#REF!+H17+H18+H19 -> #REF! | T6: =T4-T5 -> 59 | AE6: Share | AF6: 85000
C7: * | D7: Hargrevaes Lansdown | G7: 1327 | H7: 1429 | J7: Les and Jon | M7: 20000 | P7: High | Q7: =SUM(H6:H10) -> 35925
C8: * | D8: Intractive Investor | G8: 10152 | H8: 9422 | J8: Phil | M8: 1500
C9: * | D9: Now Jarvis but ISA | G9: 16857 | H9: 13928 | M9: =SUM(M5:M8) -> 48500
C10: * | D10: Now CfD | H10: 967 | J10: Cars
D11: ClearWaterCapital | G11: =86049-20729 -> 65320 | H11: 57313 | J11: MG | M11: 9000 | P11: =170114-(2*64563) -> 40988
D12: Current account - Inv, Currt and Holid | E12: Nat West Invest/Holiday - Not EX, Not Prop, Not Current below 4K | G12: 12000 | H12: =7000+2500 -> 9500 | J12: Yeti | M12: 11000 | R12: =14514*2 -> 29028 | AE12: Invest | AF12: 40000
D13: Premium Bonds | E13: Post Office | F13: JG | G13: 50000 | H13: 50000 | M13: =SUM(M11:M12) -> 20000 | AF13: =SUM(AF5:AF12) -> 225000
D14: Premium Bonds | E14: Post Office | F14: BH | J14: Rented Properties
C15: 105.06 | D15: Premium Bonds | E15: Post Office | F15: FG | G15: 50000 | H15: 50000 | J15: House | K15: 2bed | M15: =38000+1500 -> 39500 | Q15: 81287
A16: Q3 | B16: Q2 | C16: 44227 | D16: Premium Bonds | E16: Post Office | F16: MG | G16: 50000 | H16: 50000 | J16: House | K16: 3bed | M16: =38000+1500 -> 39500 | Q16: =#REF!*2 -> #REF!
A17: 766 | B17: 766 | C17: 783 | D17: EDSP | E17: equateplus.com | F17: MG | G17: 58914 | H17: 55851 | J17: Total | M17: =SUM(M15:M16) -> 79000 | N17: 73707 | Q17: =Q15-Q16 -> #REF! | X17: =SUM(A17:A19) -> 1867 | Y17: =X17*V4 -> 191927.6
A18: 504 | B18: 504 | C18: ??? | D18: Trading Account | E18: III ( both JG and MG) | F18: MGJG | G18: =(24046/1.16) + 27497 -> 48226.31 | H18: =(222*116.88)/1.16+26371 -> 48739.414
A19: 597 | B19: 555 | C19: 949 | D19: OWN SAP | E19: equateplus.com | F19: MG | G19: 103571 | H19: 96669
A20: 2011 | C20: 99 | D20: SAP Shares | E20: 1 free | F20: MG | J20: SAP Shares | K20: 1 free | N20: 42156 | P20: 37666 | W20: =388*70/1.43 -> 18993.007
A21: 2012 | C21: 96 | D21: SAP Shares | E21: 5 p 3y 3g | F21: MG | J21: SAP Shares | K21: 5 p 3y 3g | N21: 41791 | P21: 35143
A22: 2013 | C22: 87 | D22: SAP Shares | E22: B3K3G1 | F22: MG | J22: SAP Shares | K22: B3K3G1 | N22: 42583
M23: =SUM(M20:M22) -> 0
D25: Total | G25: =SUM(G4:G19) -> 605723.31 | H25: =SUM(H4:H19) -> 581045.41 | I25: =H25-#REF! -> #REF! | M25: =M9+M17+M13 -> 147500 | Z25: 1155
Q26: 900 | Z26: 80.13
D27: Potential Balance | K27: 77 | AA27: =Z26*Z25 -> 92550.15
D28: Not so liquid | N28: Actual | O28: 31st Dec | P28: 31st Dec | Q28: 31st Dec | R28: 31st Dec | S28: 31st Dec | T28: 31st Dec | Z28: 1.5 | AA28: =AA27/Z28 -> 61700.1
D29: Aston | E29: Sold | G29: 0 | O29: 2015 | P29: 2016 | Q29: 2017 | R29: 2018 | S29: 2019 | T29: 2020 | U29: =T29+1 -> 2021
D30: Golf R | G30: 15000 | N30: Value | O30: 164433.05 | P30: 248589.4 | Q30: 314989.19 | R30: 335945 | S30: 336562 | T30: 374989.19
D31: Motor Bike | G31: 2000 | O31: 0 | P31: 0 | S31: 30000 | T31: 7000
G32: =SUM(G29:G31) -> 17000 | N32: Santandar | O32: 29028
N33: Total | O33: 193461.05 | P33: 248589.4 | Q33: 314989.19 | R33: 335945 | S33: 374989.19 | T33: 381989.19
D34: Less CC Debit | G34: 1600 | P34: 55128.35 | Q34: 66399.786 | R34: =R33-Q33 -> 20955.812
D36: Sub Total | G36: =G27+G32-G34 -> 15400 | N36: Q1 | P36: 282432.89 | Q36: 33843.485 | R36: 8687 | S36: 120736 | Z36: phil | AA36: 1500
N37: Q2 | P37: 294892.7 | Q37: 12459.809 | R37: 5697 | S37: 43735
D38: Tied Assetts | G38: =M25 -> 147500 | N38: Q3 | P38: 310690.69 | Q38: 15797.999 | R38: 37050 | S38: -7000
N39: Q4 | P39: 314989.19 | Q39: 4298.4936 | R39: -31361 | S39: 11634
D40: House | G40: 360000 | Q40: 66399.786 | R40: =SUM(R36:R39) -> 20073 | S40: =SUM(S36:S39) -> 169105
D41: less mortgage | G41: =G40 -> 360000
N42: Budget | O42: 31st Dec | P42: 31st Dec | Q42: 31st Dec | R42: 31st Dec | S42: 31st Dec | T42: 31st Dec | Z42: RN Pension
D43: Nett Worth | G43: =G41+G38+G36 -> 522900 | O43: 2015 | P43: 2016 | Q43: 2017 | R43: 2018 | S43: 2019 | T43: 2020 | Z43: Nissan | AA43: GSR Capital
N44: Base | O44: 105896.15 | P44: 163396.15 | Q44: 193396.15 | R44: 223396.15 | S44: 253396.15 | T44: 283396.15
N45: Save | O45: 30000 | P45: 30000 | Q45: 30000 | R45: 30000 | S45: 30000 | T45: 30000
N46: Extra | O46: 27500
N47: Total | O47: 163396.15 | P47: 193396.15 | Q47: 223396.15 | R47: 253396.15 | S47: 283396.15 | T47: 313396.15
T48: =T47-P33 -> 64806.752

Sheet 30-11-21
A1: 201
D2: Liquid Assests | G2: Read This | J2: Tied Assests | N2: 524438 | O2: b
D3: Prod | E3: Where | F3: Who | G3: 44530 | H3: 44439 | J3: Prod | K3: Where | L3: Who | M3: Amount | Q3: At Risk | R3: Not a Risk - Cash
B4: =488+743 -> 1231 | D4: ISA | E4: Ford | F4: JG | G4: 64963 | H4: 64563 | J4: Family Loans | Q4: =H25-R4 -> 443723.31 | R4: =SUM(H12:H16) -> 162000 | T4: 130 | V4: 102.8 | W4: Share Price
B5: =504+803 -> 1307 | D5: ISA | E5: Ford | F5: MG | G5: 64963 | H5: 64563 | J5: Faye | M5: 22000 | P5: this is 17k + 5K | T5: 71 | V5: 1.125 | W5: Exchange | AE5: NSI | AF5: 100000
D6: FundSmith | G6: 10504 | H6: 10230 | J6: Nik | M6: 5000 | N6: 155K | P6: Med | Q6: =#REF!+#REF!+H17+H18+H19 -> #REF! | T6: =T4-T5 -> 59 | AE6: Share | AF6: 85000
C7: * | D7: Hargrevaes Lansdown | G7: 1304 | H7: 1327 | J7: Les and Jon | M7: 20000 | P7: High | Q7: =SUM(H6:H10) -> 38566
C8: * | D8: Intractive Investor | G8: 9517 | H8: 10152 | J8: Phil | M8: 1500
C9: * | D9: Now Jarvis but ISA | G9: 14995 | H9: 16857 | M9: =SUM(M5:M8) -> 48500
C10: * | D10: Now CfD | J10: Cars
D11: ClearWaterCapital | G11: =69364-22755 -> 46609 | H11: =86049-20729 -> 65320 | J11: MG | M11: 9000 | P11: =170114-(2*64563) -> 40988
D12: Current account - Inv, Currt and Holid | E12: Nat West Invest/Holiday - Not EX, Not Prop, Not Current below 4K | G12: 4000 | H12: 12000 | J12: Yeti | M12: 11000 | R12: =14514*2 -> 29028 | AE12: Invest | AF12: 40000
D13: Premium Bonds | E13: Post Office | F13: JG | G13: 50000 | H13: 50000 | M13: =SUM(M11:M12) -> 20000 | AF13: =SUM(AF5:AF12) -> 225000
D14: Premium Bonds | E14: Post Office | F14: BH | J14: Rented Properties
C15: 105.06 | D15: Premium Bonds | E15: Post Office | F15: FG | G15: 50000 | H15: 50000 | J15: House | K15: 2bed | M15: =38000+1500 -> 39500 | Q15: 81287
A16: Q3 | B16: Q2 | C16: 44227 | D16: Premium Bonds | E16: Post Office | F16: MG | G16: 50000 | H16: 50000 | J16: House | K16: 3bed | M16: =38000+1500 -> 39500 | Q16: =#REF!*2 -> #REF!
A17: 766 | B17: 766 | C17: 556 | D17: EDSP | E17: equateplus.com | F17: MG | G17: 53747 | H17: 58914 | J17: Total | M17: =SUM(M15:M16) -> 79000 | N17: 73707 | Q17: =Q15-Q16 -> #REF! | X17: =SUM(A17:A19) -> 1867 | Y17: =X17*V4 -> 191927.6
A18: 504 | B18: 504 | C18: ??? | D18: Trading Account | E18: III ( both JG and MG) | F18: MGJG | G18: =22775+26000 -> 48775 | H18: =(24046/1.16) + 27497 -> 48226.31
A19: 597 | B19: 555 | C19: 992 | D19: OWN SAP | E19: equateplus.com | F19: MG | G19: 95686 | H19: 103571
A20: 2011 | C20: 99 | D20: SAP Shares | E20: 1 free | F20: MG | J20: SAP Shares | K20: 1 free | N20: 42156 | P20: 37666 | W20: =388*70/1.43 -> 18993.007
A21: 2012 | C21: 96 | D21: SAP Shares | E21: 5 p 3y 3g | F21: MG | J21: SAP Shares | K21: 5 p 3y 3g | N21: 41791 | P21: 35143
A22: 2013 | C22: 87 | D22: SAP Shares | E22: B3K3G1 | F22: MG | J22: SAP Shares | K22: B3K3G1 | N22: 42583
M23: =SUM(M20:M22) -> 0
D25: Total | G25: =SUM(G4:G19) -> 565063 | H25: =SUM(H4:H19) -> 605723.31 | I25: =H25-#REF! -> #REF! | M25: =M9+M17+M13 -> 147500 | Z25: 1155
Q26: 900 | Z26: 80.13
D27: Potential Balance | K27: 77 | AA27: =Z26*Z25 -> 92550.15
D28: Not so liquid | N28: Actual | O28: 31st Dec | P28: 31st Dec | Q28: 31st Dec | R28: 31st Dec | S28: 31st Dec | T28: 31st Dec | Z28: 1.5 | AA28: =AA27/Z28 -> 61700.1
D29: Aston | E29: Sold | G29: 0 | O29: 2015 | P29: 2016 | Q29: 2017 | R29: 2018 | S29: 2019 | T29: 2020 | U29: =T29+1 -> 2021
D30: Golf R | G30: 15000 | N30: Value | O30: 164433.05 | P30: 248589.4 | Q30: 314989.19 | R30: 335945 | S30: 336562 | T30: 374989.19
D31: Motor Bike | G31: 2000 | O31: 0 | P31: 0 | S31: 30000 | T31: 7000
G32: =SUM(G29:G31) -> 17000 | N32: Santandar | O32: 29028
N33: Total | O33: 193461.05 | P33: 248589.4 | Q33: 314989.19 | R33: 335945 | S33: 374989.19 | T33: 381989.19
D34: Less CC Debit | G34: 1600 | P34: 55128.35 | Q34: 66399.786 | R34: =R33-Q33 -> 20955.812
D36: Sub Total | G36: =G27+G32-G34 -> 15400 | N36: Q1 | P36: 282432.89 | Q36: 33843.485 | R36: 8687 | S36: 120736 | Z36: phil | AA36: 1500
N37: Q2 | P37: 294892.7 | Q37: 12459.809 | R37: 5697 | S37: 43735
D38: Tied Assetts | G38: =M25 -> 147500 | N38: Q3 | P38: 310690.69 | Q38: 15797.999 | R38: 37050 | S38: -7000
N39: Q4 | P39: 314989.19 | Q39: 4298.4936 | R39: -31361 | S39: 11634
D40: House | G40: 360000 | Q40: 66399.786 | R40: =SUM(R36:R39) -> 20073 | S40: =SUM(S36:S39) -> 169105
D41: less mortgage | G41: =G40 -> 360000
N42: Budget | O42: 31st Dec | P42: 31st Dec | Q42: 31st Dec | R42: 31st Dec | S42: 31st Dec | T42: 31st Dec | Z42: RN Pension
D43: Nett Worth | G43: =G41+G38+G36 -> 522900 | O43: 2015 | P43: 2016 | Q43: 2017 | R43: 2018 | S43: 2019 | T43: 2020 | Z43: Nissan | AA43: GSR Capital
N44: Base | O44: 105896.15 | P44: 163396.15 | Q44: 193396.15 | R44: 223396.15 | S44: 253396.15 | T44: 283396.15
N45: Save | O45: 30000 | P45: 30000 | Q45: 30000 | R45: 30000 | S45: 30000 | T45: 30000
N46: Extra | O46: 27500
N47: Total | O47: 163396.15 | P47: 193396.15 | Q47: 223396.15 | R47: 253396.15 | S47: 283396.15 | T47: 313396.15
T48: =T47-P33 -> 64806.752

Sheet 31-12-21
A1: 201
D2: Liquid Assests | G2: Read This | J2: Tied Assests | N2: 524438 | O2: b
D3: Prod | E3: Where | F3: Who | G3: 44561 | H3: 44530 | J3: Prod | K3: Where | L3: Who | M3: Amount | Q3: At Risk | R3: Not a Risk - Cash
B4: =488+743 -> 1231 | D4: ISA | E4: Ford | F4: JG | G4: 65569 | H4: 64963 | J4: Family Loans | Q4: =#REF!-R4 -> #REF! | R4: =SUM(#REF!) -> #REF! | T4: 130 | V4: 102.8 | W4: Share Price
B5: =504+803 -> 1307 | D5: ISA | E5: Ford | F5: MG | G5: 65569 | H5: 64963 | J5: Faye | M5: 22000 | P5: this is 17k + 5K | T5: 71 | V5: 1.125 | W5: Exchange | AE5: NSI | AF5: 100000
D6: FundSmith | G6: 10821 | H6: 10504 | J6: Nik | M6: 5000 | N6: 155K | P6: Med | Q6: =#REF!+#REF!+#REF!+#REF!+#REF! -> #REF! | T6: =T4-T5 -> 59 | AE6: Share | AF6: 85000
C7: * | D7: Hargrevaes Lansdown | G7: 1200 | H7: 1304 | J7: Les and Jon | M7: 20000 | P7: High | Q7: =SUM(#REF!) -> #REF!
C8: * | D8: Intractive Investor | G8: 9587 | H8: 9517 | J8: Phil | M8: 1500
C9: * | D9: Now Jarvis but ISA | G9: 16189 | H9: 14995 | M9: =SUM(M5:M8) -> 48500
C10: * | D10: Now CfD | J10: Cars
D11: ClearWaterCapital | G11: =68366-23622 -> 44744 | H11: =69364-22755 -> 46609 | J11: MG | M11: 9000 | P11: =170114-(2*64563) -> 40988
D12: Current account - Inv, Currt and Holid | E12: Nat West Invest/Holiday - Not EX, Not Prop, Not Current below 4K | G12: 5500 | H12: 4000 | J12: Yeti | M12: 11000 | R12: =14514*2 -> 29028 | AE12: Invest | AF12: 40000
D13: Premium Bonds | E13: Post Office | F13: JG | G13: 50000 | H13: 50000 | M13: =SUM(M11:M12) -> 20000 | AF13: =SUM(AF5:AF12) -> 225000
D14: Premium Bonds | E14: Post Office | F14: BH | J14: Rented Properties
C15: 105.06 | D15: Premium Bonds | E15: Post Office | F15: FG | G15: 50000 | H15: 50000 | J15: House | K15: 2bed | M15: =38000+1500 -> 39500 | Q15: 81287
A16: Q3 | B16: Q2 | C16: 44227 | D16: Premium Bonds | E16: Post Office | F16: MG | G16: 50000 | H16: 50000 | J16: House | K16: 3bed | M16: =38000+1500 -> 39500 | Q16: =#REF!*2 -> #REF!
A17: 766 | B17: 766 | C17: 556 | D17: EDSP | E17: equateplus.com | F17: MG | G17: 58428 | H17: 53747 | J17: Total | M17: =SUM(M15:M16) -> 79000 | N17: 73707 | Q17: =Q15-Q16 -> #REF! | X17: =SUM(A17:A19) -> 1867 | Y17: =X17*V4 -> 191927.6
A18: 504 | B18: 504 | C18: ??? | D18: Trading Account | E18: III ( both JG and MG) | F18: MGJG | G18: =23622+27004 -> 50626 | H18: =22775+26000 -> 48775
A19: 597 | B19: 555 | C19: 992 | D19: OWN SAP | E19: equateplus.com | F19: MG | G19: 105770 | H19: 95686
A20: 2011 | C20: 99 | D20: SAP Shares | E20: 1 free | F20: MG | J20: SAP Shares | K20: 1 free | N20: 42156 | P20: 37666 | W20: =388*70/1.43 -> 18993.007
A21: 2012 | C21: 96 | D21: SAP Shares | E21: 5 p 3y 3g | F21: MG | J21: SAP Shares | K21: 5 p 3y 3g | N21: 41791 | P21: 35143
A22: 2013 | C22: 87 | D22: SAP Shares | E22: B3K3G1 | F22: MG | J22: SAP Shares | K22: B3K3G1 | N22: 42583
M23: =SUM(M20:M22) -> 0
D25: Total | G25: =SUM(G4:G19) -> 584003 | H25: =SUM(H4:H19) -> 565063 | I25: =#REF!-#REF! -> #REF! | M25: =M9+M17+M13 -> 147500 | Z25: 1155
Q26: 900 | Z26: 80.13
D27: Potential Balance | K27: 77 | AA27: =Z26*Z25 -> 92550.15
D28: Not so liquid | N28: Actual | O28: 31st Dec | P28: 31st Dec | Q28: 31st Dec | R28: 31st Dec | S28: 31st Dec | T28: 31st Dec | Z28: 1.5 | AA28: =AA27/Z28 -> 61700.1
D29: Aston | E29: Sold | G29: 0 | O29: 2015 | P29: 2016 | Q29: 2017 | R29: 2018 | S29: 2019 | T29: 2020 | U29: =T29+1 -> 2021
D30: Golf R | G30: 15000 | N30: Value | O30: 164433.05 | P30: 248589.4 | Q30: 314989.19 | R30: 335945 | S30: 336562 | T30: 374989.19
D31: Motor Bike | G31: 2000 | O31: 0 | P31: 0 | S31: 30000 | T31: 7000
G32: =SUM(G29:G31) -> 17000 | N32: Santandar | O32: 29028
N33: Total | O33: 193461.05 | P33: 248589.4 | Q33: 314989.19 | R33: 335945 | S33: 374989.19 | T33: 381989.19
D34: Less CC Debit | G34: 1600 | P34: 55128.35 | Q34: 66399.786 | R34: =R33-Q33 -> 20955.812
D36: Sub Total | G36: =G27+G32-G34 -> 15400 | N36: Q1 | P36: 282432.89 | Q36: 33843.485 | R36: 8687 | S36: 120736 | Z36: phil | AA36: 1500
N37: Q2 | P37: 294892.7 | Q37: 12459.809 | R37: 5697 | S37: 43735
D38: Tied Assetts | G38: =M25 -> 147500 | N38: Q3 | P38: 310690.69 | Q38: 15797.999 | R38: 37050 | S38: -7000
N39: Q4 | P39: 314989.19 | Q39: 4298.4936 | R39: -31361 | S39: 11634
D40: House | G40: 360000 | Q40: 66399.786 | R40: =SUM(R36:R39) -> 20073 | S40: =SUM(S36:S39) -> 169105
D41: less mortgage | G41: =G40 -> 360000
N42: Budget | O42: 31st Dec | P42: 31st Dec | Q42: 31st Dec | R42: 31st Dec | S42: 31st Dec | T42: 31st Dec | Z42: RN Pension
D43: Nett Worth | G43: =G41+G38+G36 -> 522900 | O43: 2015 | P43: 2016 | Q43: 2017 | R43: 2018 | S43: 2019 | T43: 2020 | Z43: Nissan | AA43: GSR Capital
N44: Base | O44: 105896.15 | P44: 163396.15 | Q44: 193396.15 | R44: 223396.15 | S44: 253396.15 | T44: 283396.15
N45: Save | O45: 30000 | P45: 30000 | Q45: 30000 | R45: 30000 | S45: 30000 | T45: 30000
N46: Extra | O46: 27500
N47: Total | O47: 163396.15 | P47: 193396.15 | Q47: 223396.15 | R47: 253396.15 | S47: 283396.15 | T47: 313396.15
T48: =T47-P33 -> 64806.752

Sheet 31-01-22
A1: 201
D2: Liquid Assests | G2: Read This | J2: Tied Assests | N2: 524438 | O2: b
D3: Prod | E3: Where | F3: Who | G3: 44592 | H3: 44561 | J3: Prod | K3: Where | L3: Who | M3: Amount | Q3: At Risk | R3: Not a Risk - Cash
B4: =488+743 -> 1231 | D4: ISA | E4: Ford | F4: JG | G4: 59236 | H4: 65569 | J4: Family Loans | Q4: =#REF!-R4 -> #REF! | R4: =SUM(#REF!) -> #REF! | T4: 130 | V4: 102.8 | W4: Share Price
B5: =504+803 -> 1307 | D5: ISA | E5: Ford | F5: MG | G5: 59236 | H5: 65569 | J5: Faye | M5: 22000 | P5: this is 17k + 5K | T5: 71 | V5: 1.125 | W5: Exchange | AE5: NSI | AF5: 100000
D6: FundSmith | G6: 9791 | H6: 10821 | J6: Nik | M6: 5000 | N6: 155K | P6: Med | Q6: =#REF!+#REF!+#REF!+#REF!+#REF! -> #REF! | T6: =T4-T5 -> 59 | AE6: Share | AF6: 85000
C7: * | D7: Hargrevaes Lansdown | G7: 970 | H7: 1200 | J7: Les and Jon | M7: 20000 | P7: High | Q7: =SUM(#REF!) -> #REF!
C8: * | D8: Intractive Investor | G8: 7124 | H8: 9587 | J8: Phil | M8: 1500
C9: * | D9: JG ClearWaterCapital | G9: 23501 | M9: =SUM(M5:M8) -> 48500
C10: * | D10: MG ClearWaterCapital inc ISA | G10: =44874+8497 -> 53371 | H10: =68366-23622 -> 44744 | J10: Cars
D11: Current account - Inv, Currt and Holid | E11: Nat West Invest/Holiday - Not EX, Not Prop, Not Current below 4K | G11: 5500 | H11: 5500 | J11: MG | M11: 9000 | P11: =170114-(2*64563) -> 40988
D12: Premium Bonds | E12: Post Office | F12: JG | G12: 50000 | H12: 50000 | J12: Yeti | M12: 11000 | R12: =14514*2 -> 29028 | AE12: Invest | AF12: 40000
D13: Premium Bonds | E13: Post Office | F13: BH | M13: =SUM(M11:M12) -> 20000 | AF13: =SUM(AF5:AF12) -> 225000
D14: Premium Bonds | E14: Post Office | F14: FG | G14: 50000 | H14: 50000 | J14: Rented Properties
C15: 105.06 | D15: Premium Bonds | E15: Post Office | F15: MG | G15: 50000 | H15: 50000 | J15: House | K15: 2bed | M15: =38000+1500 -> 39500 | Q15: 81287
A16: Q3 | B16: Q2 | C16: 44227 | D16: EDSP | E16: equateplus.com | F16: MG | G16: 51310 | H16: 58428 | J16: House | K16: 3bed | M16: =38000+1500 -> 39500 | Q16: =#REF!*2 -> #REF!
A17: 766 | B17: 766 | C17: 556 | D17: Trading Account | E17: III ( both JG and MG) | F17: MGJG | H17: =23622+27004 -> 50626 | J17: Total | M17: =SUM(M15:M16) -> 79000 | N17: 73707 | Q17: =Q15-Q16 -> #REF! | X17: =SUM(A17:A19) -> 1867 | Y17: =X17*V4 -> 191927.6
A18: 504 | B18: 504 | C18: ??? | D18: OWN SAP | E18: equateplus.com | F18: MG | G18: 94206 | H18: 105770
A19: 597 | B19: 555 | C19: 992
A20: 2011 | C20: 99 | D20: SAP Shares | E20: 1 free | F20: MG | J20: SAP Shares | K20: 1 free | N20: 42156 | P20: 37666 | W20: =388*70/1.43 -> 18993.007
A21: 2012 | C21: 96 | D21: SAP Shares | E21: 5 p 3y 3g | F21: MG | J21: SAP Shares | K21: 5 p 3y 3g | N21: 41791 | P21: 35143
A22: 2013 | C22: 87 | D22: SAP Shares | E22: B3K3G1 | F22: MG | J22: SAP Shares | K22: B3K3G1 | N22: 42583
M23: =SUM(M20:M22) -> 0
D25: Total | G25: =SUM(G4:G18) -> 514245 | H25: =SUM(H4:H18) -> 567814 | I25: =#REF!-#REF! -> #REF! | M25: =M9+M17+M13 -> 147500 | Z25: 1155
Q26: 900 | Z26: 80.13
D27: Potential Balance | K27: 77 | AA27: =Z26*Z25 -> 92550.15
D28: Not so liquid | N28: Actual | O28: 31st Dec | P28: 31st Dec | Q28: 31st Dec | R28: 31st Dec | S28: 31st Dec | T28: 31st Dec | Z28: 1.5 | AA28: =AA27/Z28 -> 61700.1
D29: Aston | E29: Sold | G29: 0 | O29: 2015 | P29: 2016 | Q29: 2017 | R29: 2018 | S29: 2019 | T29: 2020 | U29: =T29+1 -> 2021
D30: Golf R | G30: 15000 | N30: Value | O30: 164433.05 | P30: 248589.4 | Q30: 314989.19 | R30: 335945 | S30: 336562 | T30: 374989.19
D31: Motor Bike | G31: 2000 | O31: 0 | P31: 0 | S31: 30000 | T31: 7000
G32: =SUM(G29:G31) -> 17000 | N32: Santandar | O32: 29028
N33: Total | O33: 193461.05 | P33: 248589.4 | Q33: 314989.19 | R33: 335945 | S33: 374989.19 | T33: 381989.19
D34: Less CC Debit | G34: 1600 | P34: 55128.35 | Q34: 66399.786 | R34: =R33-Q33 -> 20955.812
D36: Sub Total | G36: =G27+G32-G34 -> 15400 | N36: Q1 | P36: 282432.89 | Q36: 33843.485 | R36: 8687 | S36: 120736 | Z36: phil | AA36: 1500
N37: Q2 | P37: 294892.7 | Q37: 12459.809 | R37: 5697 | S37: 43735
D38: Tied Assetts | G38: =M25 -> 147500 | N38: Q3 | P38: 310690.69 | Q38: 15797.999 | R38: 37050 | S38: -7000
N39: Q4 | P39: 314989.19 | Q39: 4298.4936 | R39: -31361 | S39: 11634
D40: House | G40: 360000 | Q40: 66399.786 | R40: =SUM(R36:R39) -> 20073 | S40: =SUM(S36:S39) -> 169105
D41: less mortgage | G41: =G40 -> 360000
N42: Budget | O42: 31st Dec | P42: 31st Dec | Q42: 31st Dec | R42: 31st Dec | S42: 31st Dec | T42: 31st Dec | Z42: RN Pension
D43: Nett Worth | G43: =G41+G38+G36 -> 522900 | O43: 2015 | P43: 2016 | Q43: 2017 | R43: 2018 | S43: 2019 | T43: 2020 | Z43: Nissan | AA43: GSR Capital
N44: Base | O44: 105896.15 | P44: 163396.15 | Q44: 193396.15 | R44: 223396.15 | S44: 253396.15 | T44: 283396.15
N45: Save | O45: 30000 | P45: 30000 | Q45: 30000 | R45: 30000 | S45: 30000 | T45: 30000
N46: Extra | O46: 27500
N47: Total | O47: 163396.15 | P47: 193396.15 | Q47: 223396.15 | R47: 253396.15 | S47: 283396.15 | T47: 313396.15
T48: =T47-P33 -> 64806.752

Sheet 02-03022
A1: 201
D2: Liquid Assests | G2: Read This | J2: Tied Assests | N2: 524438 | O2: b
D3: Prod | E3: Where | F3: Who | G3: 44592 | H3: 44592 | J3: Prod | K3: Where | L3: Who | M3: Amount | Q3: At Risk | R3: Not a Risk - Cash
B4: =488+743 -> 1231 | D4: ISA | E4: Ford | F4: JG | G4: 58492 | H4: 59236 | J4: Family Loans | Q4: =#REF!-R4 -> #REF! | R4: =SUM(#REF!) -> #REF! | T4: 130 | V4: 102.8 | W4: Share Price
B5: =504+803 -> 1307 | D5: ISA | E5: Ford | F5: MG | G5: 58492 | H5: 59236 | J5: Faye | M5: 22000 | P5: this is 17k + 5K | T5: 71 | V5: 1.125 | W5: Exchange | AE5: NSI | AF5: 100000
D6: FundSmith | G6: 9271 | H6: 9791 | J6: Nik | M6: 5000 | N6: 155K | P6: Med | Q6: =#REF!+#REF!+#REF!+#REF!+#REF! -> #REF! | T6: =T4-T5 -> 59 | AE6: Share | AF6: 85000
C7: * | D7: Hargrevaes Lansdown | G7: 1011 | H7: 970 | J7: Les and Jon | M7: 20000 | P7: High | Q7: =SUM(#REF!) -> #REF!
C8: * | D8: Intractive Investor | G8: 7331 | H8: 7124 | J8: Phil | M8: 1500
C9: * | D9: JG ClearWaterCapital | G9: 21799 | H9: 23501 | M9: =SUM(M5:M8) -> 48500
C10: * | D10: MG ClearWaterCapital inc ISA | G10: =38941+7936 -> 46877 | H10: =44874+8497 -> 53371 | J10: Cars
D11: Current account - Inv, Currt and Holid | E11: Nat West Invest/Holiday - Not EX, Not Prop, Not Current below 4K | G11: 5500 | H11: 5500 | J11: MG | M11: 9000 | P11: =170114-(2*64563) -> 40988
D12: Premium Bonds | E12: Post Office | F12: JG | G12: 50000 | H12: 50000 | J12: Yeti | M12: 11000 | R12: =14514*2 -> 29028 | AE12: Invest | AF12: 40000
D13: Premium Bonds | E13: Post Office | F13: BH | M13: =SUM(M11:M12) -> 20000 | AF13: =SUM(AF5:AF12) -> 225000
D14: Premium Bonds | E14: Post Office | F14: FG | G14: 50000 | H14: 50000 | J14: Rented Properties
C15: 105.06 | D15: Premium Bonds | E15: Post Office | F15: MG | G15: 50000 | H15: 50000 | J15: House | K15: 2bed | M15: =38000+1500+2500 -> 42000 | Q15: 81287
A16: Q3 | B16: Q2 | C16: 44227 | D16: EDSP | E16: equateplus.com | F16: MG | G16: 46664 | H16: 51310 | J16: House | K16: 3bed | M16: =38000+1500+2500 -> 42000 | Q16: =#REF!*2 -> #REF!
A17: 766 | B17: 766 | C17: 556 | D17: Trading Account | E17: III ( both JG and MG) | F17: MGJG | J17: Total | M17: =SUM(M15:M16) -> 84000 | N17: 73707 | Q17: =Q15-Q16 -> #REF! | X17: =SUM(A17:A19) -> 1867 | Y17: =X17*V4 -> 191927.6
A18: 504 | B18: 504 | C18: ??? | D18: OWN SAP | E18: equateplus.com | F18: MG | G18: 87426 | H18: 94206
A19: 597 | B19: 555 | C19: 992
A20: 2011 | C20: 99 | D20: SAP Shares | E20: 1 free | F20: MG | J20: SAP Shares | K20: 1 free | N20: 42156 | P20: 37666 | W20: =388*70/1.43 -> 18993.007
A21: 2012 | C21: 96 | D21: SAP Shares | E21: 5 p 3y 3g | F21: MG | J21: SAP Shares | K21: 5 p 3y 3g | N21: 41791 | P21: 35143
A22: 2013 | C22: 87 | D22: SAP Shares | E22: B3K3G1 | F22: MG | J22: SAP Shares | K22: B3K3G1 | N22: 42583
M23: =SUM(M20:M22) -> 0
D25: Total | G25: =SUM(G4:G18) -> 492863 | H25: =SUM(H4:H18) -> 514245 | I25: =#REF!-#REF! -> #REF! | M25: =M9+M17+M13 -> 152500 | Z25: 1155
Q26: 900 | Z26: 80.13
D27: Potential Balance | K27: 77 | AA27: =Z26*Z25 -> 92550.15
D28: Not so liquid | N28: Actual | O28: 31st Dec | P28: 31st Dec | Q28: 31st Dec | R28: 31st Dec | S28: 31st Dec | T28: 31st Dec | Z28: 1.5 | AA28: =AA27/Z28 -> 61700.1
D29: Aston | E29: Sold | G29: 0 | O29: 2015 | P29: 2016 | Q29: 2017 | R29: 2018 | S29: 2019 | T29: 2020 | U29: =T29+1 -> 2021
D30: Golf R | G30: 15000 | N30: Value | O30: 164433.05 | P30: 248589.4 | Q30: 314989.19 | R30: 335945 | S30: 336562 | T30: 374989.19
D31: Motor Bike | G31: 2000 | O31: 0 | P31: 0 | S31: 30000 | T31: 7000
G32: =SUM(G29:G31) -> 17000 | N32: Santandar | O32: 29028
N33: Total | O33: 193461.05 | P33: 248589.4 | Q33: 314989.19 | R33: 335945 | S33: 374989.19 | T33: 381989.19
D34: Less CC Debit | G34: 1600 | P34: 55128.35 | Q34: 66399.786 | R34: =R33-Q33 -> 20955.812
D36: Sub Total | G36: =G27+G32-G34 -> 15400 | N36: Q1 | P36: 282432.89 | Q36: 33843.485 | R36: 8687 | S36: 120736 | Z36: phil | AA36: 1500
N37: Q2 | P37: 294892.7 | Q37: 12459.809 | R37: 5697 | S37: 43735
D38: Tied Assetts | G38: =M25 -> 152500 | N38: Q3 | P38: 310690.69 | Q38: 15797.999 | R38: 37050 | S38: -7000
N39: Q4 | P39: 314989.19 | Q39: 4298.4936 | R39: -31361 | S39: 11634
D40: House | G40: 360000 | Q40: 66399.786 | R40: =SUM(R36:R39) -> 20073 | S40: =SUM(S36:S39) -> 169105
D41: less mortgage | G41: =G40 -> 360000
N42: Budget | O42: 31st Dec | P42: 31st Dec | Q42: 31st Dec | R42: 31st Dec | S42: 31st Dec | T42: 31st Dec | Z42: RN Pension
D43: Nett Worth | G43: =G41+G38+G36 -> 527900 | O43: 2015 | P43: 2016 | Q43: 2017 | R43: 2018 | S43: 2019 | T43: 2020 | Z43: Nissan | AA43: GSR Capital
N44: Base | O44: 105896.15 | P44: 163396.15 | Q44: 193396.15 | R44: 223396.15 | S44: 253396.15 | T44: 283396.15
N45: Save | O45: 30000 | P45: 30000 | Q45: 30000 | R45: 30000 | S45: 30000 | T45: 30000
N46: Extra | O46: 27500
N47: Total | O47: 163396.15 | P47: 193396.15 | Q47: 223396.15 | R47: 253396.15 | S47: 283396.15 | T47: 313396.15
T48: =T47-P33 -> 64806.752

Sheet 02-04-22
A1: 201
D2: Liquid Assests | G2: Read This | J2: Tied Assests | N2: 524438 | O2: b
D3: Prod | E3: Where | F3: Who | G3: 44653 | H3: 44620 | J3: Prod | K3: Where | L3: Who | M3: Amount | Q3: At Risk | R3: Not a Risk - Cash
B4: =488+743 -> 1231 | D4: ISA | E4: Ford | F4: JG | G4: =35870+23878 -> 59748 | H4: 58492 | J4: Family Loans | Q4: =#REF!-R4 -> #REF! | R4: =SUM(#REF!) -> #REF! | T4: 130 | V4: 102.8 | W4: Share Price
B5: =504+803 -> 1307 | D5: ISA | E5: Ford | F5: MG | G5: 59749 | H5: 58492 | J5: Faye | M5: 22000 | P5: this is 17k + 5K | T5: 71 | V5: 1.125 | W5: Exchange | AE5: NSI | AF5: 100000
D6: FundSmith | G6: 9670 | H6: 9271 | J6: Nik | M6: 5000 | N6: 155K | P6: Med | Q6: =#REF!+#REF!+#REF!+#REF!+#REF! -> #REF! | T6: =T4-T5 -> 59 | AE6: Share | AF6: 85000
C7: * | D7: Hargrevaes Lansdown | G7: 996 | H7: 1011 | J7: Les and Jon | M7: 20000 | P7: High | Q7: =SUM(#REF!) -> #REF!
C8: * | D8: Intractive Investor | G8: 7894 | H8: 7331 | J8: Phil | M8: 1500
C9: * | D9: JG ClearWaterCapital | G9: 20693 | H9: 21799 | M9: =SUM(M5:M8) -> 48500
C10: * | D10: MG ClearWaterCapital inc ISA | G10: =30794+6737 -> 37531 | H10: =38941+7936 -> 46877 | J10: Cars
D11: Current account - Inv, Currt and Holid | E11: Nat West Invest/Holiday - Not EX, Not Prop, Not Current below 4K | G11: 21000 | H11: 5500 | J11: MG | M11: 9000 | P11: =170114-(2*64563) -> 40988
D12: Premium Bonds | E12: Post Office | F12: JG | G12: 50000 | H12: 50000 | J12: Yeti | M12: 11000 | R12: =14514*2 -> 29028 | AE12: Invest | AF12: 40000
D13: Premium Bonds | E13: Post Office | F13: BH | M13: =SUM(M11:M12) -> 20000 | AF13: =SUM(AF5:AF12) -> 225000
D14: Premium Bonds | E14: Post Office | F14: FG | G14: 50000 | H14: 50000 | J14: Rented Properties
C15: 105.06 | D15: Premium Bonds | E15: Post Office | F15: MG | G15: 50000 | H15: 50000 | J15: House | K15: 2bed | M15: =38000+1500+2500 -> 42000 | Q15: 81287
C16: 556 | D16: EDSP | E16: equateplus.com | F16: MG | G16: 46765 | H16: 46664 | J16: House | K16: 3bed | M16: =38000+1500+2500 -> 42000 | Q16: =#REF!*2 -> #REF!
D17: Trading Account | E17: III ( both JG and MG) | F17: MGJG | J17: Total | M17: =SUM(M15:M16) -> 84000 | N17: 73707 | Q17: =Q15-Q16 -> #REF! | X17: =SUM(A17:A19) -> 597 | Y17: =X17*V4 -> 61371.6
C18: 1066 | D18: OWN SAP | E18: equateplus.com | F18: MG | G18: 89616 | H18: 87426
A19: 597 | B19: 555 | C19: 992
A20: 2011 | C20: 99 | D20: SAP Shares | E20: 1 free | F20: MG | J20: SAP Shares | K20: 1 free | N20: 42156 | P20: 37666 | W20: =388*70/1.43 -> 18993.007
A21: 2012 | C21: 96 | D21: SAP Shares | E21: 5 p 3y 3g | F21: MG | J21: SAP Shares | K21: 5 p 3y 3g | N21: 41791 | P21: 35143
A22: 2013 | C22: 87 | D22: SAP Shares | E22: B3K3G1 | F22: MG | J22: SAP Shares | K22: B3K3G1 | N22: 42583
M23: =SUM(M20:M22) -> 0
D25: Total | G25: =SUM(G4:G18) -> 503662 | H25: =SUM(H4:H18) -> 492863 | I25: =#REF!-#REF! -> #REF! | M25: =M9+M17+M13 -> 152500 | Z25: 1155
Q26: 900 | Z26: 80.13
D27: Potential Balance | K27: 77 | AA27: =Z26*Z25 -> 92550.15
D28: Not so liquid | N28: Actual | O28: 31st Dec | P28: 31st Dec | Q28: 31st Dec | R28: 31st Dec | S28: 31st Dec | T28: 31st Dec | Z28: 1.5 | AA28: =AA27/Z28 -> 61700.1
D29: Aston | E29: Sold | G29: 0 | O29: 2015 | P29: 2016 | Q29: 2017 | R29: 2018 | S29: 2019 | T29: 2020 | U29: =T29+1 -> 2021
D30: Golf R | G30: 15000 | N30: Value | O30: 164433.05 | P30: 248589.4 | Q30: 314989.19 | R30: 335945 | S30: 336562 | T30: 374989.19
D31: Motor Bike | G31: 2000 | O31: 0 | P31: 0 | S31: 30000 | T31: 7000
G32: =SUM(G29:G31) -> 17000 | N32: Santandar | O32: 29028
N33: Total | O33: 193461.05 | P33: 248589.4 | Q33: 314989.19 | R33: 335945 | S33: 374989.19 | T33: 381989.19
D34: Less CC Debit | G34: 1600 | P34: 55128.35 | Q34: 66399.786 | R34: =R33-Q33 -> 20955.812
D36: Sub Total | G36: =G27+G32-G34 -> 15400 | N36: Q1 | P36: 282432.89 | Q36: 33843.485 | R36: 8687 | S36: 120736 | Z36: phil | AA36: 1500
N37: Q2 | P37: 294892.7 | Q37: 12459.809 | R37: 5697 | S37: 43735
D38: Tied Assetts | G38: =M25 -> 152500 | N38: Q3 | P38: 310690.69 | Q38: 15797.999 | R38: 37050 | S38: -7000
N39: Q4 | P39: 314989.19 | Q39: 4298.4936 | R39: -31361 | S39: 11634
D40: House | G40: 360000 | Q40: 66399.786 | R40: =SUM(R36:R39) -> 20073 | S40: =SUM(S36:S39) -> 169105
D41: less mortgage | G41: =G40 -> 360000
N42: Budget | O42: 31st Dec | P42: 31st Dec | Q42: 31st Dec | R42: 31st Dec | S42: 31st Dec | T42: 31st Dec | Z42: RN Pension
D43: Nett Worth | G43: =G41+G38+G36 -> 527900 | O43: 2015 | P43: 2016 | Q43: 2017 | R43: 2018 | S43: 2019 | T43: 2020 | Z43: Nissan | AA43: GSR Capital
N44: Base | O44: 105896.15 | P44: 163396.15 | Q44: 193396.15 | R44: 223396.15 | S44: 253396.15 | T44: 283396.15
N45: Save | O45: 30000 | P45: 30000 | Q45: 30000 | R45: 30000 | S45: 30000 | T45: 30000
N46: Extra | O46: 27500
N47: Total | O47: 163396.15 | P47: 193396.15 | Q47: 223396.15 | R47: 253396.15 | S47: 283396.15 | T47: 313396.15
T48: =T47-P33 -> 64806.752

Sheet 30-04-22
A1: 201
D2: Liquid Assests | G2: Read This | J2: Tied Assests | N2: 524438 | O2: b
D3: Prod | E3: Where | F3: Who | G3: 44681 | H3: 44653 | J3: Prod | K3: Where | L3: Who | M3: Amount | Q3: At Risk | R3: Not a Risk - Cash
B4: =488+743 -> 1231 | D4: ISA | E4: Ford | F4: JG | G4: =34643+23072 -> 57715 | H4: =35870+23878 -> 59748 | J4: Family Loans | Q4: =#REF!-R4 -> #REF! | R4: =SUM(#REF!) -> #REF! | T4: 130 | V4: 102.8 | W4: Share Price
B5: =504+803 -> 1307 | D5: ISA | E5: Ford | F5: MG | G5: =34643+23072 -> 57715 | H5: 59749 | J5: Faye | M5: 22000 | P5: this is 17k + 5K | T5: 71 | V5: 1.125 | W5: Exchange | AE5: NSI | AF5: 100000
D6: FundSmith | G6: 9622 | H6: 9670 | J6: Nik | M6: 5000 | N6: 155K | P6: Med | Q6: =#REF!+#REF!+#REF!+#REF!+#REF! -> #REF! | T6: =T4-T5 -> 59 | AE6: Share | AF6: 85000
C7: * | D7: Hargrevaes Lansdown | G7: 927 | H7: 996 | J7: Les and Jon | M7: 20000 | P7: High | Q7: =SUM(#REF!) -> #REF!
C8: * | D8: Intractive Investor | G8: 7708 | H8: 7894 | J8: Phil | M8: 1500
C9: * | D9: JG ClearWaterCapital | G9: 19549 | H9: 20693 | M9: =SUM(M5:M8) -> 48500
C10: * | D10: MG ClearWaterCapital inc ISA | G10: =28244+6192 -> 34436 | H10: =30794+6737 -> 37531 | J10: Cars
D11: Current account - Inv, Currt and Holid | E11: Nat West Invest/Holiday - Not EX, Not Prop, Not Current below 4K | G11: 21000 | H11: 21000 | J11: MG | M11: 9000 | P11: =170114-(2*64563) -> 40988
D12: Premium Bonds | E12: Post Office | F12: JG | G12: 50000 | H12: 50000 | J12: Yeti | M12: 11000 | R12: =14514*2 -> 29028 | AE12: Invest | AF12: 40000
D13: Premium Bonds | E13: Post Office | F13: BH | M13: =SUM(M11:M12) -> 20000 | AF13: =SUM(AF5:AF12) -> 225000
D14: Premium Bonds | E14: Post Office | F14: FG | G14: 50000 | H14: 50000 | J14: Rented Properties
C15: 105.06 | D15: Premium Bonds | E15: Post Office | F15: MG | G15: 50000 | H15: 50000 | J15: House | K15: 2bed | M15: =38000+1500+2500 -> 42000 | Q15: 81287
C16: 556 | D16: EDSP | E16: equateplus.com | F16: MG | G16: 45549 | H16: 46765 | J16: House | K16: 3bed | M16: =38000+1500+2500 -> 42000 | Q16: =#REF!*2 -> #REF!
D17: Trading Account | E17: III ( both JG and MG) | F17: MGJG | J17: Total | M17: =SUM(M15:M16) -> 84000 | N17: 73707 | Q17: =Q15-Q16 -> #REF! | X17: =SUM(A17:A19) -> 597 | Y17: =X17*V4 -> 61371.6
C18: 1089 | D18: OWN SAP | E18: equateplus.com | F18: MG | G18: 89104 | H18: 89616
A19: 597 | B19: 555 | C19: 992
A20: 2011 | C20: 99 | D20: SAP Shares | E20: 1 free | F20: MG | J20: SAP Shares | K20: 1 free | N20: 42156 | P20: 37666 | W20: =388*70/1.43 -> 18993.007
A21: 2012 | C21: 96 | D21: SAP Shares | E21: 5 p 3y 3g | F21: MG | J21: SAP Shares | K21: 5 p 3y 3g | N21: 41791 | P21: 35143
A22: 2013 | C22: 87 | D22: SAP Shares | E22: B3K3G1 | F22: MG | J22: SAP Shares | K22: B3K3G1 | N22: 42583
M23: =SUM(M20:M22) -> 0
D25: Total | G25: =SUM(G4:G18) -> 493325 | H25: =SUM(H4:H18) -> 503662 | I25: =#REF!-#REF! -> #REF! | M25: =M9+M17+M13 -> 152500 | Z25: 1155
Q26: 900 | Z26: 80.13
D27: Potential Balance | K27: 77 | AA27: =Z26*Z25 -> 92550.15
D28: Not so liquid | N28: Actual | O28: 31st Dec | P28: 31st Dec | Q28: 31st Dec | R28: 31st Dec | S28: 31st Dec | T28: 31st Dec | Z28: 1.5 | AA28: =AA27/Z28 -> 61700.1
D29: Aston | E29: Sold | G29: 0 | O29: 2015 | P29: 2016 | Q29: 2017 | R29: 2018 | S29: 2019 | T29: 2020 | U29: =T29+1 -> 2021
D30: Golf R | G30: 15000 | N30: Value | O30: 164433.05 | P30: 248589.4 | Q30: 314989.19 | R30: 335945 | S30: 336562 | T30: 374989.19
D31: Motor Bike | G31: 2000 | O31: 0 | P31: 0 | S31: 30000 | T31: 7000
G32: =SUM(G29:G31) -> 17000 | N32: Santandar | O32: 29028
N33: Total | O33: 193461.05 | P33: 248589.4 | Q33: 314989.19 | R33: 335945 | S33: 374989.19 | T33: 381989.19
D34: Less CC Debit | G34: 1600 | P34: 55128.35 | Q34: 66399.786 | R34: =R33-Q33 -> 20955.812
D36: Sub Total | G36: =G27+G32-G34 -> 15400 | N36: Q1 | P36: 282432.89 | Q36: 33843.485 | R36: 8687 | S36: 120736 | Z36: phil | AA36: 1500
N37: Q2 | P37: 294892.7 | Q37: 12459.809 | R37: 5697 | S37: 43735
D38: Tied Assetts | G38: =M25 -> 152500 | N38: Q3 | P38: 310690.69 | Q38: 15797.999 | R38: 37050 | S38: -7000
N39: Q4 | P39: 314989.19 | Q39: 4298.4936 | R39: -31361 | S39: 11634
D40: House | G40: 360000 | Q40: 66399.786 | R40: =SUM(R36:R39) -> 20073 | S40: =SUM(S36:S39) -> 169105
D41: less mortgage | G41: =G40 -> 360000
N42: Budget | O42: 31st Dec | P42: 31st Dec | Q42: 31st Dec | R42: 31st Dec | S42: 31st Dec | T42: 31st Dec | Z42: RN Pension
D43: Nett Worth | G43: =G41+G38+G36 -> 527900 | O43: 2015 | P43: 2016 | Q43: 2017 | R43: 2018 | S43: 2019 | T43: 2020 | Z43: Nissan | AA43: GSR Capital
N44: Base | O44: 105896.15 | P44: 163396.15 | Q44: 193396.15 | R44: 223396.15 | S44: 253396.15 | T44: 283396.15
N45: Save | O45: 30000 | P45: 30000 | Q45: 30000 | R45: 30000 | S45: 30000 | T45: 30000
N46: Extra | O46: 27500
N47: Total | O47: 163396.15 | P47: 193396.15 | Q47: 223396.15 | R47: 253396.15 | S47: 283396.15 | T47: 313396.15
T48: =T47-P33 -> 64806.752

Sheet 31-05-22
A1: 201
D2: Liquid Assests | G2: Read This | J2: Tied Assests | N2: 524438 | O2: b
D3: Prod | E3: Where | F3: Who | G3: 44712 | H3: 44681 | J3: Prod | K3: Where | L3: Who | M3: Amount | Q3: At Risk | R3: Not a Risk - Cash
B4: =488+743 -> 1231 | D4: ISA | E4: Ford | F4: JG | G4: 56526 | H4: =34643+23072 -> 57715 | J4: Family Loans | Q4: =#REF!-R4 -> #REF! | R4: =SUM(#REF!) -> #REF! | T4: 130 | V4: 102.8 | W4: Share Price
B5: =504+803 -> 1307 | D5: ISA | E5: Ford | F5: MG | G5: 56526 | H5: =34643+23072 -> 57715 | J5: Faye | M5: 22000 | P5: this is 17k + 5K | T5: 71 | V5: 1.125 | W5: Exchange | AE5: NSI | AF5: 100000
D6: FundSmith | G6: 9172 | H6: 9622 | J6: Nik | M6: 5000 | N6: 155K | P6: Med | Q6: =#REF!+#REF!+#REF!+#REF!+#REF! -> #REF! | T6: =T4-T5 -> 59 | AE6: Share | AF6: 85000
C7: * | D7: Hargrevaes Lansdown | G7: 859 | H7: 927 | J7: Les and Jon | M7: 20000 | P7: High | Q7: =SUM(#REF!) -> #REF!
C8: * | D8: Intractive Investor | G8: 7698 | H8: 7708 | J8: Phil | M8: 1500
C9: * | D9: JG ClearWaterCapital | G9: 15770 | H9: 19549 | M9: =SUM(M5:M8) -> 48500
C10: * | D10: MG ClearWaterCapital inc ISA | G10: =15104+3143 -> 18247 | H10: =28244+6192 -> 34436 | J10: Cars
D11: Current account - Inv, Currt and Holid | E11: Nat West Invest/Holiday - Not EX, Not Prop, Not Current below 4K | G11: 18000 | H11: 21000 | J11: MG | M11: 9000 | P11: =170114-(2*64563) -> 40988
D12: Premium Bonds | E12: Post Office | F12: JG | G12: 50000 | H12: 50000 | J12: Yeti | M12: 11000 | R12: =14514*2 -> 29028 | AE12: Invest | AF12: 40000
D13: Premium Bonds | E13: Post Office | F13: BH | M13: =SUM(M11:M12) -> 20000 | AF13: =SUM(AF5:AF12) -> 225000
D14: Premium Bonds | E14: Post Office | F14: FG | G14: 50000 | H14: 50000 | J14: Rented Properties
C15: 105.06 | D15: Premium Bonds | E15: Post Office | F15: MG | G15: 50000 | H15: 50000 | J15: House | K15: 2bed | M15: =38000+1500+2500 -> 42000 | Q15: 81287
C16: 567 | D16: EDSP | E16: equateplus.com | F16: MG | G16: 44832 | H16: 45549 | J16: House | K16: 3bed | M16: =38000+1500+2500 -> 42000 | Q16: =#REF!*2 -> #REF!
D17: Trading Account | E17: III ( both JG and MG) | F17: MGJG | J17: Total | M17: =SUM(M15:M16) -> 84000 | N17: 73707 | Q17: =Q15-Q16 -> #REF! | X17: =SUM(A17:A19) -> 597 | Y17: =X17*V4 -> 61371.6
C18: 1130 | D18: OWN SAP | E18: equateplus.com | F18: MG | G18: 89270 | H18: 89104
A19: 597 | B19: 555 | C19: 992
A20: 2011 | C20: 99 | D20: SAP Shares | E20: 1 free | F20: MG | J20: SAP Shares | K20: 1 free | N20: 42156 | P20: 37666 | W20: =388*70/1.43 -> 18993.007
A21: 2012 | C21: 96 | D21: SAP Shares | E21: 5 p 3y 3g | F21: MG | J21: SAP Shares | K21: 5 p 3y 3g | N21: 41791 | P21: 35143
A22: 2013 | C22: 87 | D22: SAP Shares | E22: B3K3G1 | F22: MG | J22: SAP Shares | K22: B3K3G1 | N22: 42583
M23: =SUM(M20:M22) -> 0
D25: Total | G25: =SUM(G4:G18) -> 466900 | H25: =SUM(H4:H18) -> 493325 | I25: =G25-H25 -> -26425 | M25: =M9+M17+M13 -> 152500 | Z25: 1155
Q26: 900 | Z26: 80.13
D27: Potential Balance | K27: 77 | AA27: =Z26*Z25 -> 92550.15
D28: Not so liquid | N28: Actual | O28: 31st Dec | P28: 31st Dec | Q28: 31st Dec | R28: 31st Dec | S28: 31st Dec | T28: 31st Dec | Z28: 1.5 | AA28: =AA27/Z28 -> 61700.1
D29: Aston | E29: Sold | G29: 0 | O29: 2015 | P29: 2016 | Q29: 2017 | R29: 2018 | S29: 2019 | T29: 2020 | U29: =T29+1 -> 2021
D30: Golf R | G30: 15000 | N30: Value | O30: 164433.05 | P30: 248589.4 | Q30: 314989.19 | R30: 335945 | S30: 336562 | T30: 374989.19
D31: Motor Bike | G31: 2000 | O31: 0 | P31: 0 | S31: 30000 | T31: 7000
G32: =SUM(G29:G31) -> 17000 | N32: Santandar | O32: 29028
N33: Total | O33: 193461.05 | P33: 248589.4 | Q33: 314989.19 | R33: 335945 | S33: 374989.19 | T33: 381989.19
D34: Less CC Debit | G34: 1600 | P34: 55128.35 | Q34: 66399.786 | R34: =R33-Q33 -> 20955.812
D36: Sub Total | G36: =G27+G32-G34 -> 15400 | N36: Q1 | P36: 282432.89 | Q36: 33843.485 | R36: 8687 | S36: 120736 | Z36: phil | AA36: 1500
N37: Q2 | P37: 294892.7 | Q37: 12459.809 | R37: 5697 | S37: 43735
D38: Tied Assetts | G38: =M25 -> 152500 | N38: Q3 | P38: 310690.69 | Q38: 15797.999 | R38: 37050 | S38: -7000
N39: Q4 | P39: 314989.19 | Q39: 4298.4936 | R39: -31361 | S39: 11634
D40: House | G40: 360000 | Q40: 66399.786 | R40: =SUM(R36:R39) -> 20073 | S40: =SUM(S36:S39) -> 169105
D41: less mortgage | G41: =G40 -> 360000
N42: Budget | O42: 31st Dec | P42: 31st Dec | Q42: 31st Dec | R42: 31st Dec | S42: 31st Dec | T42: 31st Dec | Z42: RN Pension
D43: Nett Worth | G43: =G41+G38+G36 -> 527900 | O43: 2015 | P43: 2016 | Q43: 2017 | R43: 2018 | S43: 2019 | T43: 2020 | Z43: Nissan | AA43: GSR Capital
N44: Base | O44: 105896.15 | P44: 163396.15 | Q44: 193396.15 | R44: 223396.15 | S44: 253396.15 | T44: 283396.15
N45: Save | O45: 30000 | P45: 30000 | Q45: 30000 | R45: 30000 | S45: 30000 | T45: 30000
N46: Extra | O46: 27500
N47: Total | O47: 163396.15 | P47: 193396.15 | Q47: 223396.15 | R47: 253396.15 | S47: 283396.15 | T47: 313396.15
T48: =T47-P33 -> 64806.752

Sheet 30-06-22
A1: 201
D2: Liquid Assests | G2: Read This | J2: Tied Assests | N2: 524438 | O2: b
D3: Prod | E3: Where | F3: Who | G3: 44742 | H3: 44712 | J3: Prod | K3: Where | L3: Who | M3: Amount | Q3: At Risk | R3: Not a Risk - Cash
B4: =488+743 -> 1231 | D4: ISA | E4: Ford | F4: JG | G4: 53757 | H4: 56526 | J4: Family Loans | Q4: =#REF!-R4 -> #REF! | R4: =SUM(#REF!) -> #REF! | T4: 130 | V4: 102.8 | W4: Share Price
B5: =504+803 -> 1307 | D5: ISA | E5: Ford | F5: MG | G5: 53757 | H5: 56526 | J5: Faye | M5: 22000 | P5: this is 17k + 5K | T5: 71 | V5: 1.125 | W5: Exchange | AE5: NSI | AF5: 100000
D6: FundSmith | G6: 8897 | H6: 9172 | J6: Nik | M6: 5000 | N6: 155K | P6: Med | Q6: =#REF!+#REF!+#REF!+#REF!+#REF! -> #REF! | T6: =T4-T5 -> 59 | AE6: Share | AF6: 85000
C7: * | D7: Hargrevaes Lansdown | G7: 824 | H7: 859 | J7: Les and Jon | M7: 20000 | P7: High | Q7: =SUM(#REF!) -> #REF!
C8: * | D8: Intractive Investor | G8: 6575 | H8: 7698 | J8: Phil | M8: 1500
C9: * | D9: JG ClearWaterCapital | G9: 13758 | H9: 15770 | M9: =SUM(M5:M8) -> 48500
C10: * | D10: MG ClearWaterCapital inc ISA | G10: =1899+9732 -> 11631 | H10: =15104+3143 -> 18247 | J10: Cars
D11: Current account - Inv, Currt and Holid | E11: Nat West Invest/Holiday - Not EX, Not Prop, Not Current below 4K | G11: 18000 | H11: 18000 | J11: MG | M11: 9000 | P11: =170114-(2*64563) -> 40988
D12: Premium Bonds | E12: Post Office | F12: JG | G12: 50000 | H12: 50000 | J12: Yeti | M12: 11000 | R12: =14514*2 -> 29028 | AE12: Invest | AF12: 40000
D13: Premium Bonds | E13: Post Office | F13: BH | M13: =SUM(M11:M12) -> 20000 | AF13: =SUM(AF5:AF12) -> 225000
D14: Premium Bonds | E14: Post Office | F14: FG | G14: 50000 | H14: 50000 | J14: Rented Properties
C15: 105.06 | D15: Premium Bonds | E15: Post Office | F15: MG | G15: 50000 | H15: 50000 | J15: House | K15: 2bed | M15: =38000+1500+2500 -> 42000 | Q15: 81287
C16: 567 | D16: EDSP | E16: equateplus.com | F16: MG | G16: 42479 | H16: 44832 | J16: House | K16: 3bed | M16: =38000+1500+2500 -> 42000 | Q16: =#REF!*2 -> #REF!
D17: Trading Account | E17: III ( both JG and MG) | F17: MGJG | J17: Total | M17: =SUM(M15:M16) -> 84000 | N17: 73707 | Q17: =Q15-Q16 -> #REF! | X17: =SUM(A17:A19) -> 597 | Y17: =X17*V4 -> 61371.6
C18: 1130 | D18: OWN SAP | E18: equateplus.com | F18: MG | G18: 86060 | H18: 89270
A19: 597 | B19: 555 | C19: 992
A20: 2011 | C20: 99 | D20: SAP Shares | E20: 1 free | F20: MG | J20: SAP Shares | K20: 1 free | N20: 42156 | P20: 37666 | W20: =388*70/1.43 -> 18993.007
A21: 2012 | C21: 96 | D21: SAP Shares | E21: 5 p 3y 3g | F21: MG | J21: SAP Shares | K21: 5 p 3y 3g | N21: 41791 | P21: 35143
A22: 2013 | C22: 87 | D22: SAP Shares | E22: B3K3G1 | F22: MG | J22: SAP Shares | K22: B3K3G1 | N22: 42583
M23: =SUM(M20:M22) -> 0
D25: Total | G25: =SUM(G4:G18) -> 445738 | H25: =SUM(H4:H18) -> 466900 | I25: =G25-H25 -> -21162 | M25: =M9+M17+M13 -> 152500 | Z25: 1155
Q26: 900 | Z26: 80.13
D27: Potential Balance | K27: 77 | AA27: =Z26*Z25 -> 92550.15
D28: Not so liquid | N28: Actual | O28: 31st Dec | P28: 31st Dec | Q28: 31st Dec | R28: 31st Dec | S28: 31st Dec | T28: 31st Dec | Z28: 1.5 | AA28: =AA27/Z28 -> 61700.1
D29: Aston | E29: Sold | G29: 0 | O29: 2015 | P29: 2016 | Q29: 2017 | R29: 2018 | S29: 2019 | T29: 2020 | U29: =T29+1 -> 2021
D30: Golf R | G30: 15000 | N30: Value | O30: 164433.05 | P30: 248589.4 | Q30: 314989.19 | R30: 335945 | S30: 336562 | T30: 374989.19
D31: Motor Bike | G31: 2000 | O31: 0 | P31: 0 | S31: 30000 | T31: 7000
G32: =SUM(G29:G31) -> 17000 | N32: Santandar | O32: 29028
N33: Total | O33: 193461.05 | P33: 248589.4 | Q33: 314989.19 | R33: 335945 | S33: 374989.19 | T33: 381989.19
D34: Less CC Debit | P34: 55128.35 | Q34: 66399.786 | R34: =R33-Q33 -> 20955.812
D36: Sub Total | G36: =G27+G32-G34 -> 17000 | N36: Q1 | P36: 282432.89 | Q36: 33843.485 | R36: 8687 | S36: 120736 | Z36: phil | AA36: 1500
N37: Q2 | P37: 294892.7 | Q37: 12459.809 | R37: 5697 | S37: 43735
D38: Tied Assetts | G38: =M25 -> 152500 | N38: Q3 | P38: 310690.69 | Q38: 15797.999 | R38: 37050 | S38: -7000
N39: Q4 | P39: 314989.19 | Q39: 4298.4936 | R39: -31361 | S39: 11634
D40: House | G40: 360000 | Q40: 66399.786 | R40: =SUM(R36:R39) -> 20073 | S40: =SUM(S36:S39) -> 169105
D41: less mortgage | G41: =G40 -> 360000
N42: Budget | O42: 31st Dec | P42: 31st Dec | Q42: 31st Dec | R42: 31st Dec | S42: 31st Dec | T42: 31st Dec | Z42: RN Pension
D43: Nett Worth | G43: =G41+G38+G36 -> 529500 | O43: 2015 | P43: 2016 | Q43: 2017 | R43: 2018 | S43: 2019 | T43: 2020 | Z43: Nissan | AA43: GSR Capital
N44: Base | O44: 105896.15 | P44: 163396.15 | Q44: 193396.15 | R44: 223396.15 | S44: 253396.15 | T44: 283396.15
N45: Save | O45: 30000 | P45: 30000 | Q45: 30000 | R45: 30000 | S45: 30000 | T45: 30000
N46: Extra | O46: 27500
N47: Total | O47: 163396.15 | P47: 193396.15 | Q47: 223396.15 | R47: 253396.15 | S47: 283396.15 | T47: 313396.15
T48: =T47-P33 -> 64806.752

Sheet 31-07-22
A1: 201
D2: Liquid Assests | G2: Read This | J2: Tied Assests | N2: 524438 | O2: b
D3: Prod | E3: Where | F3: Who | G3: 44773 | H3: 44742 | J3: Prod | K3: Where | L3: Who | M3: Amount | Q3: At Risk | R3: Not a Risk - Cash
B4: =488+743 -> 1231 | D4: ISA | E4: Ford | F4: JG | G4: =34058+22590 -> 56648 | H4: 53757 | J4: Family Loans | Q4: =#REF!-R4 -> #REF! | R4: =SUM(#REF!) -> #REF! | T4: 130 | V4: 102.8 | W4: Share Price
B5: =504+803 -> 1307 | D5: ISA | E5: Ford | F5: MG | G5: =34058+22590 -> 56648 | H5: 53757 | J5: Faye | M5: 22000 | P5: this is 17k + 5K | T5: 71 | V5: 1.125 | W5: Exchange | AE5: NSI | AF5: 100000
D6: FundSmith | G6: 9549 | H6: 8897 | J6: Nik | M6: 5000 | N6: 155K | P6: Med | Q6: =#REF!+#REF!+#REF!+#REF!+#REF! -> #REF! | T6: =T4-T5 -> 59 | AE6: Share | AF6: 85000
C7: * | D7: Hargrevaes Lansdown | G7: 923 | H7: 824 | J7: ECC | M7: 2500 | P7: High | Q7: =SUM(#REF!) -> #REF!
C8: * | D8: Intractive Investor | G8: 6942 | H8: 6575 | J8: Les and Jon | M8: 20000
C9: * | D9: JG ClearWaterCapital | G9: 13887 | H9: 13758 | J9: Phil | M9: 1500
C10: * | D10: MG ClearWaterCapital inc ISA | G10: =2143+9834 -> 11977 | H10: =1899+9732 -> 11631 | M10: =SUM(M5:M9) -> 51000
D11: Current account - Inv, Currt and Holid | E11: Nat West Invest/Holiday - Not EX, Not Prop, Not Current below 4K | G11: 13000 | H11: 18000 | J11: Cars | P11: =170114-(2*64563) -> 40988
D12: Premium Bonds | E12: Post Office | F12: JG | G12: 50000 | H12: 50000 | J12: MG | M12: 9000 | R12: =14514*2 -> 29028 | AE12: Invest | AF12: 40000
D13: Premium Bonds | E13: Post Office | F13: BH | J13: Golf | AF13: =SUM(AF5:AF12) -> 225000
D14: Premium Bonds | E14: Post Office | F14: FG | G14: 50000 | H14: 50000 | J14: Yeti | M14: 11000
C15: 105.06 | D15: Premium Bonds | E15: Post Office | F15: MG | G15: 50000 | H15: 50000 | M15: =SUM(M12:M14) -> 20000 | Q15: 81287
C16: 567 | D16: EDSP | E16: equateplus.com | F16: MG | G16: 43212 | H16: 42479 | J16: Rented Properties | Q16: =#REF!*2 -> #REF!
D17: Trading Account | E17: III ( both JG and MG) | F17: MGJG | J17: House | K17: 2bed | M17: =38000+1500+2500 -> 42000 | Q17: =Q15-Q16 -> #REF! | X17: =SUM(A17:A19) -> 597 | Y17: =X17*V4 -> 61371.6
C18: 1130 | D18: OWN SAP | E18: equateplus.com | F18: MG | G18: 89136 | H18: 86060 | J18: House | K18: 3bed | M18: =38000+1500+2500+2500 -> 44500
A19: 597 | B19: 555 | C19: 992 | J19: Total | M19: =SUM(M17:M18) -> 86500 | N19: 73707
A20: 2011 | C20: 99 | D20: SAP Shares | E20: 1 free | F20: MG | J20: SAP Shares | K20: 1 free | N20: 42156 | P20: 37666 | W20: =388*70/1.43 -> 18993.007
A21: 2012 | C21: 96 | D21: SAP Shares | E21: 5 p 3y 3g | F21: MG | J21: SAP Shares | K21: 5 p 3y 3g | N21: 41791 | P21: 35143
A22: 2013 | C22: 87 | D22: SAP Shares | E22: B3K3G1 | F22: MG | J22: SAP Shares | K22: B3K3G1 | N22: 42583
M23: =SUM(M20:M22) -> 0
D25: Total | G25: =SUM(G4:G18) -> 451922 | H25: =SUM(H4:H18) -> 445738 | I25: =G25-H25 -> 6184 | M25: =M10+M19+M15 -> 157500 | Z25: 1155
Q26: 900 | Z26: 80.13
D27: Potential Balance | K27: 77 | AA27: =Z26*Z25 -> 92550.15
D28: Not so liquid | N28: Actual | O28: 31st Dec | P28: 31st Dec | Q28: 31st Dec | R28: 31st Dec | S28: 31st Dec | T28: 31st Dec | Z28: 1.5 | AA28: =AA27/Z28 -> 61700.1
D29: Aston | E29: Sold | G29: 0 | O29: 2015 | P29: 2016 | Q29: 2017 | R29: 2018 | S29: 2019 | T29: 2020 | U29: =T29+1 -> 2021
D30: Golf R | G30: 15000 | N30: Value | O30: 164433.05 | P30: 248589.4 | Q30: 314989.19 | R30: 335945 | S30: 336562 | T30: 374989.19
D31: Motor Bike | G31: 2000 | O31: 0 | P31: 0 | S31: 30000 | T31: 7000
G32: =SUM(G29:G31) -> 17000 | N32: Santandar | O32: 29028
N33: Total | O33: 193461.05 | P33: 248589.4 | Q33: 314989.19 | R33: 335945 | S33: 374989.19 | T33: 381989.19
D34: Less CC Debit | P34: 55128.35 | Q34: 66399.786 | R34: =R33-Q33 -> 20955.812
D36: Sub Total | G36: =G27+G32-G34 -> 17000 | N36: Q1 | P36: 282432.89 | Q36: 33843.485 | R36: 8687 | S36: 120736 | Z36: phil | AA36: 1500
N37: Q2 | P37: 294892.7 | Q37: 12459.809 | R37: 5697 | S37: 43735
D38: Tied Assetts | G38: =M25 -> 157500 | N38: Q3 | P38: 310690.69 | Q38: 15797.999 | R38: 37050 | S38: -7000
N39: Q4 | P39: 314989.19 | Q39: 4298.4936 | R39: -31361 | S39: 11634
D40: House | G40: 360000 | Q40: 66399.786 | R40: =SUM(R36:R39) -> 20073 | S40: =SUM(S36:S39) -> 169105
D41: less mortgage | G41: =G40 -> 360000
N42: Budget | O42: 31st Dec | P42: 31st Dec | Q42: 31st Dec | R42: 31st Dec | S42: 31st Dec | T42: 31st Dec | Z42: RN Pension
D43: Nett Worth | G43: =G41+G38+G36 -> 534500 | O43: 2015 | P43: 2016 | Q43: 2017 | R43: 2018 | S43: 2019 | T43: 2020 | Z43: Nissan | AA43: GSR Capital
N44: Base | O44: 105896.15 | P44: 163396.15 | Q44: 193396.15 | R44: 223396.15 | S44: 253396.15 | T44: 283396.15
N45: Save | O45: 30000 | P45: 30000 | Q45: 30000 | R45: 30000 | S45: 30000 | T45: 30000
N46: Extra | O46: 27500
N47: Total | O47: 163396.15 | P47: 193396.15 | Q47: 223396.15 | R47: 253396.15 | S47: 283396.15 | T47: 313396.15
T48: =T47-P33 -> 64806.752

Sheet 31-08-22
A1: 201
D2: Liquid Assests | G2: Read This | J2: Tied Assests | N2: 524438 | O2: b
D3: Prod | E3: Where | F3: Who | G3: 44804 | H3: 44773 | J3: Prod | K3: Where | L3: Who | M3: Amount | Q3: At Risk | R3: Not a Risk - Cash
B4: =488+743 -> 1231 | D4: ISA | E4: Ford | F4: JG | G4: =56278 -> 56278 | H4: =34058+22590 -> 56648 | J4: Family Loans | Q4: =#REF!-R4 -> #REF! | R4: =SUM(#REF!) -> #REF! | T4: 130 | V4: 102.8 | W4: Share Price
B5: =504+803 -> 1307 | D5: ISA | E5: Ford | F5: MG | G5: =56278 -> 56278 | H5: =34058+22590 -> 56648 | J5: Faye | M5: 22000 | P5: this is 17k + 5K | T5: 71 | V5: 1.125 | W5: Exchange | AE5: NSI | AF5: 100000
D6: FundSmith | G6: 9477 | H6: 9549 | J6: Nik | M6: 5000 | N6: 155K | P6: Med | Q6: =#REF!+#REF!+#REF!+#REF!+#REF! -> #REF! | T6: =T4-T5 -> 59 | AE6: Share | AF6: 85000
C7: * | D7: Hargrevaes Lansdown | G7: 933 | H7: 923 | J7: ECC | M7: 2500 | P7: High | Q7: =SUM(#REF!) -> #REF!
C8: * | D8: Intractive Investor | G8: 6751 | H8: 6942 | J8: Les and Jon | M8: 20000
C9: * | D9: JG ClearWaterCapital | G9: 13350 | H9: 13887 | J9: Phil | M9: 1500
C10: * | D10: MG ClearWaterCapital inc ISA | G10: =8577.07+ 2108.34 -> 10685.41 | H10: =2143+9834 -> 11977 | M10: =SUM(M5:M9) -> 51000
D11: Current account - Inv, Currt and Holid | E11: Nat West Invest/Holiday - Not EX, Not Prop, Not Current below 4K | G11: 10700 | H11: 13000 | J11: Cars | P11: =170114-(2*64563) -> 40988
D12: Premium Bonds | E12: Post Office | F12: JG | G12: 50000 | H12: 50000 | J12: MG | M12: 9000 | R12: =14514*2 -> 29028 | AE12: Invest | AF12: 40000
D13: Premium Bonds | E13: Post Office | F13: BH | J13: Golf | AF13: =SUM(AF5:AF12) -> 225000
D14: Premium Bonds | E14: Post Office | F14: FG | G14: 50000 | H14: 50000 | J14: Yeti | M14: 11000
C15: 105.06 | D15: Premium Bonds | E15: Post Office | F15: MG | G15: 50000 | H15: 50000 | M15: =SUM(M12:M14) -> 20000 | Q15: 81287
C16: 567 | D16: EDSP | E16: equateplus.com | F16: MG | G16: 41680 | H16: 43212 | J16: Rented Properties | Q16: =#REF!*2 -> #REF!
D17: Trading Account | E17: III ( both JG and MG) | F17: MGJG | J17: House | K17: 2bed | M17: =38000+1500+2500 -> 42000 | Q17: =Q15-Q16 -> #REF! | X17: =SUM(A17:A19) -> 597 | Y17: =X17*V4 -> 61371.6
C18: 1191 | D18: OWN SAP | E18: equateplus.com | F18: MG | G18: 87457 | H18: 89136 | J18: House | K18: 3bed | M18: =38000+1500+2500+2500 -> 44500
A19: 597 | B19: 555 | C19: 992 | J19: Total | M19: =SUM(M17:M18) -> 86500 | N19: 73707
A20: 2011 | C20: 99 | D20: SAP Shares | E20: 1 free | F20: MG | J20: SAP Shares | K20: 1 free | N20: 42156 | P20: 37666 | W20: =388*70/1.43 -> 18993.007
A21: 2012 | C21: 96 | D21: SAP Shares | E21: 5 p 3y 3g | F21: MG | J21: SAP Shares | K21: 5 p 3y 3g | N21: 41791 | P21: 35143
A22: 2013 | C22: 87 | D22: SAP Shares | E22: B3K3G1 | F22: MG | J22: SAP Shares | K22: B3K3G1 | N22: 42583
M23: =SUM(M20:M22) -> 0
D25: Total | G25: =SUM(G4:G18) -> 443589.41 | H25: =SUM(H4:H18) -> 451922 | I25: =G25-H25 -> -8332.59 | M25: =M10+M19+M15 -> 157500 | Z25: 1155
Q26: 900 | Z26: 80.13
D27: Potential Balance | K27: 77 | AA27: =Z26*Z25 -> 92550.15
D28: Not so liquid | N28: Actual | O28: 31st Dec | P28: 31st Dec | Q28: 31st Dec | R28: 31st Dec | S28: 31st Dec | T28: 31st Dec | Z28: 1.5 | AA28: =AA27/Z28 -> 61700.1
D29: Aston | E29: Sold | G29: 0 | O29: 2015 | P29: 2016 | Q29: 2017 | R29: 2018 | S29: 2019 | T29: 2020 | U29: =T29+1 -> 2021
D30: Golf R | G30: 15000 | N30: Value | O30: 164433.05 | P30: 248589.4 | Q30: 314989.19 | R30: 335945 | S30: 336562 | T30: 374989.19
D31: Motor Bike | G31: 2000 | O31: 0 | P31: 0 | S31: 30000 | T31: 7000
G32: =SUM(G29:G31) -> 17000 | N32: Santandar | O32: 29028
N33: Total | O33: 193461.05 | P33: 248589.4 | Q33: 314989.19 | R33: 335945 | S33: 374989.19 | T33: 381989.19
D34: Less CC Debit | P34: 55128.35 | Q34: 66399.786 | R34: =R33-Q33 -> 20955.812
D36: Sub Total | G36: =G27+G32-G34 -> 17000 | N36: Q1 | P36: 282432.89 | Q36: 33843.485 | R36: 8687 | S36: 120736 | Z36: phil | AA36: 1500
N37: Q2 | P37: 294892.7 | Q37: 12459.809 | R37: 5697 | S37: 43735
D38: Tied Assetts | G38: =M25 -> 157500 | N38: Q3 | P38: 310690.69 | Q38: 15797.999 | R38: 37050 | S38: -7000
N39: Q4 | P39: 314989.19 | Q39: 4298.4936 | R39: -31361 | S39: 11634
D40: House | G40: 360000 | Q40: 66399.786 | R40: =SUM(R36:R39) -> 20073 | S40: =SUM(S36:S39) -> 169105
D41: less mortgage | G41: =G40 -> 360000
N42: Budget | O42: 31st Dec | P42: 31st Dec | Q42: 31st Dec | R42: 31st Dec | S42: 31st Dec | T42: 31st Dec | Z42: RN Pension
D43: Nett Worth | G43: =G41+G38+G36 -> 534500 | O43: 2015 | P43: 2016 | Q43: 2017 | R43: 2018 | S43: 2019 | T43: 2020 | Z43: Nissan | AA43: GSR Capital
N44: Base | O44: 105896.15 | P44: 163396.15 | Q44: 193396.15 | R44: 223396.15 | S44: 253396.15 | T44: 283396.15
N45: Save | O45: 30000 | P45: 30000 | Q45: 30000 | R45: 30000 | S45: 30000 | T45: 30000
N46: Extra | O46: 27500
N47: Total | O47: 163396.15 | P47: 193396.15 | Q47: 223396.15 | R47: 253396.15 | S47: 283396.15 | T47: 313396.15
T48: =T47-P33 -> 64806.752

Sheet 30-09-22
A1: 201
D2: Liquid Assests | G2: Read This | J2: Tied Assests | N2: 524438 | O2: b
D3: Prod | E3: Where | F3: Who | G3: 44834 | H3: 44804 | J3: Prod | K3: Where | L3: Who | M3: Amount | Q3: At Risk | R3: Not a Risk - Cash
B4: =488+743 -> 1231 | D4: ISA | E4: Ford | F4: JG | G4: 53522 | H4: =56278 -> 56278 | J4: Family Loans | Q4: =#REF!-R4 -> #REF! | R4: =SUM(#REF!) -> #REF! | T4: 130 | V4: 102.8 | W4: Share Price
B5: =504+803 -> 1307 | D5: ISA | E5: Ford | F5: MG | G5: 53522 | H5: =56278 -> 56278 | J5: Faye | M5: 22000 | P5: this is 17k + 5K | T5: 71 | V5: 1.125 | W5: Exchange | AE5: NSI | AF5: 100000
D6: FundSmith | G6: 9047 | H6: 9477 | J6: Nik | M6: 5000 | N6: 155K | P6: Med | Q6: =#REF!+#REF!+#REF!+#REF!+#REF! -> #REF! | T6: =T4-T5 -> 59 | AE6: Share | AF6: 85000
C7: * | D7: Hargrevaes Lansdown | G7: 901 | H7: 933 | J7: ECC | M7: 2500 | P7: High | Q7: =SUM(#REF!) -> #REF!
C8: * | D8: Intractive Investor | G8: 6580 | H8: 6751 | J8: Les and Jon | M8: 20000
C9: * | D9: JG ClearWaterCapital | G9: 12960 | H9: 13350 | J9: Phil | M9: 1500
C10: * | D10: MG ClearWaterCapital inc ISA | G10: =7093+1672 -> 8765 | H10: =8577.07+ 2108.34 -> 10685.41 | M10: =SUM(M5:M9) -> 51000
D11: Current account - Inv, Currt and Holid | E11: Nat West Invest/Holiday - Not EX, Not Prop, Not Current below 4K | H11: 10700 | J11: Cars | P11: =170114-(2*64563) -> 40988
D12: Premium Bonds | E12: Post Office | F12: JG | G12: 50000 | H12: 50000 | J12: MG | M12: 9000 | R12: =14514*2 -> 29028 | AE12: Invest | AF12: 40000
D13: Premium Bonds | E13: Post Office | F13: BH | J13: Golf | AF13: =SUM(AF5:AF12) -> 225000
D14: Premium Bonds | E14: Post Office | F14: FG | G14: 50000 | H14: 50000 | J14: Yeti | M14: 11000
C15: 105.06 | D15: Premium Bonds | E15: Post Office | F15: MG | G15: 50000 | H15: 50000 | M15: =SUM(M12:M14) -> 20000 | Q15: 81287
C16: 567 | D16: EDSP | E16: equateplus.com | F16: MG | G16: 41973 | H16: 41680 | J16: Rented Properties | Q16: =#REF!*2 -> #REF!
C17: 37 | D17: Move SAP | E17: III ( both JG and MG) | F17: MG | G17: 2800 | J17: House | K17: 2bed | M17: =38000+1500+2500 -> 42000 | Q17: =Q15-Q16 -> #REF! | X17: =SUM(A17:A19) -> 597 | Y17: =X17*V4 -> 61371.6
C18: 1212 | D18: OWN SAP | E18: equateplus.com | F18: MG | G18: 89660 | H18: 87457 | J18: House | K18: 3bed | M18: =38000+1500+2500+2500 -> 44500
A19: 597 | B19: 555 | C19: 992 | J19: Total | M19: =SUM(M17:M18) -> 86500 | N19: 73707
A20: 2011 | C20: 99 | D20: SAP Shares | E20: 1 free | F20: MG | J20: SAP Shares | K20: 1 free | N20: 42156 | P20: 37666 | W20: =388*70/1.43 -> 18993.007
A21: 2012 | C21: 96 | D21: SAP Shares | E21: 5 p 3y 3g | F21: MG | J21: SAP Shares | K21: 5 p 3y 3g | N21: 41791 | P21: 35143
A22: 2013 | C22: 87 | D22: SAP Shares | E22: B3K3G1 | F22: MG | J22: SAP Shares | K22: B3K3G1 | N22: 42583
M23: =SUM(M20:M22) -> 0
D25: Total | G25: =SUM(G4:G18) -> 429730 | H25: =SUM(H4:H18) -> 443589.41 | I25: =G25-H25 -> -13859.41 | M25: =M10+M19+M15 -> 157500 | Z25: 1155
Q26: 900 | Z26: 80.13
D27: Potential Balance | K27: 77 | AA27: =Z26*Z25 -> 92550.15
D28: Not so liquid | N28: Actual | O28: 31st Dec | P28: 31st Dec | Q28: 31st Dec | R28: 31st Dec | S28: 31st Dec | T28: 31st Dec | Z28: 1.5 | AA28: =AA27/Z28 -> 61700.1
D29: Aston | E29: Sold | G29: 0 | O29: 2015 | P29: 2016 | Q29: 2017 | R29: 2018 | S29: 2019 | T29: 2020 | U29: =T29+1 -> 2021
D30: Golf R | G30: 15000 | N30: Value | O30: 164433.05 | P30: 248589.4 | Q30: 314989.19 | R30: 335945 | S30: 336562 | T30: 374989.19
D31: Motor Bike | G31: 2000 | O31: 0 | P31: 0 | S31: 30000 | T31: 7000
G32: =SUM(G29:G31) -> 17000 | N32: Santandar | O32: 29028
N33: Total | O33: 193461.05 | P33: 248589.4 | Q33: 314989.19 | R33: 335945 | S33: 374989.19 | T33: 381989.19
D34: Less CC Debit | P34: 55128.35 | Q34: 66399.786 | R34: =R33-Q33 -> 20955.812
D36: Sub Total | G36: =G27+G32-G34 -> 17000 | N36: Q1 | P36: 282432.89 | Q36: 33843.485 | R36: 8687 | S36: 120736 | Z36: phil | AA36: 1500
N37: Q2 | P37: 294892.7 | Q37: 12459.809 | R37: 5697 | S37: 43735
D38: Tied Assetts | G38: =M25 -> 157500 | N38: Q3 | P38: 310690.69 | Q38: 15797.999 | R38: 37050 | S38: -7000
N39: Q4 | P39: 314989.19 | Q39: 4298.4936 | R39: -31361 | S39: 11634
D40: House | G40: 360000 | Q40: 66399.786 | R40: =SUM(R36:R39) -> 20073 | S40: =SUM(S36:S39) -> 169105
D41: less mortgage | G41: =G40 -> 360000
N42: Budget | O42: 31st Dec | P42: 31st Dec | Q42: 31st Dec | R42: 31st Dec | S42: 31st Dec | T42: 31st Dec | Z42: RN Pension
D43: Nett Worth | G43: =G41+G38+G36 -> 534500 | O43: 2015 | P43: 2016 | Q43: 2017 | R43: 2018 | S43: 2019 | T43: 2020 | Z43: Nissan | AA43: GSR Capital
N44: Base | O44: 105896.15 | P44: 163396.15 | Q44: 193396.15 | R44: 223396.15 | S44: 253396.15 | T44: 283396.15
N45: Save | O45: 30000 | P45: 30000 | Q45: 30000 | R45: 30000 | S45: 30000 | T45: 30000
N46: Extra | O46: 27500
N47: Total | O47: 163396.15 | P47: 193396.15 | Q47: 223396.15 | R47: 253396.15 | S47: 283396.15 | T47: 313396.15
T48: =T47-P33 -> 64806.752

Sheet 31-10-22
A1: 201
D2: Liquid Assests | G2: Read This | J2: Tied Assests | N2: 524438 | O2: b
D3: Prod | E3: Where | F3: Who | G3: 44865 | H3: 44834 | J3: Prod | K3: Where | L3: Who | M3: Amount | Q3: At Risk | R3: Not a Risk - Cash
B4: =488+743 -> 1231 | D4: ISA | E4: Ford | F4: JG | G4: 52928 | H4: 53522 | J4: Family Loans | Q4: =#REF!-R4 -> #REF! | R4: =SUM(#REF!) -> #REF! | T4: 130 | V4: 102.8 | W4: Share Price
B5: =504+803 -> 1307 | D5: ISA | E5: Ford | F5: MG | G5: 52928 | H5: 53522 | J5: Faye | M5: 22000 | P5: this is 17k + 5K | T5: 71 | V5: 1.125 | W5: Exchange | AE5: NSI | AF5: 100000
D6: FundSmith | G6: 9049 | H6: 9047 | J6: Nik | M6: 5000 | N6: 155K | P6: Med | Q6: =#REF!+#REF!+#REF!+#REF!+#REF! -> #REF! | T6: =T4-T5 -> 59 | AE6: Share | AF6: 85000
C7: * | D7: Hargrevaes Lansdown | G7: 873 | H7: 901 | J7: ECC | M7: 2500 | P7: High | Q7: =SUM(#REF!) -> #REF!
C8: * | D8: Intractive Investor | G8: 6835 | H8: 6580 | J8: Les and Jon | M8: 20000
C9: * | D9: JG ClearWaterCapital | G9: 14161 | H9: 12960 | J9: Phil | M9: 1500
C10: * | D10: MG ClearWaterCapital inc ISA | G10: 10400 | H10: =7093+1672 -> 8765 | M10: =SUM(M5:M9) -> 51000
D11: Current account - Inv, Currt and Holid | E11: Nat West Invest/Holiday - Not EX, Not Prop, Not Current below 4K | G11: 7000 | J11: Cars | P11: =170114-(2*64563) -> 40988
D12: Premium Bonds | E12: Post Office | F12: JG | G12: 50000 | H12: 50000 | J12: MG | M12: 9000 | R12: =14514*2 -> 29028 | AE12: Invest | AF12: 40000
D13: Premium Bonds | E13: Post Office | F13: BH | J13: Golf | AF13: =SUM(AF5:AF12) -> 225000
D14: Premium Bonds | E14: Post Office | F14: FG | G14: 50000 | H14: 50000 | J14: Yeti | M14: 11000
C15: 105.06 | D15: Premium Bonds | E15: Post Office | F15: MG | G15: 50000 | H15: 50000 | M15: =SUM(M12:M14) -> 20000 | Q15: 81287
C16: 567 | D16: EDSP | E16: equateplus.com | F16: MG | G16: 47541 | H16: 41973 | J16: Rented Properties | Q16: =#REF!*2 -> #REF!
C17: 37 | D17: Move SAP | E17: III ( both JG and MG) | F17: MG | G17: 3171 | H17: 2800 | J17: House | K17: 2bed | M17: =38000+1500+2500 -> 42000 | Q17: =Q15-Q16 -> #REF! | X17: =SUM(A17:A19) -> 597 | Y17: =X17*V4 -> 61371.6
C18: 1232 | D18: OWN SAP | E18: equateplus.com | F18: MG | G18: 103257 | H18: 89660 | J18: House | K18: 3bed | M18: =38000+1500+2500+2500 -> 44500
A19: 597 | B19: 555 | C19: 992 | J19: Total | M19: =SUM(M17:M18) -> 86500 | N19: 73707
A20: 2011 | C20: 99 | D20: SAP Shares | E20: 1 free | F20: MG | J20: SAP Shares | K20: 1 free | N20: 42156 | P20: 37666 | W20: =388*70/1.43 -> 18993.007
A21: 2012 | C21: 96 | D21: SAP Shares | E21: 5 p 3y 3g | F21: MG | J21: SAP Shares | K21: 5 p 3y 3g | N21: 41791 | P21: 35143
A22: 2013 | C22: 87 | D22: SAP Shares | E22: B3K3G1 | F22: MG | J22: SAP Shares | K22: B3K3G1 | N22: 42583
M23: =SUM(M20:M22) -> 0
D25: Total | G25: =SUM(G4:G18) -> 458143 | H25: =SUM(H4:H18) -> 429730 | I25: =G25-H25 -> 28413 | M25: =M10+M19+M15 -> 157500 | Z25: 1155
Q26: 900 | Z26: 80.13
D27: Potential Balance | K27: 77 | AA27: =Z26*Z25 -> 92550.15
D28: Not so liquid | N28: Actual | O28: 31st Dec | P28: 31st Dec | Q28: 31st Dec | R28: 31st Dec | S28: 31st Dec | T28: 31st Dec | Z28: 1.5 | AA28: =AA27/Z28 -> 61700.1
D29: Aston | E29: Sold | G29: 0 | O29: 2015 | P29: 2016 | Q29: 2017 | R29: 2018 | S29: 2019 | T29: 2020 | U29: =T29+1 -> 2021
D30: Golf R | G30: 15000 | N30: Value | O30: 164433.05 | P30: 248589.4 | Q30: 314989.19 | R30: 335945 | S30: 336562 | T30: 374989.19
D31: Motor Bike | G31: 2000 | O31: 0 | P31: 0 | S31: 30000 | T31: 7000
G32: =SUM(G29:G31) -> 17000 | N32: Santandar | O32: 29028
N33: Total | O33: 193461.05 | P33: 248589.4 | Q33: 314989.19 | R33: 335945 | S33: 374989.19 | T33: 381989.19
D34: Less CC Debit | P34: 55128.35 | Q34: 66399.786 | R34: =R33-Q33 -> 20955.812
D36: Sub Total | G36: =G27+G32-G34 -> 17000 | N36: Q1 | P36: 282432.89 | Q36: 33843.485 | R36: 8687 | S36: 120736 | Z36: phil | AA36: 1500
N37: Q2 | P37: 294892.7 | Q37: 12459.809 | R37: 5697 | S37: 43735
D38: Tied Assetts | G38: =M25 -> 157500 | N38: Q3 | P38: 310690.69 | Q38: 15797.999 | R38: 37050 | S38: -7000
N39: Q4 | P39: 314989.19 | Q39: 4298.4936 | R39: -31361 | S39: 11634
D40: House | G40: 360000 | Q40: 66399.786 | R40: =SUM(R36:R39) -> 20073 | S40: =SUM(S36:S39) -> 169105
D41: less mortgage | G41: =G40 -> 360000
N42: Budget | O42: 31st Dec | P42: 31st Dec | Q42: 31st Dec | R42: 31st Dec | S42: 31st Dec | T42: 31st Dec | Z42: RN Pension
D43: Nett Worth | G43: =G41+G38+G36 -> 534500 | O43: 2015 | P43: 2016 | Q43: 2017 | R43: 2018 | S43: 2019 | T43: 2020 | Z43: Nissan | AA43: GSR Capital
N44: Base | O44: 105896.15 | P44: 163396.15 | Q44: 193396.15 | R44: 223396.15 | S44: 253396.15 | T44: 283396.15
N45: Save | O45: 30000 | P45: 30000 | Q45: 30000 | R45: 30000 | S45: 30000 | T45: 30000
N46: Extra | O46: 27500
N47: Total | O47: 163396.15 | P47: 193396.15 | Q47: 223396.15 | R47: 253396.15 | S47: 283396.15 | T47: 313396.15
T48: =T47-P33 -> 64806.752

Sheet 30-11-22
A1: 201
D2: Liquid Assests | G2: Read This | J2: Tied Assests | N2: 524438 | O2: b
D3: Prod | E3: Where | F3: Who | G3: 44895 | H3: 44865 | J3: Prod | K3: Where | L3: Who | M3: Amount | Q3: At Risk | R3: Not a Risk - Cash
B4: =488+743 -> 1231 | D4: ISA | E4: Ford | F4: JG | G4: 54838 | H4: 52928 | J4: Family Loans | Q4: =#REF!-R4 -> #REF! | R4: =SUM(#REF!) -> #REF! | T4: 130 | V4: 102.8 | W4: Share Price
B5: =504+803 -> 1307 | D5: ISA | E5: Ford | F5: MG | G5: 54838 | H5: 52928 | J5: Faye | M5: 22000 | P5: this is 17k + 5K | T5: 71 | V5: 1.125 | W5: Exchange | AE5: NSI | AF5: 100000
D6: FundSmith | G6: 9186 | H6: 9049 | J6: Nik | M6: 5000 | N6: 155K | P6: Med | Q6: =#REF!+#REF!+#REF!+#REF!+#REF! -> #REF! | T6: =T4-T5 -> 59 | AE6: Share | AF6: 85000
C7: * | D7: Hargrevaes Lansdown | G7: 923 | H7: 873 | J7: ECC | M7: 2500 | P7: High | Q7: =SUM(#REF!) -> #REF!
C8: * | D8: Intractive Investor | G8: 7435 | H8: 6835 | J8: Les and Jon | M8: 20000
C9: * | D9: JG ClearWaterCapital | G9: 16293 | H9: 14161 | J9: Phil | M9: 1500
C10: * | D10: MG ClearWaterCapital inc ISA | G10: 9875 | H10: 10400 | M10: =SUM(M5:M9) -> 51000
D11: Current account - Inv, Currt and Holid | E11: Nat West Invest/Holiday - Not EX, Not Prop, Not Current below 4K | G11: 7000 | H11: 7000 | J11: Cars | P11: =170114-(2*64563) -> 40988
D12: Premium Bonds | E12: Post Office | F12: JG | G12: 50000 | H12: 50000 | J12: MG | M12: 9000 | R12: =14514*2 -> 29028 | AE12: Invest | AF12: 40000
D13: Premium Bonds | E13: Post Office | F13: BH | J13: Golf | AF13: =SUM(AF5:AF12) -> 225000
D14: Premium Bonds | E14: Post Office | F14: FG | G14: 50000 | H14: 50000 | J14: Yeti | M14: 11000
C15: 105.06 | D15: Premium Bonds | E15: Post Office | F15: MG | G15: 50000 | H15: 50000 | M15: =SUM(M12:M14) -> 20000 | Q15: 81287
C16: 567 | D16: EDSP | E16: equateplus.com | F16: MG | G16: 51252 | H16: 47541 | J16: Rented Properties | Q16: =#REF!*2 -> #REF!
C17: 37 | D17: Move SAP | E17: III ( both JG and MG) | F17: MG | G17: 3419 | H17: 3171 | J17: House | K17: 2bed | M17: =38000+1500+2500 -> 42000 | Q17: =Q15-Q16 -> #REF! | X17: =SUM(A17:A19) -> 597 | Y17: =X17*V4 -> 61371.6
C18: 1249 | D18: OWN SAP | E18: equateplus.com | F18: MG | G18: 122832 | H18: 103257 | J18: House | K18: 3bed | M18: =38000+1500+2500+2500 -> 44500
A19: 597 | B19: 555 | C19: 992 | J19: Total | M19: =SUM(M17:M18) -> 86500 | N19: 73707
A20: 2011 | C20: 99 | D20: SAP Shares | E20: 1 free | F20: MG | J20: SAP Shares | K20: 1 free | N20: 42156 | P20: 37666 | W20: =388*70/1.43 -> 18993.007
A21: 2012 | C21: 96 | D21: SAP Shares | E21: 5 p 3y 3g | F21: MG | J21: SAP Shares | K21: 5 p 3y 3g | N21: 41791 | P21: 35143
A22: 2013 | C22: 87 | D22: SAP Shares | E22: B3K3G1 | F22: MG | J22: SAP Shares | K22: B3K3G1 | N22: 42583
M23: =SUM(M20:M22) -> 0
D25: Total | G25: =SUM(G4:G18) -> 487891 | H25: =SUM(H4:H18) -> 458143 | I25: =G25-H25 -> 29748 | M25: =M10+M19+M15 -> 157500 | Z25: 1155
Q26: 900 | Z26: 80.13
D27: Potential Balance | K27: 77 | AA27: =Z26*Z25 -> 92550.15
D28: Not so liquid | N28: Actual | O28: 31st Dec | P28: 31st Dec | Q28: 31st Dec | R28: 31st Dec | S28: 31st Dec | T28: 31st Dec | Z28: 1.5 | AA28: =AA27/Z28 -> 61700.1
D29: Aston | E29: Sold | G29: 0 | O29: 2015 | P29: 2016 | Q29: 2017 | R29: 2018 | S29: 2019 | T29: 2020 | U29: =T29+1 -> 2021
D30: Golf R | G30: 15000 | N30: Value | O30: 164433.05 | P30: 248589.4 | Q30: 314989.19 | R30: 335945 | S30: 336562 | T30: 374989.19
D31: Motor Bike | G31: 2000 | O31: 0 | P31: 0 | S31: 30000 | T31: 7000
G32: =SUM(G29:G31) -> 17000 | N32: Santandar | O32: 29028
N33: Total | O33: 193461.05 | P33: 248589.4 | Q33: 314989.19 | R33: 335945 | S33: 374989.19 | T33: 381989.19
D34: Less CC Debit | P34: 55128.35 | Q34: 66399.786 | R34: =R33-Q33 -> 20955.812
D36: Sub Total | G36: =G27+G32-G34 -> 17000 | N36: Q1 | P36: 282432.89 | Q36: 33843.485 | R36: 8687 | S36: 120736 | Z36: phil | AA36: 1500
N37: Q2 | P37: 294892.7 | Q37: 12459.809 | R37: 5697 | S37: 43735
D38: Tied Assetts | G38: =M25 -> 157500 | N38: Q3 | P38: 310690.69 | Q38: 15797.999 | R38: 37050 | S38: -7000
N39: Q4 | P39: 314989.19 | Q39: 4298.4936 | R39: -31361 | S39: 11634
D40: House | G40: 360000 | Q40: 66399.786 | R40: =SUM(R36:R39) -> 20073 | S40: =SUM(S36:S39) -> 169105
D41: less mortgage | G41: =G40 -> 360000
N42: Budget | O42: 31st Dec | P42: 31st Dec | Q42: 31st Dec | R42: 31st Dec | S42: 31st Dec | T42: 31st Dec | Z42: RN Pension
D43: Nett Worth | G43: =G41+G38+G36 -> 534500 | O43: 2015 | P43: 2016 | Q43: 2017 | R43: 2018 | S43: 2019 | T43: 2020 | Z43: Nissan | AA43: GSR Capital
N44: Base | O44: 105896.15 | P44: 163396.15 | Q44: 193396.15 | R44: 223396.15 | S44: 253396.15 | T44: 283396.15
N45: Save | O45: 30000 | P45: 30000 | Q45: 30000 | R45: 30000 | S45: 30000 | T45: 30000
N46: Extra | O46: 27500
N47: Total | O47: 163396.15 | P47: 193396.15 | Q47: 223396.15 | R47: 253396.15 | S47: 283396.15 | T47: 313396.15
T48: =T47-P33 -> 64806.752

Sheet 30-12-22
A1: 201
D2: Liquid Assests | G2: Read This | J2: Tied Assests | N2: 524438 | O2: b
D3: Prod | E3: Where | F3: Who | G3: 44925 | H3: 44895 | J3: Prod | K3: Where | L3: Who | M3: Amount | Q3: At Risk | R3: Not a Risk - Cash
B4: =488+743 -> 1231 | D4: ISA | E4: Ford | F4: JG | G4: 53765 | H4: 54838 | J4: Family Loans | Q4: =#REF!-R4 -> #REF! | R4: =SUM(#REF!) -> #REF! | T4: 130 | V4: 102.8 | W4: Share Price
B5: =504+803 -> 1307 | D5: ISA | E5: Ford | F5: MG | G5: 53765 | H5: 54838 | J5: Faye | M5: 22000 | P5: this is 17k + 5K | T5: 71 | V5: 1.125 | W5: Exchange | AE5: NSI | AF5: 100000
D6: FundSmith | G6: 9328 | H6: 9186 | J6: Nik | M6: 5000 | N6: 155K | P6: Med | Q6: =#REF!+#REF!+#REF!+#REF!+#REF! -> #REF! | T6: =T4-T5 -> 59 | AE6: Share | AF6: 85000
C7: * | D7: Hargrevaes Lansdown | G7: 891 | H7: 923 | J7: ECC | M7: 2500 | P7: High | Q7: =SUM(#REF!) -> #REF!
C8: * | D8: Intractive Investor | G8: 7174 | H8: 7435 | J8: Les and Jon | M8: 20000
C9: * | D9: JG ClearWaterCapital | G9: 14889 | H9: 16293 | J9: Phil | M9: 1500
C10: * | D10: MG ClearWaterCapital inc ISA | G10: =2652+1563 -> 4215 | H10: 9875 | M10: =SUM(M5:M9) -> 51000
D11: Current account - Inv, Currt and Holid | E11: Nat West Invest/Holiday - Not EX, Not Prop, Not Current below 4K | G11: 5000 | H11: 7000 | J11: Cars | P11: =170114-(2*64563) -> 40988
D12: Premium Bonds | E12: Post Office | F12: JG | G12: 50000 | H12: 50000 | J12: MG | M12: 9000 | R12: =14514*2 -> 29028 | AE12: Invest | AF12: 40000
D13: Premium Bonds | E13: Post Office | F13: BH | J13: Golf | AF13: =SUM(AF5:AF12) -> 225000
D14: Premium Bonds | E14: Post Office | F14: FG | G14: 50000 | H14: 50000 | J14: Yeti | M14: 11000
C15: 105.06 | D15: Premium Bonds | E15: Post Office | F15: MG | G15: 50000 | H15: 50000 | M15: =SUM(M12:M14) -> 20000 | Q15: 81287
C16: 567 | D16: EDSP | E16: equateplus.com | F16: MG | G16: 48519 | H16: 51252 | J16: Rented Properties | Q16: =#REF!*2 -> #REF!
C17: 57.9 | D17: Move SAP | E17: III ( both JG and MG) | F17: MG | G17: 4952 | H17: 3419 | J17: House | K17: 2bed | M17: =38000+1500+2500 -> 42000 | Q17: =Q15-Q16 -> #REF! | X17: =SUM(A17:A19) -> 597 | Y17: =X17*V4 -> 61371.6
C18: 1262 | D18: OWN SAP | E18: equateplus.com | F18: MG | G18: 107937 | H18: 122832 | J18: House | K18: 3bed | M18: =38000+1500+2500+2500 -> 44500
A19: 597 | B19: 555 | C19: 992 | J19: Total | M19: =SUM(M17:M18) -> 86500 | N19: 73707
A20: 2011 | C20: 99 | D20: SAP Shares | E20: 1 free | F20: MG | J20: SAP Shares | K20: 1 free | N20: 42156 | P20: 37666 | W20: =388*70/1.43 -> 18993.007
A21: 2012 | C21: 96 | D21: SAP Shares | E21: 5 p 3y 3g | F21: MG | J21: SAP Shares | K21: 5 p 3y 3g | N21: 41791 | P21: 35143
A22: 2013 | C22: 87 | D22: SAP Shares | E22: B3K3G1 | F22: MG | J22: SAP Shares | K22: B3K3G1 | N22: 42583
M23: =SUM(M20:M22) -> 0
D25: Total | G25: =SUM(G4:G18) -> 460435 | H25: =SUM(H4:H18) -> 487891 | I25: =G25-H25 -> -27456 | M25: =M10+M19+M15 -> 157500 | Z25: 1155
Q26: 900 | Z26: 80.13
D27: Potential Balance | K27: 77 | AA27: =Z26*Z25 -> 92550.15
D28: Not so liquid | N28: Actual | O28: 31st Dec | P28: 31st Dec | Q28: 31st Dec | R28: 31st Dec | S28: 31st Dec | T28: 31st Dec | Z28: 1.5 | AA28: =AA27/Z28 -> 61700.1
D29: Aston | E29: Sold | G29: 0 | O29: 2015 | P29: 2016 | Q29: 2017 | R29: 2018 | S29: 2019 | T29: 2020 | U29: =T29+1 -> 2021
D30: Golf R | G30: 15000 | N30: Value | O30: 164433.05 | P30: 248589.4 | Q30: 314989.19 | R30: 335945 | S30: 336562 | T30: 374989.19
D31: Motor Bike | G31: 2000 | O31: 0 | P31: 0 | S31: 30000 | T31: 7000
G32: =SUM(G29:G31) -> 17000 | N32: Santandar | O32: 29028
N33: Total | O33: 193461.05 | P33: 248589.4 | Q33: 314989.19 | R33: 335945 | S33: 374989.19 | T33: 381989.19
D34: Less CC Debit | P34: 55128.35 | Q34: 66399.786 | R34: =R33-Q33 -> 20955.812
D36: Sub Total | G36: =G27+G32-G34 -> 17000 | N36: Q1 | P36: 282432.89 | Q36: 33843.485 | R36: 8687 | S36: 120736 | Z36: phil | AA36: 1500
N37: Q2 | P37: 294892.7 | Q37: 12459.809 | R37: 5697 | S37: 43735
D38: Tied Assetts | G38: =M25 -> 157500 | N38: Q3 | P38: 310690.69 | Q38: 15797.999 | R38: 37050 | S38: -7000
N39: Q4 | P39: 314989.19 | Q39: 4298.4936 | R39: -31361 | S39: 11634
D40: House | G40: 360000 | Q40: 66399.786 | R40: =SUM(R36:R39) -> 20073 | S40: =SUM(S36:S39) -> 169105
D41: less mortgage | G41: =G40 -> 360000
N42: Budget | O42: 31st Dec | P42: 31st Dec | Q42: 31st Dec | R42: 31st Dec | S42: 31st Dec | T42: 31st Dec | Z42: RN Pension
D43: Nett Worth | G43: =G41+G38+G36 -> 534500 | O43: 2015 | P43: 2016 | Q43: 2017 | R43: 2018 | S43: 2019 | T43: 2020 | Z43: Nissan | AA43: GSR Capital
N44: Base | O44: 105896.15 | P44: 163396.15 | Q44: 193396.15 | R44: 223396.15 | S44: 253396.15 | T44: 283396.15
N45: Save | O45: 30000 | P45: 30000 | Q45: 30000 | R45: 30000 | S45: 30000 | T45: 30000
N46: Extra | O46: 27500
N47: Total | O47: 163396.15 | P47: 193396.15 | Q47: 223396.15 | R47: 253396.15 | S47: 283396.15 | T47: 313396.15
T48: =T47-P33 -> 64806.752

Sheet 31-01-23
A1: 201
D2: Liquid Assests | G2: Read This | J2: Tied Assests | N2: 524438 | O2: b
D3: Prod | E3: Where | F3: Who | G3: 44957 | H3: 44925 | J3: Prod | K3: Where | L3: Who | M3: Amount | Q3: At Risk | R3: Not a Risk - Cash
B4: =488+743 -> 1231 | D4: ISA | E4: Ford | F4: JG | G4: 56619 | H4: 53765 | J4: Family Loans | Q4: =#REF!-R4 -> #REF! | R4: =SUM(#REF!) -> #REF! | T4: 130 | V4: 102.8 | W4: Share Price
B5: =504+803 -> 1307 | D5: ISA | E5: Ford | F5: MG | G5: 56619 | H5: 53765 | J5: Faye | M5: 22000 | P5: this is 17k + 5K | T5: 71 | V5: 1.125 | W5: Exchange | AE5: NSI | AF5: 100000
D6: FundSmith | G6: 9466 | H6: 9328 | J6: Nik | M6: 5000 | N6: 155K | P6: Med | Q6: =#REF!+#REF!+#REF!+#REF!+#REF! -> #REF! | T6: =T4-T5 -> 59 | AE6: Share | AF6: 85000
C7: * | D7: Hargrevaes Lansdown | G7: 925 | H7: 891 | J7: ECC | M7: 2500 | P7: High | Q7: =SUM(#REF!) -> #REF!
C8: * | D8: Intractive Investor | G8: 7460 | H8: 7174 | J8: Les and Jon | M8: 20000
C9: * | D9: JG ClearWaterCapital | G9: 15751 | H9: 14889 | J9: Phil | M9: 1500
C10: * | D10: MG ClearWaterCapital inc ISA | G10: 3994 | H10: =2652+1563 -> 4215 | M10: =SUM(M5:M9) -> 51000
D11: Current account - Inv, Currt and Holid | E11: Nat West Invest/Holiday - Not EX, Not Prop, Not Current below 4K | G11: 5000 | H11: 5000 | J11: Cars | P11: =170114-(2*64563) -> 40988
D12: Premium Bonds | E12: Post Office | F12: JG | G12: 50000 | H12: 50000 | J12: MG | M12: 9000 | R12: =14514*2 -> 29028 | AE12: Invest | AF12: 40000
D13: Premium Bonds | E13: Post Office | F13: BH | J13: Golf | AF13: =SUM(AF5:AF12) -> 225000
D14: Premium Bonds | E14: Post Office | F14: FG | G14: 50000 | H14: 50000 | J14: Yeti | M14: 11000
C15: 105.06 | D15: Premium Bonds | E15: Post Office | F15: MG | G15: 50000 | H15: 50000 | M15: =SUM(M12:M14) -> 20000 | Q15: 81287
C16: 567 | D16: EDSP | E16: equateplus.com | F16: MG | G16: 54255 | H16: 48519 | J16: Rented Properties | Q16: =#REF!*2 -> #REF!
C17: 57.9 | D17: Move SAP | E17: III ( both JG and MG) | F17: MG | G17: 5537 | H17: 4952 | J17: House | K17: 2bed | M17: =38000+1500+2500 -> 42000 | Q17: =Q15-Q16 -> #REF! | X17: =SUM(A17:A19) -> 597 | Y17: =X17*V4 -> 61371.6
C18: 1262 | D18: OWN SAP | E18: equateplus.com | F18: MG | G18: 122345 | H18: 107937 | J18: House | K18: 3bed | M18: =38000+1500+2500+2500 -> 44500
A19: 597 | B19: 555 | C19: 992 | J19: Total | M19: =SUM(M17:M18) -> 86500 | N19: 73707
A20: 2011 | C20: 99 | D20: SAP Shares | E20: 1 free | F20: MG | J20: SAP Shares | K20: 1 free | N20: 42156 | P20: 37666 | W20: =388*70/1.43 -> 18993.007
A21: 2012 | C21: 96 | D21: SAP Shares | E21: 5 p 3y 3g | F21: MG | J21: SAP Shares | K21: 5 p 3y 3g | N21: 41791 | P21: 35143
A22: 2013 | C22: 87 | D22: SAP Shares | E22: B3K3G1 | F22: MG | J22: SAP Shares | K22: B3K3G1 | N22: 42583
M23: =SUM(M20:M22) -> 0
D25: Total | G25: =SUM(G4:G18) -> 487971 | H25: =SUM(H4:H18) -> 460435 | I25: =G25-H25 -> 27536 | M25: =M10+M19+M15 -> 157500 | Z25: 1155
Q26: 900 | Z26: 80.13
D27: Potential Balance | K27: 77 | AA27: =Z26*Z25 -> 92550.15
D28: Not so liquid | N28: Actual | O28: 31st Dec | P28: 31st Dec | Q28: 31st Dec | R28: 31st Dec | S28: 31st Dec | T28: 31st Dec | Z28: 1.5 | AA28: =AA27/Z28 -> 61700.1
D29: Aston | E29: Sold | G29: 0 | O29: 2015 | P29: 2016 | Q29: 2017 | R29: 2018 | S29: 2019 | T29: 2020 | U29: =T29+1 -> 2021
D30: Golf R | G30: 15000 | N30: Value | O30: 164433.05 | P30: 248589.4 | Q30: 314989.19 | R30: 335945 | S30: 336562 | T30: 374989.19
D31: Motor Bike | G31: 2000 | O31: 0 | P31: 0 | S31: 30000 | T31: 7000
G32: =SUM(G29:G31) -> 17000 | N32: Santandar | O32: 29028
N33: Total | O33: 193461.05 | P33: 248589.4 | Q33: 314989.19 | R33: 335945 | S33: 374989.19 | T33: 381989.19
D34: Less CC Debit | P34: 55128.35 | Q34: 66399.786 | R34: =R33-Q33 -> 20955.812
D36: Sub Total | G36: =G27+G32-G34 -> 17000 | N36: Q1 | P36: 282432.89 | Q36: 33843.485 | R36: 8687 | S36: 120736 | Z36: phil | AA36: 1500
N37: Q2 | P37: 294892.7 | Q37: 12459.809 | R37: 5697 | S37: 43735
D38: Tied Assetts | G38: =M25 -> 157500 | N38: Q3 | P38: 310690.69 | Q38: 15797.999 | R38: 37050 | S38: -7000
N39: Q4 | P39: 314989.19 | Q39: 4298.4936 | R39: -31361 | S39: 11634
D40: House | G40: 360000 | Q40: 66399.786 | R40: =SUM(R36:R39) -> 20073 | S40: =SUM(S36:S39) -> 169105
D41: less mortgage | G41: =G40 -> 360000
N42: Budget | O42: 31st Dec | P42: 31st Dec | Q42: 31st Dec | R42: 31st Dec | S42: 31st Dec | T42: 31st Dec | Z42: RN Pension
D43: Nett Worth | G43: =G41+G38+G36 -> 534500 | O43: 2015 | P43: 2016 | Q43: 2017 | R43: 2018 | S43: 2019 | T43: 2020 | Z43: Nissan | AA43: GSR Capital
N44: Base | O44: 105896.15 | P44: 163396.15 | Q44: 193396.15 | R44: 223396.15 | S44: 253396.15 | T44: 283396.15
N45: Save | O45: 30000 | P45: 30000 | Q45: 30000 | R45: 30000 | S45: 30000 | T45: 30000
N46: Extra | O46: 27500
N47: Total | O47: 163396.15 | P47: 193396.15 | Q47: 223396.15 | R47: 253396.15 | S47: 283396.15 | T47: 313396.15
T48: =T47-P33 -> 64806.752

Sheet 28-02-23
A1: 201
D2: Liquid Assests | G2: Read This | J2: Tied Assests | N2: 524438 | O2: b
D3: Prod | E3: Where | F3: Who | G3: 44985 | H3: 44957 | J3: Prod | K3: Where | L3: Who | M3: Amount | Q3: At Risk | R3: Not a Risk - Cash
B4: =488+743 -> 1231 | D4: ISA | E4: Ford | F4: JG | G4: =56231 -> 56231 | H4: 56619 | J4: Family Loans | Q4: =#REF!-R4 -> #REF! | R4: =SUM(#REF!) -> #REF! | T4: 130 | V4: 102.8 | W4: Share Price
B5: =504+803 -> 1307 | D5: ISA | E5: Ford | F5: MG | G5: =56231 -> 56231 | H5: 56619 | J5: Faye | M5: 22000 | P5: this is 17k + 5K | T5: 71 | V5: 1.125 | W5: Exchange | AE5: NSI | AF5: 100000
D6: FundSmith | G6: 9609 | H6: 9466 | J6: Nik | M6: 5000 | N6: 155K | P6: Med | Q6: =#REF!+#REF!+#REF!+#REF!+#REF! -> #REF! | T6: =T4-T5 -> 59 | AE6: Share | AF6: 85000
C7: * | D7: Hargrevaes Lansdown | G7: 883 | H7: 925 | J7: ECC | M7: 2500 | P7: High | Q7: =SUM(#REF!) -> #REF!
C8: * | D8: Intractive Investor | G8: 7257 | H8: 7460 | J8: Les and Jon | M8: 20000
C9: * | D9: JG ClearWaterCapital | G9: 16103 | H9: 15751 | J9: Phil | M9: 1500
C10: * | D10: MG ClearWaterCapital inc ISA | G10: 1970 | H10: 3994 | M10: =SUM(M5:M9) -> 51000
D11: Current account - Inv, Currt and Holid | E11: Nat West Invest/Holiday - Not EX, Not Prop, Not Current below 4K | G11: 11500 | H11: 5000 | J11: Cars | P11: =170114-(2*64563) -> 40988
D12: Premium Bonds | E12: Post Office | F12: JG | G12: 50000 | H12: 50000 | J12: MG | M12: 9000 | R12: =14514*2 -> 29028 | AE12: Invest | AF12: 40000
D13: Premium Bonds | E13: Post Office | F13: BH | J13: Golf | AF13: =SUM(AF5:AF12) -> 225000
D14: Premium Bonds | E14: Post Office | F14: FG | G14: 50000 | H14: 50000 | J14: Yeti | M14: 11000
C15: 105.06 | D15: Premium Bonds | E15: Post Office | F15: MG | G15: 50000 | H15: 50000 | M15: =SUM(M12:M14) -> 20000 | Q15: 81287
C16: 567 | D16: EDSP | E16: equateplus.com | F16: MG | G16: 53426 | H16: 54255 | J16: Rented Properties | Q16: =#REF!*2 -> #REF!
C17: 57.9 | D17: Move SAP | E17: III ( both JG and MG) | F17: MG | G17: 5452 | H17: 5537 | J17: House | K17: 2bed | M17: =38000+1500+2500 -> 42000 | Q17: =Q15-Q16 -> #REF! | X17: =SUM(A17:A19) -> 597 | Y17: =X17*V4 -> 61371.6
C18: 1296 | D18: OWN SAP | E18: equateplus.com | F18: MG | G18: 121989 | H18: 122345 | J18: House | K18: 3bed | M18: =38000+1500+2500+2500 -> 44500
A19: 597 | B19: 555 | C19: 992 | J19: Total | M19: =SUM(M17:M18) -> 86500 | N19: 73707
A20: 2011 | C20: 99 | D20: SAP Shares | E20: 1 free | F20: MG | J20: SAP Shares | K20: 1 free | N20: 42156 | P20: 37666 | W20: =388*70/1.43 -> 18993.007
A21: 2012 | C21: 96 | D21: SAP Shares | E21: 5 p 3y 3g | F21: MG | J21: SAP Shares | K21: 5 p 3y 3g | N21: 41791 | P21: 35143
A22: 2013 | C22: 87 | D22: SAP Shares | E22: B3K3G1 | F22: MG | J22: SAP Shares | K22: B3K3G1 | N22: 42583
M23: =SUM(M20:M22) -> 0
D25: Total | G25: =SUM(G4:G18) -> 490651 | H25: =SUM(H4:H18) -> 487971 | I25: =G25-H25 -> 2680 | M25: =M10+M19+M15 -> 157500 | Z25: 1155
Q26: 900 | Z26: 80.13
D27: Potential Balance | K27: 77 | AA27: =Z26*Z25 -> 92550.15
D28: Not so liquid | N28: Actual | O28: 31st Dec | P28: 31st Dec | Q28: 31st Dec | R28: 31st Dec | S28: 31st Dec | T28: 31st Dec | Z28: 1.5 | AA28: =AA27/Z28 -> 61700.1
D29: Aston | E29: Sold | G29: 0 | O29: 2015 | P29: 2016 | Q29: 2017 | R29: 2018 | S29: 2019 | T29: 2020 | U29: =T29+1 -> 2021
D30: Golf R | G30: 15000 | N30: Value | O30: 164433.05 | P30: 248589.4 | Q30: 314989.19 | R30: 335945 | S30: 336562 | T30: 374989.19
D31: Motor Bike | G31: 2000 | O31: 0 | P31: 0 | S31: 30000 | T31: 7000
G32: =SUM(G29:G31) -> 17000 | N32: Santandar | O32: 29028
N33: Total | O33: 193461.05 | P33: 248589.4 | Q33: 314989.19 | R33: 335945 | S33: 374989.19 | T33: 381989.19
D34: Less CC Debit | P34: 55128.35 | Q34: 66399.786 | R34: =R33-Q33 -> 20955.812
D36: Sub Total | G36: =G27+G32-G34 -> 17000 | N36: Q1 | P36: 282432.89 | Q36: 33843.485 | R36: 8687 | S36: 120736 | Z36: phil | AA36: 1500
N37: Q2 | P37: 294892.7 | Q37: 12459.809 | R37: 5697 | S37: 43735
D38: Tied Assetts | G38: =M25 -> 157500 | N38: Q3 | P38: 310690.69 | Q38: 15797.999 | R38: 37050 | S38: -7000
N39: Q4 | P39: 314989.19 | Q39: 4298.4936 | R39: -31361 | S39: 11634
D40: House | G40: 360000 | Q40: 66399.786 | R40: =SUM(R36:R39) -> 20073 | S40: =SUM(S36:S39) -> 169105
D41: less mortgage | G41: =G40 -> 360000
N42: Budget | O42: 31st Dec | P42: 31st Dec | Q42: 31st Dec | R42: 31st Dec | S42: 31st Dec | T42: 31st Dec | Z42: RN Pension
D43: Nett Worth | G43: =G41+G38+G36 -> 534500 | O43: 2015 | P43: 2016 | Q43: 2017 | R43: 2018 | S43: 2019 | T43: 2020 | Z43: Nissan | AA43: GSR Capital
N44: Base | O44: 105896.15 | P44: 163396.15 | Q44: 193396.15 | R44: 223396.15 | S44: 253396.15 | T44: 283396.15
N45: Save | O45: 30000 | P45: 30000 | Q45: 30000 | R45: 30000 | S45: 30000 | T45: 30000
N46: Extra | O46: 27500
N47: Total | O47: 163396.15 | P47: 193396.15 | Q47: 223396.15 | R47: 253396.15 | S47: 283396.15 | T47: 313396.15
T48: =T47-P33 -> 64806.752

Sheet 31-03-23
A1: 201
D2: Liquid Assests | G2: Read This | J2: Tied Assests | N2: 524438 | O2: b
D3: Prod | E3: Where | F3: Who | G3: 45016 | H3: 44985 | J3: Prod | K3: Where | L3: Who | M3: Amount | Q3: At Risk | R3: Not a Risk - Cash
B4: =488+743 -> 1231 | D4: ISA | E4: Ford | F4: JG | G4: 55800 | H4: =56231 -> 56231 | J4: Family Loans | Q4: =#REF!-R4 -> #REF! | R4: =SUM(#REF!) -> #REF! | T4: 130 | V4: 102.8 | W4: Share Price
B5: =504+803 -> 1307 | D5: ISA | E5: Ford | F5: MG | G5: 55800 | H5: =56231 -> 56231 | J5: Faye | M5: 22000 | P5: this is 17k + 5K | T5: 71 | V5: 1.125 | W5: Exchange | AE5: NSI | AF5: 100000
D6: FundSmith | G6: 9970 | H6: 9609 | J6: Nik | M6: 5000 | N6: 155K | P6: Med | Q6: =#REF!+#REF!+#REF!+#REF!+#REF! -> #REF! | T6: =T4-T5 -> 59 | AE6: Share | AF6: 85000
C7: * | D7: Hargrevaes Lansdown | G7: 882 | H7: 883 | J7: ECC | M7: 2500 | P7: High | Q7: =SUM(#REF!) -> #REF!
C8: * | D8: Intractive Investor | G8: 7039 | H8: 7257 | J8: Les and Jon | M8: 20000
C9: * | D9: JG ClearWaterCapital | G9: 16541 | H9: 16103 | J9: Phil | M9: 1500
C10: * | D10: MG ClearWaterCapital inc ISA | G10: 7840 | H10: 1970 | M10: =SUM(M5:M9) -> 51000
D11: Current account - Inv, Currt and Holid | E11: Nat West Invest/Holiday - Not EX, Not Prop, Not Current below 4K | G11: 10000 | H11: 11500 | J11: Cars | P11: =170114-(2*64563) -> 40988
D12: Premium Bonds | E12: Post Office | F12: JG | G12: 50000 | H12: 50000 | J12: MG | M12: 9000 | R12: =14514*2 -> 29028 | AE12: Invest | AF12: 40000
D13: Premium Bonds | E13: Post Office | F13: BH | J13: Golf | AF13: =SUM(AF5:AF12) -> 225000
D14: Premium Bonds | E14: Post Office | F14: FG | G14: 50000 | H14: 50000 | J14: Yeti | M14: 11000
C15: 105.06 | D15: Premium Bonds | E15: Post Office | F15: MG | G15: 50000 | H15: 50000 | M15: =SUM(M12:M14) -> 20000 | Q15: 81287
C16: 567 | D16: EDSP | E16: equateplus.com | F16: MG | G16: 57859 | H16: 53426 | J16: Rented Properties | Q16: =#REF!*2 -> #REF!
C17: 77.04 | D17: Move SAP | E17: III ( both JG and MG) | F17: MG | G17: 7809 | H17: 5452 | J17: House | K17: 2bed | M17: =38000+1500+2500 -> 42000 | Q17: =Q15-Q16 -> #REF! | X17: =SUM(A17:A19) -> 597 | Y17: =X17*V4 -> 61371.6
C18: 1312 | D18: OWN SAP | E18: equateplus.com | F18: MG | G18: 133769 | H18: 121989 | J18: House | K18: 3bed | M18: =38000+1500+2500+2500 -> 44500
A19: 597 | B19: 555 | C19: 992 | J19: Total | M19: =SUM(M17:M18) -> 86500 | N19: 73707
A20: 2011 | C20: 99 | D20: SAP Shares | E20: 1 free | F20: MG | J20: SAP Shares | K20: 1 free | N20: 42156 | P20: 37666 | W20: =388*70/1.43 -> 18993.007
A21: 2012 | C21: 96 | D21: SAP Shares | E21: 5 p 3y 3g | F21: MG | J21: SAP Shares | K21: 5 p 3y 3g | N21: 41791 | P21: 35143
A22: 2013 | C22: 87 | D22: SAP Shares | E22: B3K3G1 | F22: MG | J22: SAP Shares | K22: B3K3G1 | N22: 42583
M23: =SUM(M20:M22) -> 0
D25: Total | G25: =SUM(G4:G18) -> 513309 | H25: =SUM(H4:H18) -> 490651 | I25: =G25-H25 -> 22658 | M25: =M10+M19+M15 -> 157500 | Z25: 1155
Q26: 900 | Z26: 80.13
D27: Potential Balance | K27: 77 | AA27: =Z26*Z25 -> 92550.15
D28: Not so liquid | N28: Actual | O28: 31st Dec | P28: 31st Dec | Q28: 31st Dec | R28: 31st Dec | S28: 31st Dec | T28: 31st Dec | Z28: 1.5 | AA28: =AA27/Z28 -> 61700.1
D29: Aston | E29: Sold | G29: 0 | O29: 2015 | P29: 2016 | Q29: 2017 | R29: 2018 | S29: 2019 | T29: 2020 | U29: =T29+1 -> 2021
D30: Golf R | G30: 15000 | N30: Value | O30: 164433.05 | P30: 248589.4 | Q30: 314989.19 | R30: 335945 | S30: 336562 | T30: 374989.19
D31: Motor Bike | G31: 2000 | O31: 0 | P31: 0 | S31: 30000 | T31: 7000
G32: =SUM(G29:G31) -> 17000 | N32: Santandar | O32: 29028
N33: Total | O33: 193461.05 | P33: 248589.4 | Q33: 314989.19 | R33: 335945 | S33: 374989.19 | T33: 381989.19
D34: Less CC Debit | P34: 55128.35 | Q34: 66399.786 | R34: =R33-Q33 -> 20955.812
D36: Sub Total | G36: =G27+G32-G34 -> 17000 | N36: Q1 | P36: 282432.89 | Q36: 33843.485 | R36: 8687 | S36: 120736 | Z36: phil | AA36: 1500
N37: Q2 | P37: 294892.7 | Q37: 12459.809 | R37: 5697 | S37: 43735
D38: Tied Assetts | G38: =M25 -> 157500 | N38: Q3 | P38: 310690.69 | Q38: 15797.999 | R38: 37050 | S38: -7000
N39: Q4 | P39: 314989.19 | Q39: 4298.4936 | R39: -31361 | S39: 11634
D40: House | G40: 360000 | Q40: 66399.786 | R40: =SUM(R36:R39) -> 20073 | S40: =SUM(S36:S39) -> 169105
D41: less mortgage | G41: =G40 -> 360000
N42: Budget | O42: 31st Dec | P42: 31st Dec | Q42: 31st Dec | R42: 31st Dec | S42: 31st Dec | T42: 31st Dec | Z42: RN Pension
D43: Nett Worth | G43: =G41+G38+G36 -> 534500 | O43: 2015 | P43: 2016 | Q43: 2017 | R43: 2018 | S43: 2019 | T43: 2020 | Z43: Nissan | AA43: GSR Capital
N44: Base | O44: 105896.15 | P44: 163396.15 | Q44: 193396.15 | R44: 223396.15 | S44: 253396.15 | T44: 283396.15
N45: Save | O45: 30000 | P45: 30000 | Q45: 30000 | R45: 30000 | S45: 30000 | T45: 30000
N46: Extra | O46: 27500
N47: Total | O47: 163396.15 | P47: 193396.15 | Q47: 223396.15 | R47: 253396.15 | S47: 283396.15 | T47: 313396.15
T48: =T47-P33 -> 64806.752

Sheet 28-04-23
A1: 201
D2: Liquid Assests | G2: Read This | J2: Tied Assests | N2: 524438 | O2: b
D3: Prod | E3: Where | F3: Who | G3: 45044 | H3: 45016 | J3: Prod | K3: Where | L3: Who | M3: Amount | Q3: At Risk | R3: Not a Risk - Cash
B4: =488+743 -> 1231 | D4: ISA | E4: Ford | F4: JG | G4: 56077 | H4: 55800 | J4: Family Loans | Q4: =#REF!-R4 -> #REF! | R4: =SUM(#REF!) -> #REF! | T4: 130 | V4: 102.8 | W4: Share Price
B5: =504+803 -> 1307 | D5: ISA | E5: Ford | F5: MG | G5: 56077 | H5: 55800 | J5: Faye | M5: 22000 | P5: this is 17k + 5K | T5: 71 | V5: 1.125 | W5: Exchange | AE5: NSI | AF5: 100000
D6: FundSmith | G6: 10296 | H6: 9970 | J6: Nik | M6: 5000 | N6: 155K | P6: Med | Q6: =#REF!+#REF!+#REF!+#REF!+#REF! -> #REF! | T6: =T4-T5 -> 59 | AE6: Share | AF6: 85000
C7: * | D7: Hargrevaes Lansdown | G7: 849 | H7: 882 | J7: ECC | M7: 2500 | P7: High | Q7: =SUM(#REF!) -> #REF!
C8: * | D8: Intractive Investor | G8: 7114 | H8: 7039 | J8: Les and Jon | M8: 20000
C9: * | D9: JG ClearWaterCapital | G9: 19486 | H9: 16541 | J9: Phil | M9: 1500
C10: * | D10: MG ClearWaterCapital inc ISA | G10: =13259+2986 -> 16245 | H10: 7840 | M10: =SUM(M5:M9) -> 51000
D11: Current account - Inv, Currt and Holid | E11: Nat West Invest/Holiday - Not EX, Not Prop, Not Current below 4K | G11: 10000 | H11: 10000 | J11: Cars | P11: =170114-(2*64563) -> 40988
D12: Premium Bonds | E12: Post Office | F12: JG | G12: 50000 | H12: 50000 | J12: MG | M12: 9000 | R12: =14514*2 -> 29028 | AE12: Invest | AF12: 40000
D13: Premium Bonds | E13: Post Office | F13: BH | J13: Golf | AF13: =SUM(AF5:AF12) -> 225000
D14: Premium Bonds | E14: Post Office | F14: FG | G14: 50000 | H14: 50000 | J14: Yeti | M14: 11000
C15: 105.06 | D15: Premium Bonds | E15: Post Office | F15: MG | G15: 50000 | H15: 50000 | M15: =SUM(M12:M14) -> 20000 | Q15: 81287
C16: 567 | D16: EDSP | E16: equateplus.com | F16: MG | G16: 61171 | H16: 57859 | J16: Rented Properties | Q16: =#REF!*2 -> #REF!
C17: 77.04 | D17: Move SAP | E17: III ( both JG and MG) | F17: MG | G17: 8342 | H17: 7809 | J17: House | K17: 2bed | M17: =38000+1500+2500 -> 42000 | Q17: =Q15-Q16 -> #REF! | X17: =SUM(A17:A19) -> 597 | Y17: =X17*V4 -> 61371.6
C18: 1312 | D18: OWN SAP | E18: equateplus.com | F18: MG | G18: 143083 | H18: 133769 | J18: House | K18: 3bed | M18: =38000+1500+2500+2500 -> 44500
A19: 597 | B19: 555 | C19: 992 | J19: Total | M19: =SUM(M17:M18) -> 86500 | N19: 73707
A20: 2011 | C20: 99 | D20: SAP Shares | E20: 1 free | F20: MG | J20: SAP Shares | K20: 1 free | N20: 42156 | P20: 37666 | W20: =388*70/1.43 -> 18993.007
A21: 2012 | C21: 96 | D21: SAP Shares | E21: 5 p 3y 3g | F21: MG | J21: SAP Shares | K21: 5 p 3y 3g | N21: 41791 | P21: 35143
A22: 2013 | C22: 87 | D22: SAP Shares | E22: B3K3G1 | F22: MG | J22: SAP Shares | K22: B3K3G1 | N22: 42583
M23: =SUM(M20:M22) -> 0
D25: Total | G25: =SUM(G4:G18) -> 538740 | H25: =SUM(H4:H18) -> 513309 | I25: =G25-H25 -> 25431 | M25: =M10+M19+M15 -> 157500 | Z25: 1155
Q26: 900 | Z26: 80.13
D27: Potential Balance | K27: 77 | AA27: =Z26*Z25 -> 92550.15
D28: Not so liquid | N28: Actual | O28: 31st Dec | P28: 31st Dec | Q28: 31st Dec | R28: 31st Dec | S28: 31st Dec | T28: 31st Dec | Z28: 1.5 | AA28: =AA27/Z28 -> 61700.1
D29: Aston | E29: Sold | G29: 0 | O29: 2015 | P29: 2016 | Q29: 2017 | R29: 2018 | S29: 2019 | T29: 2020 | U29: =T29+1 -> 2021
D30: Golf R | G30: 15000 | N30: Value | O30: 164433.05 | P30: 248589.4 | Q30: 314989.19 | R30: 335945 | S30: 336562 | T30: 374989.19
D31: Motor Bike | G31: 2000 | O31: 0 | P31: 0 | S31: 30000 | T31: 7000
G32: =SUM(G29:G31) -> 17000 | N32: Santandar | O32: 29028
N33: Total | O33: 193461.05 | P33: 248589.4 | Q33: 314989.19 | R33: 335945 | S33: 374989.19 | T33: 381989.19
D34: Less CC Debit | P34: 55128.35 | Q34: 66399.786 | R34: =R33-Q33 -> 20955.812
D36: Sub Total | G36: =G27+G32-G34 -> 17000 | N36: Q1 | P36: 282432.89 | Q36: 33843.485 | R36: 8687 | S36: 120736 | Z36: phil | AA36: 1500
N37: Q2 | P37: 294892.7 | Q37: 12459.809 | R37: 5697 | S37: 43735
D38: Tied Assetts | G38: =M25 -> 157500 | N38: Q3 | P38: 310690.69 | Q38: 15797.999 | R38: 37050 | S38: -7000
N39: Q4 | P39: 314989.19 | Q39: 4298.4936 | R39: -31361 | S39: 11634
D40: House | G40: 360000 | Q40: 66399.786 | R40: =SUM(R36:R39) -> 20073 | S40: =SUM(S36:S39) -> 169105
D41: less mortgage | G41: =G40 -> 360000
N42: Budget | O42: 31st Dec | P42: 31st Dec | Q42: 31st Dec | R42: 31st Dec | S42: 31st Dec | T42: 31st Dec | Z42: RN Pension
D43: Nett Worth | G43: =G41+G38+G36 -> 534500 | O43: 2015 | P43: 2016 | Q43: 2017 | R43: 2018 | S43: 2019 | T43: 2020 | Z43: Nissan | AA43: GSR Capital
N44: Base | O44: 105896.15 | P44: 163396.15 | Q44: 193396.15 | R44: 223396.15 | S44: 253396.15 | T44: 283396.15
N45: Save | O45: 30000 | P45: 30000 | Q45: 30000 | R45: 30000 | S45: 30000 | T45: 30000
N46: Extra | O46: 27500
N47: Total | O47: 163396.15 | P47: 193396.15 | Q47: 223396.15 | R47: 253396.15 | S47: 283396.15 | T47: 313396.15
T48: =T47-P33 -> 64806.752

Sheet 31-05-23
A1: 201
D2: Liquid Assests | G2: Read This | J2: Tied Assests | N2: 524438 | O2: b
D3: Prod | E3: Where | F3: Who | G3: 45044 | H3: 45044 | J3: Prod | K3: Where | L3: Who | M3: Amount | Q3: At Risk | R3: Not a Risk - Cash
B4: =488+743 -> 1231 | D4: ISA | E4: Ford | F4: JG | G4: =35848+22319 -> 58167 | H4: 56077 | J4: Family Loans | Q4: =#REF!-R4 -> #REF! | R4: =SUM(#REF!) -> #REF! | T4: 130 | V4: 102.8 | W4: Share Price
B5: =504+803 -> 1307 | D5: ISA | E5: Ford | F5: MG | G5: =33941+22319 -> 56260 | H5: 56077 | J5: Faye | M5: 22000 | P5: this is 17k + 5K | T5: 71 | V5: 1.125 | W5: Exchange | AE5: NSI | AF5: 100000
D6: FundSmith | G6: 9954 | H6: 10296 | J6: Nik | M6: 5000 | N6: 155K | P6: Med | Q6: =#REF!+#REF!+#REF!+#REF!+#REF! -> #REF! | T6: =T4-T5 -> 59 | AE6: Share | AF6: 85000
C7: * | D7: Hargrevaes Lansdown | G7: 845 | H7: 849 | J7: ECC | M7: 2500 | P7: High | Q7: =SUM(#REF!) -> #REF!
C8: * | D8: Intractive Investor | G8: 6470 | H8: 7114 | J8: Les and Jon | M8: 20000
C9: * | D9: JG ClearWaterCapital | G9: 17621 | H9: 19486 | J9: Phil | M9: 1500
C10: * | D10: MG ClearWaterCapital inc ISA | G10: =10230+1794 -> 12024 | H10: =13259+2986 -> 16245 | M10: =SUM(M5:M9) -> 51000
D11: Current account - Inv, Currt and Holid | E11: Nat West Invest/Holiday - Not EX, Not Prop, Not Current below 4K | G11: 10000 | H11: 10000 | J11: Cars | P11: =170114-(2*64563) -> 40988
D12: Premium Bonds | E12: Post Office | F12: JG | G12: 50000 | H12: 50000 | J12: MG | M12: 9000 | R12: =14514*2 -> 29028 | AE12: Invest | AF12: 40000
D13: Premium Bonds | E13: Post Office | F13: BH | J13: Golf | AF13: =SUM(AF5:AF12) -> 225000
D14: Premium Bonds | E14: Post Office | F14: FG | G14: 50000 | H14: 50000 | J14: Yeti | M14: 11000
C15: 105.06 | D15: Premium Bonds | E15: Post Office | F15: MG | G15: 50000 | H15: 50000 | M15: =SUM(M12:M14) -> 20000 | Q15: 81287
C16: 574 | D16: EDSP | E16: equateplus.com | F16: MG | G16: 60400 | H16: 61171 | J16: Rented Properties | Q16: =#REF!*2 -> #REF!
C17: 78.37 | D17: Move SAP | E17: III ( both JG and MG) | F17: MG | G17: 8236 | H17: 8342 | J17: House | K17: 2bed | M17: =38000+1500+2500+3317 -> 45317 | Q17: =Q15-Q16 -> #REF! | X17: =SUM(A17:A19) -> 597 | Y17: =X17*V4 -> 61371.6
C18: 1359 | D18: OWN SAP | E18: equateplus.com | F18: MG | G18: 142895 | H18: 143083 | J18: House | K18: 3bed | M18: =38000+1500+2500+2500 -> 44500
A19: 597 | B19: 555 | C19: 992 | J19: Total | M19: =SUM(M17:M18) -> 89817 | N19: 73707
A20: 2011 | C20: 99 | D20: SAP Shares | E20: 1 free | F20: MG | J20: SAP Shares | K20: 1 free | N20: 42156 | P20: 37666 | W20: =388*70/1.43 -> 18993.007
A21: 2012 | C21: 96 | D21: SAP Shares | E21: 5 p 3y 3g | F21: MG | J21: SAP Shares | K21: 5 p 3y 3g | N21: 41791 | P21: 35143
A22: 2013 | C22: 87 | D22: SAP Shares | E22: B3K3G1 | F22: MG | J22: SAP Shares | K22: B3K3G1 | N22: 42583
M23: =SUM(M20:M22) -> 0
D25: Total | G25: =SUM(G4:G18) -> 532872 | H25: =SUM(H4:H18) -> 538740 | I25: =G25-H25 -> -5868 | M25: =M10+M19+M15 -> 160817 | Z25: 1155
Q26: 900 | Z26: 80.13
D27: Potential Balance | K27: 77 | AA27: =Z26*Z25 -> 92550.15
D28: Not so liquid | N28: Actual | O28: 31st Dec | P28: 31st Dec | Q28: 31st Dec | R28: 31st Dec | S28: 31st Dec | T28: 31st Dec | Z28: 1.5 | AA28: =AA27/Z28 -> 61700.1
D29: Aston | E29: Sold | G29: 0 | O29: 2015 | P29: 2016 | Q29: 2017 | R29: 2018 | S29: 2019 | T29: 2020 | U29: =T29+1 -> 2021
D30: Golf R | G30: 15000 | N30: Value | O30: 164433.05 | P30: 248589.4 | Q30: 314989.19 | R30: 335945 | S30: 336562 | T30: 374989.19
D31: Motor Bike | G31: 2000 | O31: 0 | P31: 0 | S31: 30000 | T31: 7000
G32: =SUM(G29:G31) -> 17000 | N32: Santandar | O32: 29028
N33: Total | O33: 193461.05 | P33: 248589.4 | Q33: 314989.19 | R33: 335945 | S33: 374989.19 | T33: 381989.19
D34: Less CC Debit | P34: 55128.35 | Q34: 66399.786 | R34: =R33-Q33 -> 20955.812
D36: Sub Total | G36: =G27+G32-G34 -> 17000 | N36: Q1 | P36: 282432.89 | Q36: 33843.485 | R36: 8687 | S36: 120736 | Z36: phil | AA36: 1500
N37: Q2 | P37: 294892.7 | Q37: 12459.809 | R37: 5697 | S37: 43735
D38: Tied Assetts | G38: =M25 -> 160817 | N38: Q3 | P38: 310690.69 | Q38: 15797.999 | R38: 37050 | S38: -7000
N39: Q4 | P39: 314989.19 | Q39: 4298.4936 | R39: -31361 | S39: 11634
D40: House | G40: 360000 | Q40: 66399.786 | R40: =SUM(R36:R39) -> 20073 | S40: =SUM(S36:S39) -> 169105
D41: less mortgage | G41: =G40 -> 360000
N42: Budget | O42: 31st Dec | P42: 31st Dec | Q42: 31st Dec | R42: 31st Dec | S42: 31st Dec | T42: 31st Dec | Z42: RN Pension
D43: Nett Worth | G43: =G41+G38+G36 -> 537817 | O43: 2015 | P43: 2016 | Q43: 2017 | R43: 2018 | S43: 2019 | T43: 2020 | Z43: Nissan | AA43: GSR Capital
N44: Base | O44: 105896.15 | P44: 163396.15 | Q44: 193396.15 | R44: 223396.15 | S44: 253396.15 | T44: 283396.15
N45: Save | O45: 30000 | P45: 30000 | Q45: 30000 | R45: 30000 | S45: 30000 | T45: 30000
N46: Extra | O46: 27500
N47: Total | O47: 163396.15 | P47: 193396.15 | Q47: 223396.15 | R47: 253396.15 | S47: 283396.15 | T47: 313396.15
T48: =T47-P33 -> 64806.752

Sheet 30-06-23
A1: 201
D2: Liquid Assests | G2: Read This | J2: Tied Assests | N2: 524438 | O2: b
D3: Prod | E3: Where | F3: Who | G3: 45107 | H3: 45077 | J3: Prod | K3: Where | L3: Who | M3: Amount | Q3: At Risk | R3: Not a Risk - Cash
B4: =488+743 -> 1231 | D4: ISA | E4: Ford | F4: JG | G4: =(36948+34043+44866)/2 -> 57928.5 | H4: =35848+22319 -> 58167 | J4: Family Loans | Q4: =#REF!-R4 -> #REF! | R4: =SUM(#REF!) -> #REF! | T4: 130 | V4: 102.8 | W4: Share Price
B5: =504+803 -> 1307 | D5: ISA | E5: Ford | F5: MG | G5: =(36948+34043+44866)/2 -> 57928.5 | H5: =33941+22319 -> 56260 | J5: Faye | M5: 22000 | P5: this is 17k + 5K | T5: 71 | V5: 1.125 | W5: Exchange | AE5: NSI | AF5: 100000
D6: FundSmith | G6: 10117 | H6: 9954 | J6: Nik | M6: 5000 | N6: 155K | P6: Med | Q6: =#REF!+#REF!+#REF!+#REF!+#REF! -> #REF! | T6: =T4-T5 -> 59 | AE6: Share | AF6: 85000
C7: * | D7: Hargrevaes Lansdown | G7: 833 | H7: 845 | J7: ECC | M7: 2500 | P7: High | Q7: =SUM(#REF!) -> #REF!
C8: * | D8: Intractive Investor | G8: 6775 | H8: 6470 | J8: Les and Jon | M8: 20000
C9: * | D9: JG ClearWaterCapital | G9: 17621 | H9: 17621 | J9: Phil | M9: 1500
C10: * | D10: MG ClearWaterCapital inc ISA | G10: =10230+1794 -> 12024 | H10: =10230+1794 -> 12024 | M10: =SUM(M5:M9) -> 51000
D11: Current account - Inv, Currt and Holid | E11: Nat West Invest/Holiday - Not EX, Not Prop, Not Current below 4K | G11: 10000 | H11: 10000 | J11: Cars | P11: =170114-(2*64563) -> 40988
D12: Premium Bonds | E12: Post Office | F12: JG | G12: 50000 | H12: 50000 | J12: MG | M12: 9000 | R12: =14514*2 -> 29028 | AE12: Invest | AF12: 40000
D13: Premium Bonds | E13: Post Office | F13: BH | J13: Golf | AF13: =SUM(AF5:AF12) -> 225000
D14: Premium Bonds | E14: Post Office | F14: FG | G14: 50000 | H14: 50000 | J14: Yeti | M14: 11000
C15: 105.06 | D15: Premium Bonds | E15: Post Office | F15: MG | G15: 50000 | H15: 50000 | M15: =SUM(M12:M14) -> 20000 | Q15: 81287
C16: 574 | D16: EDSP | E16: equateplus.com | F16: MG | G16: 62099 | H16: 60400 | J16: Rented Properties | Q16: =#REF!*2 -> #REF!
C17: 97 | D17: Move SAP | E17: III ( both JG and MG) | F17: MG | G17: 10750 | H17: 8236 | J17: House | K17: 2bed | M17: =38000+1500+2500+3317 -> 45317 | Q17: =Q15-Q16 -> #REF! | X17: =SUM(A17:A19) -> 597 | Y17: =X17*V4 -> 61371.6
C18: 1357 | D18: OWN SAP | E18: equateplus.com | F18: MG | G18: 148577 | H18: 142895 | J18: House | K18: 3bed | M18: =38000+1500+2500+2500 -> 44500
A19: 597 | B19: 555 | C19: 992 | J19: Total | M19: =SUM(M17:M18) -> 89817 | N19: 73707
A20: 2011 | C20: 99 | D20: SAP Shares | E20: 1 free | F20: MG | J20: SAP Shares | K20: 1 free | N20: 42156 | P20: 37666 | W20: =388*70/1.43 -> 18993.007
A21: 2012 | C21: 96 | D21: SAP Shares | E21: 5 p 3y 3g | F21: MG | J21: SAP Shares | K21: 5 p 3y 3g | N21: 41791 | P21: 35143
A22: 2013 | C22: 87 | D22: SAP Shares | E22: B3K3G1 | F22: MG | J22: SAP Shares | K22: B3K3G1 | N22: 42583
M23: =SUM(M20:M22) -> 0
D25: Total | G25: =SUM(G4:G18) -> 544653 | H25: =SUM(H4:H18) -> 532872 | I25: =G25-H25 -> 11781 | M25: =M10+M19+M15 -> 160817 | Z25: 1155
Q26: 900 | Z26: 80.13
D27: Potential Balance | K27: 77 | AA27: =Z26*Z25 -> 92550.15
D28: Not so liquid | N28: Actual | O28: 31st Dec | P28: 31st Dec | Q28: 31st Dec | R28: 31st Dec | S28: 31st Dec | T28: 31st Dec | Z28: 1.5 | AA28: =AA27/Z28 -> 61700.1
D29: Aston | E29: Sold | G29: 0 | O29: 2015 | P29: 2016 | Q29: 2017 | R29: 2018 | S29: 2019 | T29: 2020 | U29: =T29+1 -> 2021
D30: Golf R | G30: 15000 | N30: Value | O30: 164433.05 | P30: 248589.4 | Q30: 314989.19 | R30: 335945 | S30: 336562 | T30: 374989.19
D31: Motor Bike | G31: 2000 | O31: 0 | P31: 0 | S31: 30000 | T31: 7000
G32: =SUM(G29:G31) -> 17000 | N32: Santandar | O32: 29028
N33: Total | O33: 193461.05 | P33: 248589.4 | Q33: 314989.19 | R33: 335945 | S33: 374989.19 | T33: 381989.19
D34: Less CC Debit | P34: 55128.35 | Q34: 66399.786 | R34: =R33-Q33 -> 20955.812
D36: Sub Total | G36: =G27+G32-G34 -> 17000 | N36: Q1 | P36: 282432.89 | Q36: 33843.485 | R36: 8687 | S36: 120736 | Z36: phil | AA36: 1500
N37: Q2 | P37: 294892.7 | Q37: 12459.809 | R37: 5697 | S37: 43735
D38: Tied Assetts | G38: =M25 -> 160817 | N38: Q3 | P38: 310690.69 | Q38: 15797.999 | R38: 37050 | S38: -7000
N39: Q4 | P39: 314989.19 | Q39: 4298.4936 | R39: -31361 | S39: 11634
D40: House | G40: 360000 | Q40: 66399.786 | R40: =SUM(R36:R39) -> 20073 | S40: =SUM(S36:S39) -> 169105
D41: less mortgage | G41: =G40 -> 360000
N42: Budget | O42: 31st Dec | P42: 31st Dec | Q42: 31st Dec | R42: 31st Dec | S42: 31st Dec | T42: 31st Dec | Z42: RN Pension
D43: Nett Worth | G43: =G41+G38+G36 -> 537817 | O43: 2015 | P43: 2016 | Q43: 2017 | R43: 2018 | S43: 2019 | T43: 2020 | Z43: Nissan | AA43: GSR Capital
N44: Base | O44: 105896.15 | P44: 163396.15 | Q44: 193396.15 | R44: 223396.15 | S44: 253396.15 | T44: 283396.15
N45: Save | O45: 30000 | P45: 30000 | Q45: 30000 | R45: 30000 | S45: 30000 | T45: 30000
N46: Extra | O46: 27500
N47: Total | O47: 163396.15 | P47: 193396.15 | Q47: 223396.15 | R47: 253396.15 | S47: 283396.15 | T47: 313396.15
T48: =T47-P33 -> 64806.752

Sheet 31-07-23
A1: 201
D2: Liquid Assests | G2: Read This | J2: Tied Assests | N2: 524438 | O2: b
D3: Prod | E3: Where | F3: Who | G3: 45138 | H3: 45107 | J3: Prod | K3: Where | L3: Who | M3: Amount | Q3: At Risk | R3: Not a Risk - Cash
B4: =488+743 -> 1231 | D4: ISA | E4: Ford | F4: JG | G4: =36529+22835 -> 59364 | H4: =(36948+34043+44866)/2 -> 57928.5 | J4: Family Loans | Q4: =#REF!-R4 -> #REF! | R4: =SUM(#REF!) -> #REF! | T4: 130 | V4: 102.8 | W4: Share Price
B5: =504+803 -> 1307 | D5: ISA | E5: Ford | F5: MG | G5: =34580+22835 -> 57415 | H5: =(36948+34043+44866)/2 -> 57928.5 | J5: Faye | M5: 22000 | P5: this is 17k + 5K | T5: 71 | V5: 1.125 | W5: Exchange | AE5: NSI | AF5: 100000
D6: FundSmith | G6: 10206 | H6: 10117 | J6: Nik | M6: 5000 | N6: 155K | P6: Med | Q6: =#REF!+#REF!+#REF!+#REF!+#REF! -> #REF! | T6: =T4-T5 -> 59 | AE6: Share | AF6: 85000
C7: * | D7: Hargrevaes Lansdown | G7: 816 | H7: 833 | J7: ECC | M7: 2500 | P7: High | Q7: =SUM(#REF!) -> #REF!
C8: * | D8: Intractive Investor | G8: 7120 | H8: 6775 | J8: Les and Jon | M8: 20000
C9: * | D9: JG ClearWaterCapital | G9: 17320 | H9: 17621 | J9: Phil | M9: 1500
C10: * | D10: MG ClearWaterCapital inc ISA | G10: 10856 | H10: =10230+1794 -> 12024 | M10: =SUM(M5:M9) -> 51000
D11: Current account - Inv, Currt and Holid | E11: Nat West Invest/Holiday - Not EX, Not Prop, Not Current below 4K | G11: 10000 | H11: 10000 | J11: Cars | P11: =170114-(2*64563) -> 40988
D12: Premium Bonds | E12: Post Office | F12: JG | G12: 50000 | H12: 50000 | J12: MG | M12: 9000 | R12: =14514*2 -> 29028 | AE12: Invest | AF12: 40000
D13: Premium Bonds | E13: Post Office | F13: BH | J13: Golf | AF13: =SUM(AF5:AF12) -> 225000
D14: Premium Bonds | E14: Post Office | F14: FG | G14: 50000 | H14: 50000 | J14: Yeti | M14: 11000
C15: 105.06 | D15: Premium Bonds | E15: Post Office | F15: MG | G15: 50000 | H15: 50000 | M15: =SUM(M12:M14) -> 20000 | Q15: 81287
C16: 574 | D16: EDSP | E16: equateplus.com | F16: MG | G16: 61262 | H16: 62099 | J16: Rented Properties | Q16: =#REF!*2 -> #REF!
C17: 97 | D17: Move SAP | E17: III ( both JG and MG) | F17: MG | G17: 10428 | H17: 10750 | J17: House | K17: 2bed | M17: =38000+1500+2500+3317 -> 45317 | Q17: =Q15-Q16 -> #REF! | X17: =SUM(A17:A19) -> 597 | Y17: =X17*V4 -> 61371.6
C18: 1357 | D18: OWN SAP | E18: equateplus.com | F18: MG | G18: 148236 | H18: 148577 | J18: House | K18: 3bed | M18: =38000+1500+2500+2500 -> 44500
A19: 597 | B19: 555 | C19: 992 | J19: Total | M19: =SUM(M17:M18) -> 89817 | N19: 73707
A20: 2011 | C20: 99 | D20: SAP Shares | E20: 1 free | F20: MG | J20: SAP Shares | K20: 1 free | N20: 42156 | P20: 37666 | W20: =388*70/1.43 -> 18993.007
A21: 2012 | C21: 96 | D21: SAP Shares | E21: 5 p 3y 3g | F21: MG | J21: SAP Shares | K21: 5 p 3y 3g | N21: 41791 | P21: 35143
A22: 2013 | C22: 87 | D22: SAP Shares | E22: B3K3G1 | F22: MG | J22: SAP Shares | K22: B3K3G1 | N22: 42583
M23: =SUM(M20:M22) -> 0
D25: Total | G25: =SUM(G4:G18) -> 543023 | H25: =SUM(H4:H18) -> 544653 | I25: =G25-H25 -> -1630 | M25: =M10+M19+M15 -> 160817 | Z25: 1155
Q26: 900 | Z26: 80.13
D27: Potential Balance | K27: 77 | AA27: =Z26*Z25 -> 92550.15
D28: Not so liquid | N28: Actual | O28: 31st Dec | P28: 31st Dec | Q28: 31st Dec | R28: 31st Dec | S28: 31st Dec | T28: 31st Dec | Z28: 1.5 | AA28: =AA27/Z28 -> 61700.1
D29: Aston | E29: Sold | G29: 0 | O29: 2015 | P29: 2016 | Q29: 2017 | R29: 2018 | S29: 2019 | T29: 2020 | U29: =T29+1 -> 2021
D30: Golf R | G30: 15000 | N30: Value | O30: 164433.05 | P30: 248589.4 | Q30: 314989.19 | R30: 335945 | S30: 336562 | T30: 374989.19
D31: Motor Bike | G31: 2000 | O31: 0 | P31: 0 | S31: 30000 | T31: 7000
G32: =SUM(G29:G31) -> 17000 | N32: Santandar | O32: 29028
N33: Total | O33: 193461.05 | P33: 248589.4 | Q33: 314989.19 | R33: 335945 | S33: 374989.19 | T33: 381989.19
D34: Less CC Debit | P34: 55128.35 | Q34: 66399.786 | R34: =R33-Q33 -> 20955.812
D36: Sub Total | G36: =G27+G32-G34 -> 17000 | N36: Q1 | P36: 282432.89 | Q36: 33843.485 | R36: 8687 | S36: 120736 | Z36: phil | AA36: 1500
N37: Q2 | P37: 294892.7 | Q37: 12459.809 | R37: 5697 | S37: 43735
D38: Tied Assetts | G38: =M25 -> 160817 | N38: Q3 | P38: 310690.69 | Q38: 15797.999 | R38: 37050 | S38: -7000
N39: Q4 | P39: 314989.19 | Q39: 4298.4936 | R39: -31361 | S39: 11634
D40: House | G40: 360000 | Q40: 66399.786 | R40: =SUM(R36:R39) -> 20073 | S40: =SUM(S36:S39) -> 169105
D41: less mortgage | G41: =G40 -> 360000
N42: Budget | O42: 31st Dec | P42: 31st Dec | Q42: 31st Dec | R42: 31st Dec | S42: 31st Dec | T42: 31st Dec | Z42: RN Pension
D43: Nett Worth | G43: =G41+G38+G36 -> 537817 | O43: 2015 | P43: 2016 | Q43: 2017 | R43: 2018 | S43: 2019 | T43: 2020 | Z43: Nissan | AA43: GSR Capital
N44: Base | O44: 105896.15 | P44: 163396.15 | Q44: 193396.15 | R44: 223396.15 | S44: 253396.15 | T44: 283396.15
N45: Save | O45: 30000 | P45: 30000 | Q45: 30000 | R45: 30000 | S45: 30000 | T45: 30000
N46: Extra | O46: 27500
N47: Total | O47: 163396.15 | P47: 193396.15 | Q47: 223396.15 | R47: 253396.15 | S47: 283396.15 | T47: 313396.15
T48: =T47-P33 -> 64806.752

Sheet 31-08-23
A1: 201
D2: Liquid Assests | G2: Read This | J2: Tied Assests | N2: 524438 | O2: b
D3: Prod | E3: Where | F3: Who | G3: 45169 | H3: 45138 | J3: Prod | K3: Where | L3: Who | M3: Amount | Q3: At Risk | R3: Not a Risk - Cash
B4: =488+743 -> 1231 | D4: ISA | E4: Ford | F4: JG | G4: =35962+22491 -> 58453 | H4: =36529+22835 -> 59364 | J4: Family Loans | Q4: =#REF!-R4 -> #REF! | R4: =SUM(#REF!) -> #REF! | T4: 130 | V4: 102.8 | W4: Share Price
B5: =504+803 -> 1307 | D5: ISA | E5: Ford | F5: MG | G5: 56575 | H5: =34580+22835 -> 57415 | J5: Faye | M5: 22000 | P5: this is 17k + 5K | T5: 71 | V5: 1.125 | W5: Exchange | AE5: NSI | AF5: 100000
D6: FundSmith | G6: 10128 | H6: 10206 | J6: Nik | M6: 5000 | N6: 155K | P6: Med | Q6: =#REF!+#REF!+#REF!+#REF!+#REF! -> #REF! | T6: =T4-T5 -> 59 | AE6: Share | AF6: 85000
C7: * | D7: Hargrevaes Lansdown | G7: 759 | H7: 816 | J7: ECC | M7: 2500 | P7: High | Q7: =SUM(#REF!) -> #REF!
C8: * | D8: Intractive Investor | G8: 5267 | H8: 7120 | J8: Les and Jon | M8: 20000
C9: * | D9: JG ClearWaterCapital | G9: 18458 | H9: 17320 | J9: Phil | M9: 1500
C10: * | D10: MG ClearWaterCapital inc ISA | G10: 14464 | H10: 10856 | M10: =SUM(M5:M9) -> 51000
D11: Current account - Inv, Currt and Holid | E11: Nat West Invest/Holiday - Not EX, Not Prop, Not Current below 4K | G11: 0 | H11: 10000 | J11: Cars | P11: =170114-(2*64563) -> 40988
D12: Premium Bonds | E12: Post Office | F12: JG | G12: 50000 | H12: 50000 | J12: E-type | M12: 85500 | R12: =14514*2 -> 29028 | AE12: Invest | AF12: 40000
D13: Premium Bonds | E13: Post Office | F13: BH | J13: MG | M13: 9000 | AF13: =SUM(AF5:AF12) -> 225000
D14: Premium Bonds | E14: Post Office | F14: FG | G14: 1000 | H14: 50000 | J14: Golf
C15: 105.06 | D15: Premium Bonds | E15: Post Office | F15: MG | G15: 25000 | H15: 50000 | J15: Yeti | M15: 11000 | Q15: 81287
C16: 574 | D16: EDSP | E16: equateplus.com | F16: MG | G16: 63519 | H16: 61262 | M16: =SUM(M12:M15) -> 105500 | Q16: =#REF!*2 -> #REF!
C17: 97 | D17: Move SAP | E17: III ( both JG and MG) | F17: MG | G17: 10812 | H17: 10428 | J17: Rented Properties | Q17: =Q15-Q16 -> #REF! | X17: =SUM(A17:A19) -> 597 | Y17: =X17*V4 -> 61371.6
C18: 1406 | D18: OWN SAP | E18: equateplus.com | F18: MG | G18: 155429 | H18: 148236 | J18: House | K18: 2bed | M18: =38000+1500+2500+3317 -> 45317
A19: 597 | B19: 555 | C19: 992 | J19: House | K19: 3bed | M19: =38000+1500+2500+2500 -> 44500 | N19: 73707
A20: 2011 | C20: 99 | D20: SAP Shares | E20: 1 free | F20: MG | J20: Total | M20: =SUM(M18:M19) -> 89817 | N20: 42156 | P20: 37666 | W20: =388*70/1.43 -> 18993.007
A21: 2012 | C21: 96 | D21: SAP Shares | E21: 5 p 3y 3g | F21: MG | J21: SAP Shares | K21: 1 free | N21: 41791 | P21: 35143
A22: 2013 | C22: 87 | D22: SAP Shares | E22: B3K3G1 | F22: MG | J22: SAP Shares | K22: 5 p 3y 3g | N22: 42583
J23: SAP Shares | K23: B3K3G1
M24: =SUM(M21:M23) -> 0
D25: Total | G25: =SUM(G4:G18) -> 469864 | H25: =SUM(H4:H24) -> 543023 | I25: =G25-H25 -> -73159 | Z25: 1155
M26: =M10+M20+M16 -> 246317 | Q26: 900 | Z26: 80.13
D27: Potential Balance | K27: 77 | AA27: =Z26*Z25 -> 92550.15
D28: Not so liquid | N28: Actual | O28: 31st Dec | P28: 31st Dec | Q28: 31st Dec | R28: 31st Dec | S28: 31st Dec | T28: 31st Dec | Z28: 1.5 | AA28: =AA27/Z28 -> 61700.1
D29: Aston | E29: Sold | G29: 0 | O29: 2015 | P29: 2016 | Q29: 2017 | R29: 2018 | S29: 2019 | T29: 2020 | U29: =T29+1 -> 2021
D30: Golf R | G30: 15000 | N30: Value | O30: 164433.05 | P30: 248589.4 | Q30: 314989.19 | R30: 335945 | S30: 336562 | T30: 374989.19
D31: Motor Bike | G31: 2000 | O31: 0 | P31: 0 | S31: 30000 | T31: 7000
G32: =SUM(G29:G31) -> 17000 | N32: Santandar | O32: 29028
N33: Total | O33: 193461.05 | P33: 248589.4 | Q33: 314989.19 | R33: 335945 | S33: 374989.19 | T33: 381989.19
D34: Less CC Debit | P34: 55128.35 | Q34: 66399.786 | R34: =R33-Q33 -> 20955.812
D36: Sub Total | G36: =G27+G32-G34 -> 17000 | N36: Q1 | P36: 282432.89 | Q36: 33843.485 | R36: 8687 | S36: 120736 | Z36: phil | AA36: 1500
N37: Q2 | P37: 294892.7 | Q37: 12459.809 | R37: 5697 | S37: 43735
D38: Tied Assetts | G38: =M26 -> 246317 | N38: Q3 | P38: 310690.69 | Q38: 15797.999 | R38: 37050 | S38: -7000
N39: Q4 | P39: 314989.19 | Q39: 4298.4936 | R39: -31361 | S39: 11634
D40: House | G40: 360000 | Q40: 66399.786 | R40: =SUM(R36:R39) -> 20073 | S40: =SUM(S36:S39) -> 169105
D41: less mortgage | G41: =G40 -> 360000
N42: Budget | O42: 31st Dec | P42: 31st Dec | Q42: 31st Dec | R42: 31st Dec | S42: 31st Dec | T42: 31st Dec | Z42: RN Pension
D43: Nett Worth | G43: =G41+G38+G36 -> 623317 | O43: 2015 | P43: 2016 | Q43: 2017 | R43: 2018 | S43: 2019 | T43: 2020 | Z43: Nissan | AA43: GSR Capital
N44: Base | O44: 105896.15 | P44: 163396.15 | Q44: 193396.15 | R44: 223396.15 | S44: 253396.15 | T44: 283396.15
N45: Save | O45: 30000 | P45: 30000 | Q45: 30000 | R45: 30000 | S45: 30000 | T45: 30000
N46: Extra | O46: 27500
N47: Total | O47: 163396.15 | P47: 193396.15 | Q47: 223396.15 | R47: 253396.15 | S47: 283396.15 | T47: 313396.15
T48: =T47-P33 -> 64806.752

Sheet 30-09-23
A1: 201
D2: Liquid Assests | G2: Read This | J2: Tied Assests | N2: 524438 | O2: b
D3: Prod | E3: Where | F3: Who | G3: 45199 | H3: 45169 | J3: Prod | K3: Where | L3: Who | M3: Amount | Q3: At Risk | R3: Not a Risk - Cash
B4: =488+743 -> 1231 | D4: ISA | E4: Ford | F4: JG | G4: =35326+22114 -> 57440 | H4: =35962+22491 -> 58453 | J4: Family Loans | Q4: =#REF!-R4 -> #REF! | R4: =SUM(#REF!) -> #REF! | T4: 130 | V4: 102.8 | W4: Share Price
B5: =504+803 -> 1307 | D5: ISA | E5: Ford | F5: MG | G5: =33481+22114 -> 55595 | H5: 56575 | J5: Faye | M5: 22000 | P5: this is 17k + 5K | T5: 71 | V5: 1.125 | W5: Exchange | AE5: NSI | AF5: 100000
D6: FundSmith | G6: 9938 | H6: 10128 | J6: Nik | M6: 5000 | N6: 155K | P6: Med | Q6: =#REF!+#REF!+#REF!+#REF!+#REF! -> #REF! | T6: =T4-T5 -> 59 | AE6: Share | AF6: 85000
C7: * | D7: Hargrevaes Lansdown | G7: 760 | H7: 759 | J7: ECC | M7: 2500 | P7: High | Q7: =SUM(#REF!) -> #REF!
C8: * | D8: Intractive Investor | G8: 5726 | H8: 5267 | J8: Les and Jon | M8: 20000
C9: * | D9: JG ClearWaterCapital | G9: 16911 | H9: 18458 | J9: Phil | M9: 1500
C10: * | D10: MG ClearWaterCapital inc ISA | G10: 11874 | H10: 14464 | M10: =SUM(M5:M9) -> 51000
D11: Current account - Inv, Currt and Holid | E11: Nat West Invest/Holiday - Not EX, Not Prop, Not Current below 4K | G11: 0 | H11: 0 | J11: Cars | P11: =170114-(2*64563) -> 40988
D12: Premium Bonds | E12: Post Office | F12: JG | G12: 40000 | H12: 50000 | J12: E-type | M12: 85500 | R12: =14514*2 -> 29028 | AE12: Invest | AF12: 40000
D13: Premium Bonds | E13: Post Office | F13: BH | J13: MG | M13: 9000 | AF13: =SUM(AF5:AF12) -> 225000
D14: Premium Bonds | E14: Post Office | F14: FG | G14: 1000 | H14: 1000 | J14: Golf
C15: 105.06 | D15: Premium Bonds | E15: Post Office | F15: MG | G15: 25000 | H15: 25000 | J15: Yeti | M15: 11000 | Q15: 81287
